Workbook

Sheet Analiza_KPA
J1: =22*(7822/365) -> 471.46301
E2: 02.09.1997 | J2: 22.01.2002
B3: No. | C3: DESCRIPTION / PERIOD | D3: 1996 | E3: 1997 | F3: 1998 | G3: 1999 | H3: 2000 | I3: 2001 | J3: 2002 | K3: 2003 | L3: 1996-2003 | M3: 2004 | N3: 2005 | O3: 2006 | P3: 2007 | Q3: 2008 | R3: 2009 | S3: 2010 | T3: 2011 | U3: 2012 | V3: 2013 | W3: 2014 | X3: 2015 | Y3: 2016 | Z3: TOTALI | AA3: VETTING
B4: I | C4: INCOME | D4: =SUM(D5:D10) -> 60154 | E4: =SUM(E5:E10) -> 231024 | F4: =SUM(F5:F10) -> 360525 | G4: =SUM(G5:G10) -> 461249 | H4: =SUM(H5:H10) -> 603437 | I4: =SUM(I5:I10) -> 636075.5 | J4: =SUM(J5:J10) -> 608853.5 | K4: =SUM(K5:K10) -> 765140 | L4: =SUM(L5:L10) -> 3726458 | M4: =SUM(M5:M11) -> 933625 | N4: =SUM(N5:N10) -> 1145795 | O4: =SUM(O5:O10) -> 1093156 | P4: =SUM(P5:P10) -> 1029704 | Q4: =SUM(Q5:Q10) -> 1623856 | R4: =SUM(R5:R10) -> 1349735 | S4: =SUM(S5:S10) -> 1389475 | T4: =SUM(T5:T10) -> 1519983 | U4: =SUM(U5:U10) -> 1568737 | ... Z4: =SUM(Z5:Z10) -> 27337579 | AA4: 175673
B5: 1 | C5: Income of Assessee | D5: ='Te Ardhurat '!D4 -> 60154 | E5: ='Te Ardhurat '!E4 -> 231024 | F5: ='Te Ardhurat '!F4 -> 360525 | G5: ='Te Ardhurat '!G4 -> 390615 | H5: ='Te Ardhurat '!H4 -> 442564 | I5: ='Te Ardhurat '!I4 -> 446705 | J5: ='Te Ardhurat '!J4 -> 414633 | K5: ='Te Ardhurat '!K4 -> 473716 | L5: =SUM(D5:K5) -> 2819936 | M5: ='Te Ardhurat '!L4+'Te Ardhurat '!L5 -> 606194 | N5: ='Te Ardhurat '!M5 -> 818245 | O5: ='Te Ardhurat '!N5 -> 815652 | P5: ='Te Ardhurat '!O5+'Te Ardhurat '!O6 -> 841418 | Q5: ='Te Ardhurat '!P6 -> 905278 | R5: ='Te Ardhurat '!Q6 -> 851469 | S5: ='Te Ardhurat '!R6+'Te Ardhurat '!R7 -> 814286 | T5: ='Te Ardhurat '!S7 -> 942368 | U5: ='Te Ardhurat '!T7 -> 983776 | V5: ='Te Ardhurat '!U7 -> 917794 | W5: ='Te Ardhurat '!V7 -> 1091512 | X5: ='Te Ardhurat '!W7 -> 1123493 | Y5: ='Te Ardhurat '!X7 -> 1170841 | Z5: =SUM(M5:Y5)+K5 -> 12356042 | AA5: 99845
B6: 2 | C6: Income of Spouse | D6: 0 | E6: 0 | F6: 0 | G6: ='Te Ardhurat '!G20+'Te Ardhurat '!G21 -> 70634 | H6: ='Te Ardhurat '!H20+'Te Ardhurat '!H21 -> 160873 | I6: ='Te Ardhurat '!I20+'Te Ardhurat '!I21 -> 189370.5 | J6: ='Te Ardhurat '!J20+'Te Ardhurat '!J21 -> 194220.5 | K6: ='Te Ardhurat '!K20+'Te Ardhurat '!K21 -> 291424 | L6: =SUM(D6:K6) -> 906522 | M6: ='Te Ardhurat '!L20 -> 327431 | N6: ='Te Ardhurat '!M20 -> 327550 | O6: ='Te Ardhurat '!N20 -> 277504 | P6: ='Te Ardhurat '!O22+'Te Ardhurat '!O23 -> 188286 | Q6: ='Te Ardhurat '!P22+'Te Ardhurat '!P23 -> 318578 | R6: ='Te Ardhurat '!Q22+'Te Ardhurat '!Q23 -> 498266 | S6: ='Te Ardhurat '!R22+'Te Ardhurat '!R23 -> 575189 | T6: ='Te Ardhurat '!S22+'Te Ardhurat '!S23 -> 577615 | U6: ='Te Ardhurat '!T22+'Te Ardhurat '!T23 -> 584961 | V6: ='Te Ardhurat '!U22+'Te Ardhurat '!U23 -> 596778 | W6: ='Te Ardhurat '!V22+'Te Ardhurat '!V23 -> 749732 | ... Y6: ='Te Ardhurat '!X22+'Te Ardhurat '!X23 -> 904419 | Z6: =SUM(M6:Y6)+K6 -> 7034347 | AA6: 75828
B7: 3 | C7: Sale of "Mercedes Benz"_09.09.2008 | D7: 0 | E7: 0 | F7: 0 | G7: 0 | H7: 0 | I7: 0 | J7: 0 | K7: 0 | L7: 0 | M7: 0 | N7: 0 | O7: 0 | P7: 0 | Q7: 400000 | R7: 0 | S7: 0 | T7: 0 | U7: 0 | V7: 0 | W7: 0 | X7: 0 | Y7: 0 | Z7: =SUM(M7:Y7)+K7 -> 400000 | AA7: 0
B8: 4 | C8: Down payment for sale of house in K.Kamëz_01.10.2014 | D8: 0 | E8: 0 | F8: 0 | G8: 0 | H8: 0 | I8: 0 | J8: 0 | K8: 0 | L8: 0 | M8: 0 | N8: 0 | O8: 0 | P8: 0 | Q8: 0 | R8: 0 | S8: 0 | T8: 0 | U8: 0 | V8: 0 | W8: =20000*139.87 -> 2797400 | X8: =30000*140.84 -> 4225200 | Y8: 0 | Z8: =SUM(M8:Y8)+K8 -> 7022600
B9: 5 | C9: Sale of "Mercedes Benz"15.03.2016 | D9: 0 | E9: 0 | F9: 0 | G9: 0 | H9: 0 | I9: 0 | J9: 0 | K9: 0 | L9: 0 | M9: 0 | N9: 0 | O9: 0 | P9: 0 | Q9: 0 | R9: 0 | S9: 0 | T9: 0 | U9: 0 | V9: 0 | W9: 0 | X9: 0 | Y9: =3800*138.05 -> 524590 | Z9: =SUM(M9:Y9)+K9 -> 524590 | AA9: 0
B10: 6 | C10: Sale of house in K.Kamëz cont.16.06.2017 | D10: 0 | E10: 0 | F10: 0 | G10: 0 | H10: 0 | I10: 0 | J10: 0 | K10: 0 | L10: 0 | M10: 0 | N10: 0 | O10: 0 | P10: 0 | Q10: 0 | R10: 0 | S10: 0 | T10: 0 | U10: 0 | V10: 0 | W10: 0 | X10: 0 | Y10: 0 | Z10: =SUM(M10:Y10)+K10 -> 0
B11: 7 | C11: Settled from use of agr. land | D11: 0 | E11: 0 | F11: 0 | G11: 0 | H11: 0 | I11: 0 | J11: 0 | K11: 0 | L11: 0 | M11: 0 | N11: 300000 | O11: 100000 | P11: 200000 | Q11: 370000 | R11: 350000 | S11: 470000 | T11: 530000 | U11: 670000 | V11: 540000 | W11: 450000 | X11: 240000 | Y11: 200000 | Z11: =SUM(M11:Y11)+K11 -> 4420000
B13: II | C13: EXPENDITURE | D13: =SUM(D14:D22) -> 39701.64 | E13: =SUM(E14:E22) -> 152475.84 | F13: =SUM(F14:F22) -> 237946.5 | G13: =SUM(G14:G22) -> 257805.9 | H13: =SUM(H14:H22) -> 216000 | I13: =SUM(I14:I22) -> 216000 | J13: =SUM(J14:J22) -> 374984.54 | K13: =SUM(K14:K22) -> 375456 | ... Z13: =SUM(Z14:Z22) -> 11980242 | AA13: 113918.35
B14: 1 | C14: Living expenses | D14: =D5*66% -> 39701.64 | E14: =E5*66% -> 152475.84 | F14: =F5*66% -> 237946.5 | G14: =G5*66% -> 257805.9 | H14: =108000*2 -> 216000 | I14: =H14 -> 216000 | J14: =93864*4-J1 -> 374984.54 | K14: 375456 | L14: =SUM(D14:K14) -> 1870370.4 | M14: 375856 | N14: 438228 | O14: 438228 | P14: 546480 | Q14: 546480 | R14: =546480 -> 546480 | S14: =546480 -> 546480 | T14: =546480 -> 546480 | U14: 564096 | V14: 564096 | W14: 879992 | X14: 897104 | Y14: 940368 | Z14: =SUM(M14:Y14)+K14 -> 8205824 | AA14: 79351.351
B15: 2 | C15: Travel expenses TIMS | D15: 0 | E15: 0 | F15: 0 | G15: 0 | H15: 0 | I15: 0 | J15: 0 | K15: 0 | L15: 0 | M15: 0 | N15: 0 | O15: 0 | P15: 0 | Q15: 3695.475 | R15: 0 | S15: 0 | T15: =TIMS!F6 -> 338835 | U15: 0 | V15: =TIMS!G6 -> 0 | W15: =TIMS!I6 -> 140110 | X15: =TIMS!J6 -> 37165.5 | Y15: =TIMS!K6 -> 31054 | Z15: =SUM(M15:Y15)+K15 -> 550859.97 | AA15: 7977 | AC15: 2196
B16: 3 | C16: Legalization expenses 3-storey house 01.07.2015 | D16: 0 | E16: 0 | F16: 0 | G16: 0 | H16: 0 | I16: 0 | J16: 0 | K16: 0 | L16: 0 | M16: 0 | N16: 0 | O16: 0 | P16: 0 | Q16: 0 | R16: 0 | S16: 0 | T16: 0 | U16: 0 | V16: 0 | W16: 0 | X16: =(500000*0.1)+360000 -> 410000 | Y16: 0 | Z16: =SUM(M16:Y16)+K16 -> 410000
B17: 4 | C17: Exp. on local tax on agr. land | D17: 0 | E17: 0 | F17: 0 | G17: 0 | H17: 0 | I17: 0 | J17: 0 | K17: 0 | L17: 0 | M17: 0 | N17: 0 | O17: 0 | P17: 732 | Q17: 732 | R17: 732 | S17: 1350 | T17: 1350 | U17: 1227 | V17: 1520.5 | W17: 1520.5 | X17: 1229 | Y17: 1651.24 | Z17: =SUM(M17:Y17)+K17 -> 12044.24
B18: 5 | C18: Education expenses_Enea Sharra | D18: 0 | E18: 0 | F18: 0 | G18: 0 | H18: 0 | I18: 0 | J18: 0 | K18: 0 | L18: 0 | M18: 0 | N18: 0 | O18: 0 | P18: 0 | Q18: 0 | R18: 0 | S18: 0 | T18: 0 | U18: 0 | V18: 0 | W18: 0 | X18: 16000 | Y18: 40000 | Z18: =SUM(M18:Y18)+K18 -> 56000
B19: 6 | C19: Education expenses_Ersa Sharra_"F.Konica" | D19: 0 | E19: 0 | F19: 0 | G19: 0 | H19: 0 | I19: 0 | J19: 0 | K19: 0 | L19: 0 | M19: 0 | N19: 0 | O19: 0 | P19: 0 | Q19: 0 | R19: 0 | S19: 0 | T19: 0 | U19: 0 | V19: 95903.64 | W19: 244632.06 | X19: 247770 | Y19: 254307.6 | Z19: =SUM(M19:Y19)+K19 -> 842613.3 | AA19: 26590
B20: 7 | C20: Education expenses Ersa Sharra_"Elitë" | D20: 0 | E20: 0 | F20: 0 | G20: 0 | H20: 0 | I20: 0 | J20: 0 | K20: 0 | L20: 0 | M20: 0 | N20: 0 | O20: 0 | P20: 0 | Q20: 0 | R20: 0 | S20: 0 | T20: 0 | U20: 0 | V20: 0 | W20: 0 | X20: 0 | Y20: 0 | Z20: =SUM(M20:Y20)+K20 -> 0
B21: 8 | C21: Furnishing expenses | D21: 0 | E21: 0 | F21: 0 | G21: 0 | H21: 0 | I21: 0 | J21: 0 | K21: 0 | L21: 0 | M21: 0 | N21: 0 | O21: 0 | P21: 0 | Q21: 0 | R21: 0 | S21: 0 | T21: 0 | U21: 0 | V21: 0 | W21: 186813.33 | X21: 186813.33 | Y21: 186813.33 | Z21: =SUM(M21:Y21)+K21 -> 560440
B22: 9 | C22: Exp.on loan interests+commissions NBG | D22: 0 | E22: 0 | F22: 0 | G22: 0 | H22: 0 | I22: 0 | J22: 0 | K22: 0 | L22: 0 | M22: 0 | N22: 0 | O22: 0 | P22: 0 | Q22: =32*121.67+'Kredi ne NBG '!D38*KK!R4 -> 216571.72 | R22: ='Kredi ne NBG '!F49*KK!S4 -> 293827.74 | S22: ='Kredi ne NBG '!H45*KK!T4 -> 266262.57 | T22: ='Kredi ne NBG '!J61*KK!U4 -> 232151.76 | U22: ='Kredi ne NBG '!L61*KK!V4 -> 159912.33 | V22: ='Kredi ne NBG '!N69*KK!W4 -> 173734.21 | W22: 0 | X22: 0 | Y22: 0 | Z22: =SUM(M22:Y22)+K22 -> 1342460.3
B24: III | C24: ASSETS | D24: =SUM(D25:D31) -> 0 | E24: =SUM(E25:E31) -> 0 | F24: =SUM(F25:F31) -> 0 | G24: =SUM(G25:G31) -> 0 | H24: =SUM(H25:H31) -> 0 | I24: =SUM(I25:I31) -> 0 | J24: =SUM(J25:J31) -> 0 | K24: =SUM(K25:K31) -> 267300 | ... AA24: =SUM(AA25:AA31) -> 9673
B25: 1 | C25: House_ 134.5 m2 | D25: 0 | E25: 0 | F25: 0 | G25: 0 | H25: 0 | I25: 0 | J25: 0 | K25: 0 | L25: =SUM(D25:K25) -> 0 | M25: 0 | N25: 0 | O25: 0 | P25: 0 | Q25: 0 | R25: 0 | S25: 0 | T25: 0 | U25: 0 | V25: 0 | W25: 0 | X25: 0 | Y25: 0 | Z25: =SUM(M25:Y25)+K25 -> 0
B26: 2 | C26: "Mercedes Benz" 1988_2003 | D26: 0 | E26: 0 | F26: 0 | G26: 0 | H26: 0 | I26: 0 | J26: 0 | K26: =2000*133.65 -> 267300 | L26: =SUM(D26:K26) -> 267300 | M26: 0 | N26: 0 | O26: 0 | P26: 0 | Q26: 0 | R26: 0 | S26: 0 | T26: 0 | U26: 0 | V26: 0 | W26: 0 | X26: 0 | Y26: 0 | Z26: =SUM(M26:Y26)+K26 -> 267300
B27: 3 | C27: Apartment . 128.1 m2_23.06.2008 | D27: 0 | E27: 0 | F27: 0 | G27: 0 | H27: 0 | I27: 0 | J27: 0 | K27: 0 | L27: =SUM(D27:K27) -> 0 | M27: 0 | N27: 0 | O27: 0 | P27: 0 | Q27: =94830*121.99 -> 11568312 | R27: 0 | S27: 0 | T27: 0 | U27: 0 | V27: 0 | W27: 0 | X27: 0 | Y27: 0 | Z27: =SUM(M27:Y27)+K27 -> 11568312
B28: 4 | C28: "Daimler Chrysler"_14.11.2008 | D28: 0 | E28: 0 | F28: 0 | G28: 0 | H28: 0 | I28: 0 | J28: 0 | K28: 0 | L28: =SUM(D28:K28) -> 0 | M28: 0 | N28: 0 | O28: 0 | P28: 0 | Q28: =5500*123.25 -> 677875 | R28: 0 | S28: 0 | T28: 0 | U28: 0 | V28: 0 | W28: 0 | X28: 0 | Y28: 0 | Z28: =SUM(M28:Y28)+K28 -> 677875
B29: 5 | C29: Garage 45 m2_13.04.2013 | D29: 0 | E29: 0 | F29: 0 | G29: 0 | H29: 0 | I29: 0 | J29: 0 | K29: 0 | L29: =SUM(D29:K29) -> 0 | M29: 0 | N29: 0 | O29: 0 | P29: 0 | Q29: 0 | R29: 0 | S29: 0 | T29: 0 | U29: 0 | V29: =11000*140.21 -> 1542310 | W29: 0 | X29: 0 | Y29: 0 | Z29: =SUM(M29:Y29)+K29 -> 1542310
B30: 6 | C30: "Mercedes Benz"_02.03.2017 | D30: 0 | E30: 0 | F30: 0 | G30: 0 | H30: 0 | I30: 0 | J30: 0 | K30: 0 | L30: =SUM(D30:K30) -> 0 | M30: 0 | N30: 0 | O30: 0 | P30: 0 | Q30: 0 | R30: 0 | S30: 0 | T30: 0 | U30: 0 | V30: 0 | W30: 0 | X30: 0 | Y30: 0 | Z30: =SUM(M30:Y30)+K30 -> 0
B31: 7 | C31: Change of liquidity | D31: 0 | E31: 0 | F31: 0 | G31: 0 | H31: 0 | I31: 0 | J31: 0 | K31: 0 | L31: 0 | M31: 0 | N31: =N32-M32 -> 604815.44 | O31: =O32-N32 -> 863578.06 | P31: =+' Likujditete'!S58 -> 339106.54 | Q31: =+' Likujditete'!T58 -> 395498.02 | R31: =R32-Q32 -> -1543902.5 | S31: =S32-R32 -> 1270.44 | T31: =T32-S32 -> 413557.02 | U31: =U32-T32 -> 138927 | V31: =V32-U32 -> 1093559.8 | W31: =W32-V32 -> 198214.83 | X31: =X32-W32 -> 64549.13 | Y31: =Y32-X32 -> 668773.15 | Z31: =SUM(M31:Y31)+K31 -> 3237946.9 | AA31: =+' Likujditete'!AD58 -> 9673
B32: 7/a | C32: Total liquidity | D32: 0 | E32: 0 | F32: 0 | G32: 0 | H32: 0 | I32: 0 | J32: 0 | K32: 0 | L32: 0 | M32: 0 | N32: =SUM(N33:N34) -> 604815.44 | O32: =SUM(O33:O34) -> 1468393.5 | P32: =SUM(P33:P34) -> 1807500 | Q32: =SUM(Q33:Q34) -> 2202998.1 | R32: =SUM(R33:R34) -> 659095.6 | S32: =SUM(S33:S34) -> 660366.04 | T32: =SUM(T33:T34) -> 1073923.1 | U32: =SUM(U33:U34) -> 1212850.1 | ... Z32: =SUM(Z33:Z34) -> 20308097
B33: 7/b | C33: Liquidity in bank | D33: 0 | E33: 0 | F33: 0 | G33: 0 | H33: 0 | I33: 0 | J33: 0 | K33: 0 | L33: =SUM(D33:K33) -> 0 | M33: =+' Likujditete'!P57 -> 0 | N33: =' Likujditete'!Q53 -> 4815.44 | O33: =' Likujditete'!R53 -> 268393.5 | P33: =' Likujditete'!S53 -> 57500.04 | Q33: =' Likujditete'!T53 -> 52998.06 | R33: =' Likujditete'!U53 -> 9095.6 | S33: =' Likujditete'!V53 -> 48670.04 | T33: =' Likujditete'!W53 -> 62227.06 | U33: =' Likujditete'!X53 -> 61154.06 | V33: =+' Likujditete'!Y57 -> 1154713.8 | W33: =' Likujditete'!Z53 -> 546609.66 | X33: =' Likujditete'!AA53 -> 611158.79 | Y33: =' Likujditete'!AB53 -> 1221931.9 | Z33: =SUM(M33:Y33)+K33 -> 4099268 | AA33: =+' Likujditete'!AD57 -> 1287604.9
B34: 7/c | C34: Cash | D34: 0 | E34: 0 | F34: 0 | G34: 0 | H34: 0 | I34: 0 | J34: 0 | K34: 0 | L34: =SUM(D34:K34) -> 0 | M34: =+' Likujditete'!P54 -> 0 | N34: =+' Likujditete'!Q56 -> 600000 | O34: =N34+600000 -> 1200000 | P34: =O34+550000 -> 1750000 | Q34: =P34+400000 -> 2150000 | R34: =Q34-2000000+500000 -> 650000 | S34: =R34+800000-838304 -> 611696 | T34: =S34+400000 -> 1011696 | U34: =T34+140000 -> 1151696 | V34: =+' Likujditete'!Y56 -> 1151696 | W34: =V34+400000+2900*KK!X4 -> 1958015 | X34: =W34 -> 1958015 | Y34: =X34+58000 -> 2016015 | Z34: =SUM(M34:Y34)+K34 -> 16208829 | AA34: =+' Likujditete'!AD54 -> 0
B36: IV | C36: LIABILITES | D36: =SUM(D37:D45) -> 0 | E36: =SUM(E37:E45) -> 0 | F36: =SUM(F37:F45) -> 0 | G36: =SUM(G37:G45) -> 0 | H36: =SUM(H37:H45) -> 0 | I36: =SUM(I37:I45) -> 0 | J36: =SUM(J37:J45) -> 0 | K36: =SUM(K37:K45) -> 0 | ... AA36: =SUM(AA37:AA45) -> 0
B37: 1 | C37: Loan at NBG _ EUR 46.000_01.08.2008 | D37: 0 | E37: 0 | F37: 0 | G37: 0 | H37: 0 | I37: 0 | J37: 0 | K37: 0 | L37: 0 | M37: 0 | N37: 0 | O37: 0 | P37: 0 | Q37: =46000*121.67 -> 5596820 | R37: 0 | S37: 0 | T37: 0 | U37: 0 | V37: 0 | W37: 0 | X37: 0 | Y37: 0 | Z37: =SUM(M37:Y37)+K37 -> 5596820
B38: 2 | C38: Loan repayment to NBG | D38: 0 | E38: 0 | F38: 0 | G38: 0 | H38: 0 | I38: 0 | J38: 0 | K38: 0 | L38: 0 | M38: 0 | N38: 0 | O38: 0 | P38: 0 | Q38: =-601.09*KK!R4 -> -74043.769 | R38: =-16196.62*KK!S4 -> -2221690.4 | S38: =-4020.03*KK!T4 -> -558020.36 | T38: =-5897.49*KK!U4 -> -815622.87 | U38: =-3475.15*KK!V4 -> -485547.96 | V38: =-668.98*KK!W4 -> -93797.686 | W38: =-'Kredi ne NBG '!O56*KK!X4 -> -2250252.1 | X38: 0 | Y38: 0 | Z38: =SUM(M38:Y38)+K38 -> -6498975.1
B39: 3 | C39: Liability to "KDK" ShPK company | D39: 0 | E39: 0 | F39: 0 | G39: 0 | H39: 0 | I39: 0 | J39: 0 | K39: 0 | L39: 0 | M39: 0 | N39: 0 | O39: 0 | P39: 0 | Q39: =Q27 -> 11568312 | R39: 0 | S39: 0 | T39: 0 | U39: 0 | V39: 0 | W39: 0 | X39: 0 | Y39: 0 | Z39: =SUM(M39:Y39)+K39 -> 11568312
B40: 4 | C40: Liability paid to "KDK" ShPK | D40: 0 | E40: 0 | F40: 0 | G40: 0 | H40: 0 | I40: 0 | J40: 0 | K40: 0 | L40: 0 | M40: 0 | N40: 0 | O40: 0 | P40: 0 | Q40: =-45968*121.67 -> -5592926.6 | R40: 0 | S40: 0 | T40: 0 | U40: =-5000*139.72 -> -698600 | V40: =-40000 -> -40000 | W40: 0 | X40: =-(230*138.33+24400*140.84+5000*137.39) -> -4155261.9 | Z40: =SUM(M40:Y40)+K40 -> -10486788 | AA40: 0
B41: 5 | C41: Loan from the father _ EUR 4.000 _2013 | D41: 0 | E41: 0 | F41: 0 | G41: 0 | H41: 0 | I41: 0 | J41: 0 | K41: 0 | L41: 0 | M41: 0 | N41: 0 | O41: 0 | P41: 0 | Q41: 0 | R41: 0 | S41: 0 | T41: 0 | U41: 0 | V41: 0 | W41: 0 | X41: 0 | Y41: 0 | Z41: =SUM(M41:Y41)+K41 -> 0
B42: 6 | C42: Loan from the mother _ EUR 2.000_2017 | D42: 0 | E42: 0 | F42: 0 | G42: 0 | H42: 0 | I42: 0 | J42: 0 | K42: 0 | L42: 0 | M42: 0 | N42: 0 | O42: 0 | P42: 0 | Q42: 0 | R42: 0 | S42: 0 | T42: 0 | U42: 0 | V42: 0 | W42: 0 | X42: 0 | Y42: 0 | Z42: =SUM(M42:Y42)+K42 -> 0
B43: 7 | C43: Repaid loan to the mother | D43: 0 | E43: 0 | F43: 0 | G43: 0 | H43: 0 | I43: 0 | J43: 0 | K43: 0 | L43: 0 | M43: 0 | N43: 0 | O43: 0 | P43: 0 | Q43: 0 | R43: 0 | S43: 0 | T43: 0 | U43: 0 | V43: 0 | W43: 0 | X43: 0 | Y43: 0 | Z43: =SUM(M43:Y43)+K43 -> 0
B44: 8 | C44: Liability for the garage | D44: 0 | E44: 0 | F44: 0 | G44: 0 | H44: 0 | I44: 0 | J44: 0 | K44: 0 | L44: 0 | M44: 0 | N44: 0 | O44: 0 | P44: 0 | Q44: 0 | R44: 0 | S44: 0 | T44: 0 | U44: 0 | V44: =11000*140.21 -> 1542310 | W44: 0 | X44: 0 | Y44: 0 | Z44: =SUM(M44:Y44)+K44 -> 1542310
B45: 9 | C45: Liability paid for the garage | D45: 0 | E45: 0 | F45: 0 | G45: 0 | H45: 0 | I45: 0 | J45: 0 | K45: 0 | L45: 0 | M45: 0 | N45: 0 | O45: 0 | P45: 0 | Q45: 0 | R45: 0 | S45: 0 | T45: 0 | U45: 0 | V45: =-10000*140.21 -> -1402100 | W45: 0 | X45: 0 | Y45: 0 | Z45: =SUM(M45:Y45)+K45 -> -1402100
B47: V | C47: NET ASSETS | D47: =+D24-D36 -> 0 | E47: =+E24-E36 -> 0 | F47: =+F24-F36 -> 0 | G47: =+G24-G36 -> 0 | H47: =+H24-H36 -> 0 | I47: =+I24-I36 -> 0 | J47: =+J24-J36 -> 0 | K47: =+K24-K36 -> 267300 | ... Y47: =+Y24-Y36 -> 668773.15 | Z47: =SUM(L47:Y47) -> 16974165 | AA47: =+AA24-AA36 -> 9673
L48: 0 | Z48: =SUM(L48:Y48) -> 0
B49: VI | C49: FINANCIAL RESULT VI=I-II-V | D49: =(D4)-(D13)-(D47) -> 20452.36 | E49: =(E4)-(E13)-(E47) -> 78548.16 | F49: =(F4)-(F13)-(F47) -> 122578.5 | G49: =(G4)-(G13)-(G47) -> 203443.1 | H49: =(H4)-(H13)-(H47) -> 387437 | I49: =(I4)-(I13)-(I47) -> 420075.5 | J49: =(J4)-(J13)-(J47) -> 233868.96 | K49: =(K4)-(K13)-(K47) -> 122384 | ... Y49: =(Y4)-(Y13)-(Y47) -> 476882.68
W51: =Q49+R49+T49+U49+V49 -> -3713965.9 | Y51: =O49+Q49+R49+T49+U49+V49 -> -3922616
O54: PERIUDHA/PËRSHKRIMI | P54: TË ARDHURA | Q54: SHPENZIME | R54: PASURI | S54: DETYRIME | T54: PASURI NETO | U54: REZULTATI
P55: I | Q55: II | R55: III | S55: IV | T55: V = III-IV | U55: VI = I-II-V
O56: 2003 | P56: =K4 -> 765140 | Q56: =K13 -> 375456 | R56: =K24 -> 267300 | S56: =K36 -> 0 | T56: =R56-S56 -> 267300 | U56: =(P56)-(Q56)-(T56) -> 122384
O57: 2004 | P57: =M4 -> 933625 | Q57: =M13 -> 375856 | R57: =M24 -> 0 | S57: =M36 -> 0 | T57: =R57-S57 -> 0 | U57: =(P57)-(Q57)-(T57) -> 557769
O58: 2005 | P58: =N4 -> 1145795 | Q58: =N13 -> 438228 | R58: =N24 -> 604815.44 | S58: =N36 -> 0 | T58: =R58-S58 -> 604815.44 | U58: =(P58)-(Q58)-(T58) -> 102751.56
O59: 2006 | P59: =O4 -> 1093156 | Q59: =O13 -> 438228 | R59: =O24 -> 863578.06 | S59: =O36 -> 0 | T59: =R59-S59 -> 863578.06 | U59: =(P59)-(Q59)-(T59) -> -208650.06
O60: 2007 | P60: =P4 -> 1029704 | Q60: =P13 -> 547212 | R60: =P24 -> 339106.54 | S60: =P36 -> 0 | T60: =R60-S60 -> 339106.54 | U60: =(P60)-(Q60)-(T60) -> 143385.46
O61: 2008 | P61: =Q4 -> 1623856 | Q61: =Q13 -> 767479.2 | R61: =Q24 -> 12641685 | S61: =Q36 -> 11498161 | T61: =R61-S61 -> 1143523.3 | U61: =(P61)-(Q61)-(T61) -> -287146.55
O62: 2009 | P62: =R4 -> 1349735 | Q62: =R13 -> 841039.74 | R62: =R24 -> -1543902.5 | S62: =R36 -> -2221690.4 | T62: =R62-S62 -> 677787.91 | U62: =(P62)-(Q62)-(T62) -> -169092.65
O63: 2010 | P63: =S4 -> 1389475 | Q63: =S13 -> 814092.57 | R63: =S24 -> 1270.44 | S63: =S36 -> -558020.36 | T63: =R63-S63 -> 559290.8 | U63: =(P63)-(Q63)-(T63) -> 16091.63
O64: 2011 | P64: =T4 -> 1519983 | Q64: =T13 -> 1118816.8 | R64: =T24 -> 413557.02 | S64: =T36 -> -815622.87 | T64: =R64-S64 -> 1229179.9 | U64: =(P64)-(Q64)-(T64) -> -828013.65
O65: 2012 | P65: =U4 -> 1568737 | Q65: =U13 -> 725235.33 | R65: =U24 -> 138927 | S65: =U36 -> -1184148 | T65: =R65-S65 -> 1323075 | U65: =(P65)-(Q65)-(T65) -> -479573.29
O66: 2013 | P66: =V4 -> 1514572 | Q66: =V13 -> 835254.35 | R66: =V24 -> 2635869.8 | S66: =V36 -> 6412.3142 | T66: =R66-S66 -> 2629457.5 | U66: =(P66)-(Q66)-(T66) -> -1950139.8
O67: 2014 | P67: =W4 -> 4638644 | Q67: =W13 -> 1453067.9 | R67: =W24 -> 198214.83 | S67: =W36 -> -2250252.1 | T67: =R67-S67 -> 2448466.9 | U67: =(P67)-(Q67)-(T67) -> 737109.21
O68: 2015 | P68: =X4 -> 6165307 | Q68: =X13 -> 1796081.8 | R68: =X24 -> 64549.13 | S68: =X36 -> -4155261.9 | T68: =R68-S68 -> 4219811 | U68: =(P68)-(Q68)-(T68) -> 149414.14
O69: 2016 | P69: =Y4 -> 2599850 | Q69: =Y13 -> 1454194.2 | R69: =Y24 -> 668773.15 | S69: =Y36 -> 0 | T69: =R69-S69 -> 668773.15 | U69: =(P69)-(Q69)-(T69) -> 476882.68
O70: TOTAL | P70: =SUM(P56:P69) -> 27337579 | Q70: =SUM(Q56:Q69) -> 11980242 | R70: =SUM(R56:R69) -> 17293744 | S70: =SUM(S56:S69) -> 319578.16 | T70: =SUM(T56:T69) -> 16974165
U71: =U59+U61+U62+U64+U65+U66 -> -3922616

Sheet 05.10.2007
C2: Analiza finanaciare e S.R. për blerjen e pas. 56.5 m2
B3: Nr. | C3: PASURIA/PERIUDHA | D3: 2006 | E3: 05.10.2007
B5: I | C5: TË ARDHURA | E5: =SUM(E6:E7) -> 786928.5
B6: 1 | C6: Të ardh.S.R._pagat | E6: =[1]sp_NRP_Balance!$M$116 -> 677095
B7: 2 | C7: Të ardh.B.S.R._pagat | E7: ='Te Ardhurat '!O25/12*7 -> 109833.5
B9: II | C9: SHPENZIME | E9: =SUM(E10:E16) -> 550592
B10: 1 | C10: Shpenz.jetike | E10: =943872/12*7 -> 550592
B11: 2 | C11: Shpenz.shkoll.Enea Sharra
B12: 3 | C12: Shpenz.shkoll.Ersa Sharra_"F.Konica"
B13: 4 | C13: Shpenz.udhët._TIMS
B14: 5 | C14: Shpenz.mobilimi
B15: 6 | C15: Shpenz.legal.godinës tre kate K.K.
B16: 7 | C16: Shpenz,taksa vendore_tokë bujq.
B18: III | C18: PASURI | E18: =SUM(E19:E20) -> 7179284.3
B19: 1 | C19: Ap.56.5 m2 rr.T.Tashko | E19: ='KPA_ndërt.2 kate+ papaf.'!K42 -> 7363200
B20: 2 | C20: Ndrysh.gjend.lik. | E20: =E21-D21 -> -183915.67
B21: a | C21: Total gjendje lik. | D21: =D22+D23 -> 1468393.5 | E21: =E22+E23 -> 1284477.8
B22: b | C22: Gjendje lik.bankë | D22: =Analiza_KPA!O33 -> 268393.5 | E22: =[1]sp_NRP_Balance!$L$174 -> 84477.83
B23: c | C23: Gjendje lik.cash | D23: =Analiza_KPA!O34 -> 1200000 | E23: =D23 -> 1200000
B25: IV | C25: DETYRIME | D25: =SUM(D26:D28) -> 0 | E25: =SUM(E26:E28) -> 0
B26: 1 | C26: Detyrime ndaj shoq."KDK" ShPK | D26: - | E26: -
B27: 2 | C27: Detyrim ndaj A.Ramadani | D27: - | E27: -
B28: 3 | C28: Detyrim ndaj babait | D28: - | E28: -
B30: V | C30: PASURI NETO: V = III - IV | E30: =E18-E25 -> 7179284.3
B48: VI | C48: REZULTATI FIN. VI = I - II - V | E48: =E5-E9-E30 -> -6942947.8

Sheet KK
C3: 1993 | D3: 1994 | E3: 1995 | F3: 1996 | G3: 1997 | H3: 1998 | I3: 1999 | J3: 2000 | K3: 2001 | L3: 2002 | M3: 2003 | N3: 2004 | O3: 2005 | P3: 2006 | Q3: 2007 | R3: 2008 | S3: 2009 | T3: 2010 | U3: 2011 | V3: 2012 | W3: 2013 | X3: 2014 | Y3: 2015 | Z3: 2016 | AA3: 2017 | AB3: 2018 | AC3: 2019 | AJ3: Për reference më poshtë është paraqitur një tabelë përmbledhëse me shpenzimet vjetore sipas tre varianteve për një familje me 4 persona
B4: euro | J4: 132.57 | K4: 120.72 | L4: 140.18 | M4: 133.65 | N4: 126.74 | O4: 122.54 | P4: 123.703 | Q4: 120.91 | R4: 123.1825 | S4: 137.17 | T4: 138.81 | U4: 138.3 | V4: 139.72 | W4: 140.21 | X4: 140.11 | Y4: 137.65 | Z4: 135.27 | AA4: 132.95 | AB4: 123.42 | AC4: 121.77
B5: usd | C5: 102.06 | D5: 94.62 | E5: 92.79 | F5: 104.5 | G5: 148.93 | H5: 150.64 | I5: 137.69 | J5: 142.64 | K5: 136.55 | L5: 133.74 | M5: 108.69 | N5: 94.58 | O5: 103.33 | P5: 93.672 | Q5: 83.03 | R5: 90.96 | S5: 93.98 | T5: 104.95 | U5: 105.08 | V5: 106.57 | W5: 102.38 | X5: 113.64 | Y5: 126.64 | Z5: 128.29 | AA5: 111.1 | AB5: 107.82 | AC5: 108.64 | AJ5: VITET | AK5: 2003 | AL5: 2004 | AM5: 2005 | AN5: 2006 | AO5: 2007 | AP5: 2008 | AQ5: 2009 | AR5: 2010 | AS5: 2011 | AT5: 2012 | AU5: 2013 | AV5: 2014 | AW5: 2015 | AX5: 2016
B6: GBP | J6: 212.23 | K6: 197.86 | L6: 215.31 | M6: 189.92 | N6: 178.69 | O6: 178.65 | P6: 184.65 | Q6: 166.02 | R6: 127.66 | S6: 154.64 | T6: 161.46 | U6: 165.92 | V6: 171.18 | W6: 168.39 | X6: 179.48 | Y6: 186.59 | Z6: 157.56 | AA6: 149.95 | AB6: 137.42 | AC6: 143 | AJ6: INSTAT | AK6: 342252 | AL6: 342252 | AM6: 342252 | AN6: 342252 | AO6: 342252 | AP6: 385152 | AQ6: 385152 | AR6: 385152 | AS6: 385152 | AT6: 385152 | AU6: 385152 | AV6: 360060 | AW6: 400452 | AX6: 397224
AG7: ILDKPKI | AH7: 642857.14 | AI7: 642857.14 | AJ7: 642857.14 | AK7: 642857.14 | AL7: 642857.14 | AM7: 642857.14 | AN7: 642857.14 | AO7: 642857.14 | AP7: 642857.14 | AQ7: 642857.14 | AR7: 642857.14 | AS7: 642857.14 | AT7: 642857.14 | AU7: 642857.14
B9: Ref. ILDKPIK nr.804/1 prot.dt.29.01.2019
J10: 2000 | K10: 2001 | L10: 2002 | M10: 2003 | N10: 2004 | O10: 2005 | P10: 2006 | Q10: 2007 | R10: 2008 | S10: 2009 | T10: 2010 | U10: 2011 | V10: 2012 | W10: 2013 | X10: 2014 | Y10: 2015 | Z10: 2016 | AA10: 2017 | AB10: 2018
B11: per fryme | J11: 108000 | K11: 108000 | L11: 93894 | M11: 93964 | N11: 93964 | O11: 109557 | P11: 109557 | Q11: 136620 | R11: 136620 | S11: 136620 | T11: 136620 | U11: 136620 | V11: 139548 | W11: 141024 | X11: 219998 | Y11: 224276 | Z11: 235092 | AA11: 238054.05 | AB11: 246275.68
B12: 2 familjare | J12: 216000 | K12: 216000 | L12: 187788 | M12: 187928 | N12: 187928 | O12: 219114 | P12: 219114 | Q12: 273240 | R12: 273240 | S12: 273240 | T12: 273240 | U12: 273240 | V12: 279096 | W12: 282048 | X12: 439996 | Y12: 448552 | Z12: 470184 | AA12: 476108.11 | AB12: 492551.35
B13: 3 familjare | J13: 324000 | K13: 324000 | L13: 281682 | M13: 281892 | N13: 281892 | O13: 328671 | P13: 328671 | Q13: 409860 | R13: 409860 | S13: 409860 | T13: 409860 | U13: 409860 | V13: 418644 | W13: 423072 | X13: 659994 | Y13: 672828 | Z13: 705276 | AA13: 714162.16 | AB13: 738827.03
B14: 4 familjare | J14: 432000 | K14: 432000 | L14: 375576 | M14: 375856 | N14: 375856 | O14: 438228 | P14: 438228 | Q14: 546480 | R14: 546480 | S14: 546480 | T14: 546480 | U14: 546480 | V14: 558192 | W14: 564096 | X14: 879992 | Y14: 897104 | Z14: 940368 | AA14: 952216.22 | AB14: 985102.7
B15: 5 familjare | J15: 540000 | K15: 540000 | L15: 469470 | M15: 469820 | N15: 469820 | O15: 547785 | P15: 547785 | Q15: 683100 | R15: 683100 | S15: 683100 | T15: 683100 | U15: 683100 | V15: 697740 | W15: 705120 | X15: 1099990 | Y15: 1121380 | Z15: 1175460 | AA15: 1190270.3 | AB15: 1231378.4
B16: 6 familjare | J16: 648000 | K16: 648000 | L16: 563364 | M16: 563784 | N16: 563784 | O16: 657342 | P16: 657342 | Q16: 819720 | R16: 819720 | S16: 819720 | T16: 819720 | U16: 819720 | V16: 837288 | W16: 846144 | X16: 1319988 | Y16: 1345656 | Z16: 1410552 | AA16: 1428324.3 | AB16: 1477654.1
B17: 7 familjare | J17: 756000 | K17: 756000 | L17: 657258 | M17: 657748 | N17: 657748 | O17: 766899 | P17: 766899 | Q17: 956340 | R17: 956340 | S17: 956340 | T17: 956340 | U17: 956340 | V17: 976836 | W17: 987168 | X17: 1539986 | Y17: 1569932 | Z17: 1645644 | AA17: 1666378.4 | AB17: 1723929.7
B18: 8 familjare | J18: 864000 | K18: 864000 | L18: 751152 | M18: 751712 | N18: 751712 | O18: 876456 | P18: 876456 | Q18: 1092960 | R18: 1092960 | S18: 1092960 | T18: 1092960 | U18: 1092960 | V18: 1116384 | W18: 1128192 | X18: 1759984 | Y18: 1794208 | Z18: 1880736 | AA18: 1904432.4 | AB18: 1970205.4
A20: Shenim | B20: Sipas Shkreses se sipercituar te ILDKPIK shpenzimet per fryme te vitin 2007 jane 235,968 Leke, vlere e cila eshte 2-fish ne krahasim me Vitet 2006 dhe 2008.
B21: Në praktiken tonë Vlera e shpenzimeve per fryme merret e barabartë me Vitin 2008.
B22: Kjo rritje dhe pastaj ulje nuk bazohet ne shifrat e Inflacionit Zyrtar i cili ne V.2006 eshte 2,5%, V.2007-3% dhe V.2008-2%.
B23: http://open.data.al/sq/lajme/lajm/lang/sq/id/71/Historik-i-Inflacionit-ne-Shqiperi
J28: 2000 | K28: 2001 | L28: 2002 | M28: 2003 | N28: 2004 | O28: 2005 | P28: 2006 | Q28: 2007 | R28: 2008 | S28: 2009 | T28: 2010 | U28: 2011 | V28: 2012 | W28: 2013 | X28: 2014 | Y28: 2015 | Z28: 2016 | AA28: 2017 | AB28: 2018
B29: 2 familjare | J29: 216000 | K29: 216000 | L29: 187788 | M29: 187928 | N29: 187928 | O29: 219114 | P29: 219114 | Q29: 273240 | R29: 273240 | S29: 273240 | T29: 273240 | U29: 273240 | V29: 279096 | W29: 282048 | X29: 439996 | Y29: 448552 | Z29: 470184 | AA29: 476108.11 | AB29: 492551.35
X32: =2900 -> 2900
X33: =X32*X4 -> 406319

Sheet ID
C2: Emer | D2: Atesi | E2: Mbiemer | F2: Datelindje
B3: S.R. | C3: Arben | D3: Sinan | E3: Sharra | F3: 29.03.1973
B4: B/Sh | C4: Flutura | D4: Halit | E4: Sharra | F4: 09.05.1974
B5: I biri | C5: Enea | D5: Arben | E5: Sharra | F5: 02.09.1997
B6: E bija | C6: Ersa | D6: Arben | E6: Sharra | F6: 22.01.2002

Sheet Analiza 
L2: Ne detyre ne date 16.07.2004
C3: 1996 | D3: 1997 | E3: 1998 | F3: 1999 | G3: 2000 | H3: 2001 | I3: 2002 | J3: 2003 | K3: 1996-2003 | L3: 2004 | M3: 2005 | N3: 2006 | O3: 2007 | P3: 2008 | Q3: 2009 | R3: 2010 | S3: 2011 | T3: 2012 | U3: 2013 | V3: 2014 | W3: 2015 | X3: 2016 | Y3: Totali | Z3: Deklarata Vetting
B4: Pasuria | D4: =SUM(D5:D11) -> 0 | E4: =SUM(E5:E11) -> 0 | F4: =SUM(F5:F11) -> 0 | G4: =SUM(G5:G11) -> 0 | H4: =SUM(H5:H11) -> 0 | I4: =SUM(I5:I11) -> 0 | J4: =SUM(J5:J11) -> 267300 | K4: 267300 | L4: =SUM(L5:L11) -> 0 | M4: =SUM(M5:M11) -> 604815.44 | N4: =SUM(N5:N11) -> 863578.06 | O4: =SUM(O5:O11) -> 339106.54 | P4: =SUM(P5:P11) -> 12754398 | Q4: =SUM(Q5:Q11) -> -1543902.5 | R4: =SUM(R5:R11) -> 1270.44 | S4: =SUM(S5:S11) -> 413557.02 | ... Z4: =SUM(Z5:Z11) -> 9673
B5: Shtepi Banimi sip 134.5 M2 | K5: 0 | L5: 0 | M5: 0 | N5: 0 | O5: 0 | P5: 0 | Y5: =SUM(K5:X5) -> 0
B6: Mercedes Benz 2003 | J6: =2000*KK!M4 -> 267300 | K6: 267300 | L6: 0 | M6: 0 | N6: 0 | O6: 0 | P6: 0 | Y6: =SUM(K6:X6) -> 267300
B7: Apartament banimi me sip 128.1 m2 | K7: 0 | L7: 0 | M7: 0 | N7: 0 | O7: 0 | P7: =94830*KK!R4 -> 11681396 | Y7: =SUM(K7:X7) -> 11681396
B8: Automjet Daimler Chrysler | K8: 0 | L8: 0 | M8: 0 | N8: 0 | O8: 0 | P8: =5500*KK!R4 -> 677503.75 | Y8: =SUM(K8:X8) -> 677503.75
B9: Garazhd me sip 45 m2 | K9: 0 | L9: 0 | M9: 0 | N9: 0 | O9: 0 | P9: 0 | U9: =11000*KK!W4 -> 1542310 | Y9: =SUM(K9:X9) -> 1542310
B10: Automjet Mercedes Benz 02.03.2017 | K10: 0 | L10: 0 | M10: 0 | N10: 0 | O10: 0 | P10: 0 | Y10: =SUM(K10:X10) -> 0
B11: Ndryshim likujditeti | J11: =+' Likujditete'!O58 -> 0 | K11: 0 | L11: =+' Likujditete'!P58 -> 0 | M11: =+' Likujditete'!Q58 -> 604815.44 | N11: =+' Likujditete'!R58 -> 863578.06 | O11: =+' Likujditete'!S58 -> 339106.54 | P11: =+' Likujditete'!T58 -> 395498.02 | Q11: =+' Likujditete'!U58 -> -1543902.5 | R11: =+' Likujditete'!V58 -> 1270.44 | S11: =+' Likujditete'!W58 -> 413557.02 | ... X11: =+' Likujditete'!AB58 -> 666773.15 | Y11: =SUM(K11:X11) -> 2084250.9 | Z11: =+' Likujditete'!AD58 -> 9673
B12: Total Likujditeti | J12: =+' Likujditete'!O57 -> 0 | K12: 0 | L12: =+' Likujditete'!P57 -> 0 | M12: =+' Likujditete'!Q57 -> 604815.44 | N12: =+' Likujditete'!R57 -> 1468393.5 | O12: =+' Likujditete'!S57 -> 1807500 | P12: =+' Likujditete'!T57 -> 2202998.1 | Q12: =+' Likujditete'!U57 -> 659095.6 | R12: =+' Likujditete'!V57 -> 660366.04 | S12: =+' Likujditete'!W57 -> 1073923.1 | ... X12: =+' Likujditete'!AB57 -> 2084250.9 | Y12: =SUM(K12:X12) -> 15699313 | Z12: =+' Likujditete'!AD57 -> 1287604.9
B13: cash | D13: 0 | E13: 0 | F13: 0 | G13: 0 | H13: 0 | I13: 0 | J13: =+' Likujditete'!O54 -> 0 | K13: 0 | L13: =+' Likujditete'!P54 -> 0 | M13: =+' Likujditete'!Q56 -> 600000 | N13: =+' Likujditete'!R56 -> 1200000 | O13: =+' Likujditete'!S56 -> 1750000 | P13: =+' Likujditete'!T56 -> 2150000 | Q13: =+' Likujditete'!U56 -> 650000 | R13: =+' Likujditete'!V56 -> 611696 | S13: =+' Likujditete'!W56 -> 1011696 | T13: =+' Likujditete'!X56 -> 1151696 | ... X13: =+' Likujditete'!AB56 -> 862319 | Y13: =SUM(K13:X13) -> 12751741 | Z13: =+' Likujditete'!AD54 -> 0
B14: Detyrime | C14: =SUM(C15:C23) -> 0 | D14: =SUM(D15:D23) -> 0 | E14: =SUM(E15:E23) -> 0 | F14: =SUM(F15:F23) -> 0 | G14: =SUM(G15:G23) -> 0 | H14: =SUM(H15:H23) -> 0 | I14: =SUM(I15:I23) -> 0 | J14: =SUM(J15:J23) -> 0 | K14: 0 | L14: =SUM(L15:L23) -> 0 | M14: =SUM(M15:M23) -> 0 | N14: =SUM(N15:N23) -> 0 | O14: =SUM(O15:O23) -> 0 | P14: =SUM(P15:P23) -> 11430104 | Q14: =SUM(Q15:Q23) -> -2532838.6 | R14: =SUM(R15:R23) -> -855658.15 | S14: =SUM(S15:S23) -> -1037710.5 | ... X14: =SUM(X15:X23) -> 0 | Y14: =SUM(K14:X14) -> -1013066.1 | Z14: =SUM(Z15:Z23) -> 0
B15: Kredi ne NBG 46,000 Euro | K15: 0 | L15: 0 | M15: 0 | N15: 0 | O15: 0 | P15: =46000*KK!R4 -> 5666395 | Y15: =SUM(K15:X15) -> 5666395
B16: Shlyerje e kredise ne NBG 46,000 Euro | K16: 0 | L16: 0 | M16: 0 | N16: 0 | O16: 0 | P16: =-'Kredi ne NBG '!D6 -> -255234.14 | Q16: =-'Kredi ne NBG '!E6 -> -2532838.6 | R16: =-'Kredi ne NBG '!F6 -> -855658.15 | S16: =-'Kredi ne NBG '!G6 -> -1037710.5 | T16: =-'Kredi ne NBG '!H6 -> -684628 | U16: =-'Kredi ne NBG '!I6 -> -267941.31 | V16: =-'Kredi ne NBG '!J6 -> -2387474.4 | Y16: =SUM(K16:X16) -> -8021485.1
B17: Detyrim ndaj KDK | K17: 0 | L17: 0 | M17: 0 | N17: 0 | O17: 0 | P17: =+P7 -> 11681396 | Y17: =SUM(K17:X17) -> 11681396
B18: Shlyerje detyrim ndaj KDK | K18: 0 | L18: 0 | M18: 0 | N18: 0 | O18: 0 | P18: =-(45968*KK!R4) -> -5662453.2 | Q18: 0 | R18: 0 | S18: 0 | T18: =-5000*KK!V4 -> -698600 | U18: =-(285)*KK!W4 -> -39959.85 | W18: =-(230+24400+5000)*KK!Y4 -> -4078569.5 | Y18: =SUM(K18:X18) -> -10479583 | Z18: 0
B19: Hua nga babai 4000 Euro 2013 | K19: 0 | L19: 0 | M19: 0 | N19: 0 | O19: 0 | P19: 0 | Y19: =SUM(K19:X19) -> 0
B20: Hua nga nena 2000 Euro 2017 | K20: 0 | L20: 0 | M20: 0 | N20: 0 | O20: 0 | P20: 0 | Y20: =SUM(K20:X20) -> 0
B21: Shlyerje Hua ndaj nenes | K21: 0 | L21: 0 | M21: 0 | N21: 0 | O21: 0 | P21: 0 | U21: 0 | Y21: =SUM(K21:X21) -> 0
B22: Detyrim per garazhdin | K22: 0 | L22: 0 | M22: 0 | N22: 0 | O22: 0 | P22: 0 | U22: =+U9 -> 1542310 | Y22: =SUM(K22:X22) -> 1542310
B23: Shlyerje detyrim per garazhdin | K23: 0 | L23: 0 | M23: 0 | N23: 0 | O23: 0 | P23: 0 | U23: =-10000*KK!W4 -> -1402100 | Y23: =SUM(K23:X23) -> -1402100
B24: Pasuria Neto | C24: =+C4-C14 -> 0 | D24: =+D4-D14 -> 0 | E24: =+E4-E14 -> 0 | F24: =+F4-F14 -> 0 | G24: =+G4-G14 -> 0 | H24: =+H4-H14 -> 0 | I24: =+I4-I14 -> 0 | J24: =+J4-J14 -> 267300 | K24: 267300 | L24: =+L4-L14 -> 0 | M24: =+M4-M14 -> 604815.44 | N24: =+N4-N14 -> 863578.06 | O24: =+O4-O14 -> 339106.54 | P24: =+P4-P14 -> 1324294.1 | Q24: =+Q4-Q14 -> 988936.1 | R24: =+R4-R14 -> 856928.59 | S24: =+S4-S14 -> 1451267.6 | ... X24: =+X4-X14 -> 666773.15 | Y24: =SUM(K24:X24) -> 17265827 | Z24: =+Z4-Z14 -> 9673
K25: 0 | Y25: =SUM(K25:X25) -> 0
B26: Te ardhura | C26: =SUM(C27:C32) -> 60154 | D26: =SUM(D27:D32) -> 231024 | E26: =SUM(E27:E32) -> 360525 | F26: =SUM(F27:F32) -> 461249 | G26: =SUM(G27:G32) -> 603437 | H26: =SUM(H27:H32) -> 636075.5 | I26: =SUM(I27:I32) -> 608853.5 | J26: =SUM(J27:J32) -> 765140 | K26: 3726458 | L26: =SUM(L27:L32) -> 933625 | M26: =SUM(M27:M32) -> 1145795 | N26: =SUM(N27:N32) -> 1093156 | O26: =SUM(O27:O32) -> 1029704 | P26: =SUM(P27:P32) -> 1623856 | Q26: =SUM(Q27:Q32) -> 1349735 | R26: =SUM(R27:R32) -> 1389475 | S26: =SUM(S27:S32) -> 1519983 | ... X26: =SUM(X27:X32) -> 2607678 | Y26: =SUM(K26:X26) -> 30215825 | Z26: =SUM(Z27:Z32) -> 175673
B27: Te ardhurat e subjektit | C27: =+'Te Ardhurat '!D9 -> 60154 | D27: =+'Te Ardhurat '!E9 -> 231024 | E27: =+'Te Ardhurat '!F9 -> 360525 | F27: =+'Te Ardhurat '!G9 -> 390615 | G27: =+'Te Ardhurat '!H9 -> 442564 | H27: =+'Te Ardhurat '!I9 -> 446705 | I27: =+'Te Ardhurat '!J9 -> 414633 | J27: =+'Te Ardhurat '!K9 -> 473716 | K27: 2819936 | L27: =+'Te Ardhurat '!L9 -> 606194 | M27: =+'Te Ardhurat '!M9 -> 818245 | N27: =+'Te Ardhurat '!N9 -> 815652 | O27: =+'Te Ardhurat '!O9 -> 841418 | P27: =+'Te Ardhurat '!P9 -> 905278 | Q27: =+'Te Ardhurat '!Q9 -> 851469 | R27: =+'Te Ardhurat '!R9 -> 814286 | S27: =+'Te Ardhurat '!S9 -> 942368 | ... X27: =+'Te Ardhurat '!X9 -> 1170841 | Y27: =SUM(K27:X27) -> 14702262 | Z27: =+'Te Ardhurat '!Z9 -> 99845
B28: Te ardhurat e Bshortes se Subjektit | C28: =+'Te Ardhurat '!D25 -> 0 | D28: =+'Te Ardhurat '!E25 -> 0 | E28: =+'Te Ardhurat '!F25 -> 0 | F28: =+'Te Ardhurat '!G25 -> 70634 | G28: =+'Te Ardhurat '!H25 -> 160873 | H28: =+'Te Ardhurat '!I25 -> 189370.5 | I28: =+'Te Ardhurat '!J25 -> 194220.5 | J28: =+'Te Ardhurat '!K25 -> 291424 | K28: 906522 | L28: =+'Te Ardhurat '!L25 -> 327431 | M28: =+'Te Ardhurat '!M25 -> 327550 | N28: =+'Te Ardhurat '!N25 -> 277504 | O28: =+'Te Ardhurat '!O25 -> 188286 | P28: =+'Te Ardhurat '!P25 -> 318578 | Q28: =+'Te Ardhurat '!Q25 -> 498266 | R28: =+'Te Ardhurat '!R25 -> 575189 | S28: =+'Te Ardhurat '!S25 -> 577615 | ... X28: =+'Te Ardhurat '!X25 -> 904419 | Y28: =SUM(K28:X28) -> 7649445 | Z28: =+'Te Ardhurat '!Z25 -> 75828
B29: Te ardhura nga shitja e automjetit Mercedes Benz dt 09.09.2008 shuma 400,000 leke | C29: =+'Te Ardhurat '!D33 -> 0 | D29: =+'Te Ardhurat '!E33 -> 0 | E29: =+'Te Ardhurat '!F33 -> 0 | F29: =+'Te Ardhurat '!G33 -> 0 | G29: =+'Te Ardhurat '!H33 -> 0 | H29: =+'Te Ardhurat '!I33 -> 0 | I29: =+'Te Ardhurat '!J33 -> 0 | J29: =+'Te Ardhurat '!K33 -> 0 | K29: 0 | L29: =+'Te Ardhurat '!L33 -> 0 | M29: =+'Te Ardhurat '!M33 -> 0 | N29: =+'Te Ardhurat '!N33 -> 0 | O29: =+'Te Ardhurat '!O33 -> 0 | P29: =+'Te Ardhurat '!P33 -> 400000 | Q29: =+'Te Ardhurat '!Q33 -> 0 | R29: =+'Te Ardhurat '!R33 -> 0 | S29: =+'Te Ardhurat '!S33 -> 0 | ... X29: =+'Te Ardhurat '!X33 -> 0 | Y29: =SUM(K29:X29) -> 400000 | Z29: =+'Te Ardhurat '!Z33 -> 0
B30: PARADHENIE per shitjen e baneses ne K.Kamez | K30: 0 | L30: =+'Te Ardhurat '!L34 -> 0 | M30: =+'Te Ardhurat '!M34 -> 0 | N30: =+'Te Ardhurat '!N34 -> 0 | O30: =+'Te Ardhurat '!O34 -> 0 | P30: =+'Te Ardhurat '!P34 -> 0 | V30: =20000*KK!X4 -> 2802200 | W30: =30000*KK!Y4 -> 4129500 | Y30: =SUM(K30:X30) -> 6931700
B31: Te ardhura nga shitja e automjetit Mercedes Benz dt 15.03.2016 shuma 3,800 Euro | C31: =+'Te Ardhurat '!D34 -> 0 | D31: =+'Te Ardhurat '!E34 -> 0 | E31: =+'Te Ardhurat '!F34 -> 0 | F31: =+'Te Ardhurat '!G34 -> 0 | G31: =+'Te Ardhurat '!H34 -> 0 | H31: =+'Te Ardhurat '!I34 -> 0 | I31: =+'Te Ardhurat '!J34 -> 0 | J31: =+'Te Ardhurat '!K34 -> 0 | K31: 0 | L31: =+'Te Ardhurat '!L35 -> 0 | M31: =+'Te Ardhurat '!M35 -> 0 | N31: =+'Te Ardhurat '!N35 -> 0 | O31: =+'Te Ardhurat '!O35 -> 0 | P31: =+'Te Ardhurat '!P35 -> 0 | Q31: =+'Te Ardhurat '!Q34 -> 0 | R31: =+'Te Ardhurat '!R34 -> 0 | S31: =+'Te Ardhurat '!S34 -> 0 | T31: =+'Te Ardhurat '!T34 -> 0 | U31: =+'Te Ardhurat '!U34 -> 0 | V31: =+'Te Ardhurat '!V34 -> 0 | W31: =+'Te Ardhurat '!W34 -> 0 | X31: =3800*KK!X4 -> 532418 | Y31: =SUM(K31:X31) -> 532418 | Z31: =+'Te Ardhurat '!Z34 -> 0
B32: Te ardhura nga shitja e baneses ne K.Kamez kontrete shitje dt 16.06.2017 | K32: 0 | L32: =+'Te Ardhurat '!L36 -> 0 | M32: =+'Te Ardhurat '!M36 -> 0 | N32: =+'Te Ardhurat '!N36 -> 0 | O32: =+'Te Ardhurat '!O36 -> 0 | P32: 0 | Y32: =SUM(K32:X32) -> 0
B33: Shpenzime | C33: =SUM(C34:C41) -> 19850.82 | D33: =SUM(D34:D41) -> 76237.92 | E33: =SUM(E34:E41) -> 118973.25 | F33: =SUM(F34:F41) -> 152212.17 | G33: =SUM(G34:G41) -> 324000 | H33: =SUM(H34:H41) -> 324000 | I33: =SUM(I34:I41) -> 367751.5 | J33: =SUM(J34:J41) -> 375856 | K33: 1758881.7 | L33: =SUM(L34:L41) -> 375856 | M33: =SUM(M34:M41) -> 438228 | N33: =SUM(N34:N41) -> 438228 | O33: =SUM(O34:O41) -> 547212 | P33: =SUM(P34:P41) -> 550907.47 | Q33: =SUM(Q34:Q41) -> 547212 | R33: =SUM(R34:R41) -> 547830 | S33: =SUM(S34:S41) -> 886665 | ... X33: =SUM(X34:X41) -> 1454194.2 | Y33: =SUM(K33:X33) -> 12407891 | Z33: =SUM(Z34:Z41) -> 113918.35
B34: Shpenzime Jetike | C34: =+(C27+C28)*0.33 -> 19850.82 | D34: =+(D27+D28)*0.33 -> 76237.92 | E34: =+(E27+E28)*0.33 -> 118973.25 | F34: =+(F27+F28)*0.33 -> 152212.17 | G34: =+KK!J13 -> 324000 | H34: =+KK!K13 -> 324000 | I34: =+KK!L13/12*1+KK!L14/12*11 -> 367751.5 | J34: =+KK!M14 -> 375856 | K34: 1758881.7 | L34: =+KK!N14 -> 375856 | M34: =+KK!O14 -> 438228 | N34: =+KK!P14 -> 438228 | O34: =+KK!Q14 -> 546480 | P34: =+KK!R14 -> 546480 | Q34: =+KK!S14 -> 546480 | R34: =+KK!T14 -> 546480 | S34: =+KK!U14 -> 546480 | ... X34: =+KK!Z14 -> 940368 | Y34: =SUM(K34:X34) -> 9583345.7 | Z34: =+KK!AA14/12 -> 79351.351
B35: TIMS | K35: 0 | L35: 0 | M35: 0 | N35: 0 | O35: 0 | P35: =+TIMS!C6 -> 3695.475 | Q35: =+TIMS!D6 -> 0 | R35: =+TIMS!E6 -> 0 | S35: =+TIMS!F6 -> 338835 | T35: =+TIMS!G6 -> 0 | U35: =+TIMS!H6 -> 392588 | V35: =+TIMS!I6 -> 140110 | W35: =+TIMS!J6 -> 37165.5 | X35: =+TIMS!K6 -> 31054 | Y35: =SUM(K35:X35) -> 943447.97 | Z35: =+TIMS!M6 -> 7977 | AB35: 2196
B36: Shpenzime per legalizimin e Godine banimi 3 kateshe 01.07.2015 | K36: 0 | L36: 0 | M36: 0 | N36: 0 | O36: 0 | P36: 0 | W36: =(500000*0.1)+360000 -> 410000 | Y36: =SUM(K36:X36) -> 410000
B37: Shpenzime per Taksat vendore te tokes bujqesore | K37: 0 | L37: 0 | M37: 0 | N37: 0 | O37: 732 | P37: 732 | Q37: 732 | R37: 1350 | S37: 1350 | T37: 1227 | U37: 1520.5 | V37: 1520.5 | W37: 1229 | X37: 1651.24 | Y37: =SUM(K37:X37) -> 12044.24
B38: Shpenzime per shkollimin e Enea Sharra | K38: 0 | L38: 0 | M38: 0 | N38: 0 | O38: 0 | P38: 0 | W38: =40000/10*4 -> 16000 | X38: 40000 | Y38: =SUM(K38:X38) -> 56000
B39: Shpenzime per shkollimin e Ersa Sharra Shkolla Faik Konica | K39: 0 | L39: 0 | M39: 0 | N39: 0 | O39: 0 | P39: 0 | U39: =1710/10*4*KK!W4 -> 95903.64 | V39: =+(1710/10*6+1800/10*4)*KK!X4 -> 244632.06 | W39: =+(1800/10*4+1800/10*6)*KK!Y4 -> 247770 | X39: =+(1800/10*6+2000/10*4)*KK!Z4 -> 254307.6 | Y39: =SUM(K39:X39) -> 842613.3 | Z39: =+(200)*KK!AA4 -> 26590
B40: Shpenzime per shkollimin e Ersa Sharra Shkolla Elite | K40: 0 | L40: 0 | M40: 0 | N40: 0 | O40: 0 | P40: 0 | Y40: =SUM(K40:X40) -> 0
B41: Shpenzime Mobilimi | K41: 0 | L41: 0 | M41: 0 | N41: 0 | O41: 0 | P41: 0 | V41: =4000*KK!X4/3 -> 186813.33 | W41: 186813.33 | X41: 186813.33 | Y41: =SUM(K41:X41) -> 560440
B42: Mundesia per kursime | C42: =+C26-C24-C33 -> 40303.18 | D42: =+D26-D24-D33 -> 154786.08 | E42: =+E26-E24-E33 -> 241551.75 | F42: =+F26-F24-F33 -> 309036.83 | G42: =+G26-G24-G33 -> 279437 | H42: =+H26-H24-H33 -> 312075.5 | I42: =+I26-I24-I33 -> 241102 | J42: =+J26-J24-J33 -> 121984 | K42: 1700276.3 | L42: =+L26-L24-L33 -> 557769 | M42: =+M26-M24-M33 -> 102751.56 | N42: =+N26-N24-N33 -> -208650.06 | O42: =+O26-O24-O33 -> 143385.46 | P42: =+P26-P24-P33 -> -251345.54 | Q42: =+Q26-Q24-Q33 -> -186413.1 | R42: =+R26-R24-R33 -> -15283.594 | S42: =+S26-S24-S33 -> -817949.56 | ... X42: =+X26-X24-X33 -> 486710.68 | Y42: =SUM(K42:X42) -> 542106.52 | Z42: =+Z26-Z24-Z33 -> 52081.649
D44: 02.09.1997 lind Enea Sharra | I44: 22.01.2002 lind Ersa Sharra | Y44: =+N42+P42+Q42+R42+S42+T42+U42 -> -3183879.9

Sheet  Likujditete
B3: Subjekti Arben Sharra | C3: BANKA | D3: Nr Llogarise | E3: monedha | H3: 1996 | I3: 1997 | J3: 1998 | K3: 1999 | L3: 2000 | M3: 2001 | N3: 2002 | O3: 2003 | P3: 2004 | Q3: 2005 | R3: 2006 | S3: 2007 | T3: 2008 | U3: 2009 | V3: 2010 | W3: 2011 | X3: 2012 | Y3: 2013 | Z3: 2014 | AA3: 2015 | AB3: 2016 | AC3: TOTAL | AD3: DVETTING
B5: Llogari kredie | C5: NBG | D5: 18791341016015 | E5: Euro | T5: =0.41*KK!R4 -> 50.504825 | U5: =0.62*KK!S4 -> 85.0454 | V5: =4.65*KK!T4 -> 645.4665 | W5: =0.37*KK!U4 -> 51.171 | X5: 0 | Y5: =2.82*KK!W4 -> 395.3922 | Z5: =24.85*KK!X4 -> 3481.7335
B6: kestet e paguara | E6: Euro | T6: =346+345+345+346+345+345 -> 2072 | U6: =345+346+345.24+345+345.24+15000+230.24+356.24+231+230+230+231+230 -> 18464.96 | V6: =230*7+231+230.24+231+126+231+3405+100 -> 6164.24 | W6: =201+204+205+205+205+205+205+3290+180.86+180.86+180.86+180.75+2060 -> 7503.33 | X6: =165+165+165+165+162+165+165+3090+198+180+150+130 -> 4900 | Y6: =140+138+138+140+140+140+137+140+138+140+100+150+130+140 -> 1911 | Z6: =140*8+100+135+135+15550 -> 17040
U7: 15000 eruo cash dep dt 28 maj 2009 | V7: 3405 euro cash dep dt 25.11.2010 | W7: 3290 euro cash dep dt 01 gusht 2011 | X7: 3090 euro Cash depozite dt 13 gusht 2012 | Z7: 15550 euro cash depozit dt 07 nentor 2014
W8: 2060 Euro cash dep dt 30 dhjetor 2011
B10: Gjendja 31.12….. | C10: RZB | D10: 525206 | E10: lek | Q10: 4568.44 | R10: 268021.29 | S10: 57127.83 | T10: 52625.52 | U10: 11.43 | V10: 233.04 | W10: 308.06 | X10: -60.17 | Y10: 598.48 | Z10: 83216.14 | AA10: 6144.87 | AB10: 411888.02 | AD10: 451733.02
B11: llogari page | Q11: =27726+65858+69069+65221+83364+63936+65221+68432+10000+67305+62123 -> 648255 | R11: =23495+68432+65081+65081+68292+68292+68292+64088+62445+74824+71362+79158+15000+42095 -> 835937 | S11: =24027+71195+69348+75976+72976+72703+40605+36021+66228+76627+79229+65136+68450+14507+49943+30000 -> 912971 | T11: =64450+85761+76775+76438+74579+74326+6449+93825+68121+74716+70320+70320+52500 -> 888580 | U11: =26820+70320+66495+66495+91257+66495+77050+66495+66495+66495+66495+77772 -> 808684 | V11: =31772+49833+65772+65773+65772+65772+65772+65772+65380+68872+66876+49537+12564+75877+9000+5381 -> 829725 | W11: =67774+72258+77639+72258+88401+72258+66877+83020+76833+85400+69526+87247+9000 -> 928491 | X11: =81650+69526+80718+80718+86314+69526+69526+81151+74699+69249+73809+71264+77012+9000 -> 994162 | Y11: =71264+77012+82760+71264+71264+73180+71264+72801+72477+72477+85081+78249+11714 -> 910807 | Z11: =78249+89195+120275+89195+95857+95857+95857+108513+89014+105426+60648+51843+978 -> 1080907 | AA11: =90762+86345+95055+91791+96155+89608+102577+89608+99519+91334+91334+96334 -> 1120422 | AB11: =93834+97167+91334+96333+91334+86941+91334+93060+93060+114222+104537+111673 -> 1164829 | AD11: 99845
B15: Gjendja 31.12….. | C15: RZB | D15: 525206 | E15: Euro
B17: TOTALI | I17: =SUM(I4:I16) -> 0 | J17: =SUM(J4:J16) -> 0 | K17: =SUM(K4:K16) -> 0 | L17: =SUM(L4:L16) -> 0 | M17: =SUM(M4:M16) -> 0 | N17: =SUM(N4:N16) -> 0 | O17: =+O10+O15 -> 0 | P17: =+P10+P15 -> 0 | Q17: =+Q10+Q15 -> 4568.44 | R17: =+R10+R15 -> 268021.29 | S17: =+S10+S15 -> 57127.83 | T17: =+T10+T15 -> 52625.52 | U17: =+U10+U15 -> 11.43 | V17: =+V10+V15 -> 233.04 | ... AD17: =+AD10+AD15 -> 451733.02
B19: B/Shhorti I subjektit | C19: BANKA | D19: Nr Llogarise | E19: monedha | H19: 1996 | I19: 1997 | J19: 1998 | K19: 1999 | L19: 2000 | M19: 2001 | N19: 2002 | O19: 2003 | P19: 2004 | Q19: 2005 | R19: 2006 | S19: 2007 | T19: 2008 | U19: 2009 | V19: 2010 | W19: 2011 | X19: 2012 | Y19: 2013 | Z19: 2014 | AA19: 2015 | AB19: 2016 | AC19: TOTAL | AD19: DVETTING
B21: Gjendja 31.12….. | C21: Tirana Bank | D21: 267207 | E21: lek | U21: 9084 | V21: 48437 | W21: 61919 | X21: 61214.23 | Y21: 2419.35 | Z21: 0
B22: llogari page pagat nga 27 shkurt 2009-31 dhjetor 2013 | U22: =33225+45567*9+53756+9000 -> 506084 | V22: =45591*9+50664+49750+9000+47620 -> 567353 | W22: =47620*9+49785+38549+9000+52865 -> 578779 | X22: =48574*5+50807+37408+49133+49733+49058*3+9000 -> 586125 | Y22: =49058*3+37781+50750+50733*3+51790+51281*2+4490+46566 -> 593312
B24: Gjendja 31.12….. | C24: BKT | D24: 507253775 | E24: lek | Q24: 247 | R24: 372.21 | S24: =R24 -> 372.21 | T24: 372.54 | U24: 0.17 | V24: 0 | W24: 0 | X24: 0 | Y24: 0 | Z24: 463393.52 | AA24: 605013.92 | AB24: 810043.92 | AD24: 835871.92
B25: llogari page paga kaluar Prill 2005-tetor 2006 llogari page janar 2009 llogari page janar 2014- 2020 | Q25: =27624*9+28379 -> 276995 | R25: =28379*8+40593 -> 267625 | U25: 26571 | Z25: =53229*3+55728*5+60228+62657+60228+60228 -> 681668 | AA25: =15660+60228+57256+58742+60625+54289+74890+68472+74890+74716+74890+74890+74890 -> 824438 | AB25: =73418+71313+74890+75140+75142*7+75828 -> 896583 | AD25: 75828
B33: TOTALI | I33: =SUM(I20:I32) -> 0 | J33: =SUM(J20:J32) -> 0 | K33: =SUM(K20:K32) -> 0 | L33: =SUM(L20:L32) -> 0 | M33: =SUM(M20:M32) -> 0 | N33: =SUM(N20:N32) -> 0 | O33: =+O21+O24 -> 0 | P33: =+P21+P24 -> 0 | Q33: =+Q21+Q24 -> 247 | R33: =+R21+R24 -> 372.21 | S33: =+S21+S24 -> 372.21 | T33: =+T21+T24 -> 372.54 | U33: =+U21+U24 -> 9084.17 | V33: =+V21+V24 -> 48437 | ... AD33: =+AD21+AD24 -> 835871.92
B36: Prinderit Hamide dhe Sinan Sharra | C36: BANKA | D36: Nr Llogarise | E36: monedha | H36: 1996 | I36: 1997 | J36: 1998 | K36: 1999 | L36: 2000 | M36: 2001 | N36: 2002 | O36: 2003 | P36: 2004 | Q36: 2005 | R36: 2006 | S36: 2007 | T36: 2008 | U36: 2009 | V36: 2010 | W36: 2011 | X36: 2012 | Y36: 2013 | Z36: 2014 | AA36: 2015 | AB36: 2016 | AC36: TOTAL | AD36: DVETTING
B37: Hamide Sharra 31.12…… | C37: Intesa san paolo | D37: 847639 | E37: lek | X37: 13525 | Y37: 22222.54 | Z37: 112722.54 | AA37: 442.54
B38: kjo llogari eshte perdorur per kalimin e ndihmes ekonomike paaftesi Sinan Sharr | X38: =10600*10+43200+43200+28800 -> 221200 | Y38: =10800*15+11100*4+22200 -> 228600 | Z38: =11100*20+22200*2+13500+13500+3000 -> 296400 | AA38: =11250*18+11530*2+22780*2+2000 -> 273120
B40: Hamide Sharra 31.12…… | C40: RZB | D40: 185095 | E40: Euro
B43: Sinan Sharra 31.12…… | C43: RZB | D43: 185095 | E43: USD | S43: 0 | T43: =5042*KK!R5 -> 458620.32 | U43: =5084.09*KK!S5 -> 477802.78 | V43: 0
B44: Depozite krijuar ne 22.08.2007 ne 100,000 USD | C44: Int. perf. nga depoz. | S44: =(104483.5-100000)*KK!Q5 -> 372265.01
B46: Hamide & Sinan Sharra | C46: Procredit | D46: 170205510001 | E46: Lek | V46: 0
B49: TOTALI | P49: =+P45 -> 0 | Q49: =+Q45 -> 0 | R49: =+R45 -> 0 | S49: =+S45 -> 0 | T49: =+T45 -> 0 | U49: =+U45 -> 0 | V49: =+V45 -> 0 | W49: =+W45 -> 0 | ... AB49: =+AB45 -> 0
H51: 1996 | I51: 1997 | J51: 1998 | K51: 1999 | L51: 2000 | M51: 2001 | N51: 2002 | O51: 2003 | P51: 2004 | Q51: 2005 | R51: 2006 | S51: 2007 | T51: 2008 | U51: 2009 | V51: 2010 | W51: 2011 | X51: 2012 | Y51: 2013 | Z51: 2014 | AA51: 2015 | AB51: 2016 | AC51: TOTAL | AD51: DVETTING
B52: NE DVP | O52: Deklarata para detyres nuk ka deklaruar gjendje cash | P52: nuk deklaron gjendje cash | Q52: Ne rubriken shtesa / pakesime deklaron 1. Likujditet I krijuar ne vitin 2005 shuma 600,000 leke 2. Likujditet nga shfrytezimi I tokes bujqesore 300,000 leke | R52: Ne rubriken shtesa / pakesime deklaron Likujditet I krijuar ne vitin 2006 shumen 600,000 leke dhe Likujditet nga shfrytezimi I tokes bujqesore 100,000 leke | S52: Ne rubriken shtesa / pakesime deklaron Likujditet I krijuar ne vitin 2007 shumen 550,000 leke dhe Likujditet nga shfrytezimi I tokes bujqesore 200,000 leke | T52: Ne rubriken shtesa / pakesime deklaron gjendje CASH krijuar pet vitin 2008 shumen 400,000 leke | U52: pakesime ne vleren 2,000,000 leke nga kursmiet e bera deri ne 31.12.2008 deklaron gjendje CASH 500,000 leke krijuar per vitin 2009 | V52: Deklaron pakesime likujditete ne vleren 838,304 leke deklaron gjendje CASH per vitin 2010 shumen 800,000 leke | W52: deklaron gejndje CASH shume 400,000,leke nga kursimet e te ardhurat e vitit 2011 | X52: Deklaron gjendje CASH shumen 140,000 leke (kursime te vitit 2012 | Y52: Nuk deklaron gjendje cash | Z52: deklaron te ardhura te kursyera nga paga RZBderi ne 31.12.2014 shuma 83216.14leke te ardhura te kursyera nga paga deri ne 31.12.2014 BKT shuma 463,393.52 leke Deklaron gjendje CASH krijuar per vitin 2014 shuma 400,000 leke dhe nga kursimet e te ardhurave shumwn 2,900 Euro | AA52: nuk deklaron cash | AB52: deklaron gjendje CASH 58,000 leke krijuar per 2016 | AD52: Nuk deklaron gjendje CASH
B53: TOTAL BANKA | I53: =+I49+I33+I17 -> 0 | J53: =+J49+J33+J17 -> 0 | K53: =+K49+K33+K17 -> 0 | L53: =+L33+L17 -> 0 | M53: =+M33+M17 -> 0 | N53: =+N33+N17 -> 0 | O53: =+O33+O17 -> 0 | P53: =+P33+P17 -> 0 | Q53: =+Q33+Q17 -> 4815.44 | R53: =+R33+R17 -> 268393.5 | S53: =+S33+S17 -> 57500.04 | ... AD53: =+AD33+AD17 -> 1287604.9
B54: CASH I vitit paraardhes | O54: 0 | P54: 0 | Q54: =+P54 -> 0 | R54: =+Q56 -> 600000 | S54: =+R56 -> 1200000 | T54: =+S56 -> 1750000 | U54: =+T56 -> 2150000 | V54: =+U56 -> 650000 | W54: =+V56 -> 611696 | X54: =+W56 -> 1011696 | Y54: =+X56 -> 1151696 | Z54: 0 | AA54: =+Z56 -> 806319 | AB54: =+AA56 -> 806319 | AD54: 0
B55: Shtesa /pakesime gjate vitit | Q55: 600000 | R55: 600000 | S55: 550000 | T55: 400000 | U55: =-2000000+500000 -> -1500000 | V55: =-838304+800000 -> -38304 | W55: 400000 | X55: 140000 | Z55: =400000+2900*KK!X4 -> 806319 | AB55: 56000
B56: Gjendja e CASH ne analize | Q56: =SUM(Q54:Q55) -> 600000 | R56: =SUM(R54:R55) -> 1200000 | S56: =SUM(S54:S55) -> 1750000 | T56: =SUM(T54:T55) -> 2150000 | U56: =SUM(U54:U55) -> 650000 | V56: =SUM(V54:V55) -> 611696 | W56: =SUM(W54:W55) -> 1011696 | X56: =SUM(X54:X55) -> 1151696 | ... Z56: =SUM(Z54:Z55) -> 806319 | AA56: =+AA54+AA55 -> 806319 | AB56: =SUM(AB54:AB55) -> 862319 | AD56: 0
B57: TOTALI Likujditete | I57: =SUM(I53:I54) -> 0 | J57: =SUM(J53:J54) -> 0 | K57: =SUM(K53:K54) -> 0 | L57: =SUM(L53:L54) -> 0 | M57: =SUM(M53:M54) -> 0 | N57: =SUM(N53:N54) -> 0 | O57: =SUM(O53:O54) -> 0 | P57: =SUM(P53:P54) -> 0 | Q57: =+Q53+Q56 -> 604815.44 | R57: =+R53+R56 -> 1468393.5 | S57: =+S53+S56 -> 1807500 | T57: =+T53+T56 -> 2202998.1 | U57: =+U53+U56 -> 659095.6 | V57: =+V53+V56 -> 660366.04 | W57: =+W53+W56 -> 1073923.1 | X57: =+X53+X56 -> 1212850.1 | ... AD57: =+AD53+AD56 -> 1287604.9
B58: Ndryshim Likujditeti | I58: =+I57 -> 0 | J58: =+J57-I57 -> 0 | K58: =+K57-J57 -> 0 | L58: =+L57-K57 -> 0 | M58: =+M57-L57 -> 0 | N58: =+N57-M57 -> 0 | O58: =+O57-N57 -> 0 | P58: =+P57-O57 -> 0 | Q58: =+Q57-P57 -> 604815.44 | ... AB58: =+AB57-AA57 -> 666773.15 | AD58: =+AD53-AB53-AB55 -> 9673
V60: =U56+800000-838304 -> 611696 | W60: =V60+W55 -> 1011696 | X60: =W60+140000 -> 1151696
Q61: =Q55+Q24+Q10 -> 604815.44 | R61: =R55+Q55+R24+R10 -> 1468393.5 | S61: =S55+R55+Q55+S24+S10 -> 1807500 | T61: =T55+S55+R55+Q55+T24+T10 -> 2202998.1
Q63: =Q61-E61 -> 604815.44 | R63: =R61-Q61 -> 863578.06 | S63: =S61-R61 -> 339106.54 | T63: =T61-S61 -> 395498.02
Q65: =Q53 -> 4815.44 | R65: =R53 -> 268393.5 | S65: =S53 -> 57500.04 | T65: =T53 -> 52998.06 | U65: =U53 -> 9095.6 | V65: =V53 -> 48670.04 | W65: =W53 -> 62227.06 | X65: =X53 -> 61154.06 | ... AB65: =AB53 -> 1221931.9
Q66: =Q55 -> 600000 | R66: =Q66+600000 -> 1200000 | S66: =S55+R66 -> 1750000 | T66: =T55+S66 -> 2150000 | U66: =500000+T66-2000000 -> 650000 | V66: =U66+800000-838304 -> 611696 | W66: =V66+400000 -> 1011696 | X66: =W66+140000 -> 1151696 | Y66: =X66 -> 1151696 | Z66: =400000+2900*KK!X4 -> 806319 | AA66: =Z66 -> 806319 | AB66: =AA66+58000 -> 864319
Q67: =SUM(Q65:Q66) -> 604815.44 | R67: =SUM(R65:R66) -> 1468393.5 | S67: =SUM(S65:S66) -> 1807500 | T67: =SUM(T65:T66) -> 2202998.1 | U67: =SUM(U65:U66) -> 659095.6 | V67: =SUM(V65:V66) -> 660366.04 | W67: =SUM(W65:W66) -> 1073923.1 | X67: =SUM(X65:X66) -> 1212850.1 | ... AB67: =SUM(AB65:AB66) -> 2086250.9
Q68: =Q67-P67 -> 604815.44 | R68: =R67-Q67 -> 863578.06 | S68: =S67-R67 -> 339106.54 | T68: =T67-S67 -> 395498.02 | U68: =U67-T67 -> -1543902.5 | V68: =V67-U67 -> 1270.44 | W68: =W67-V67 -> 413557.02 | X68: =X67-W67 -> 138927 | ... AB68: =AB67-AA67 -> 668773.15
X72: 143042
X73: =X72-W53 -> 80814.94
W74: ```````````````````````````````````````````````` | X74: =X55/12*9.5 -> 110833.33
X75: =X54+X74-W57 -> 48606.273 | Y75: =X72+X75 -> 191648.27

Sheet Analiza fin. 2005-2008
G3: (në lekë)
B4: Nr. | C4: PËRSHKRIMI/PERIUDHA | D4: 2005 | E4: 2006 | F4: 2007 | G4: 2008
B6: I | C6: TË ARDHURA | D6: =SUM(D7:D9) -> 1145795 | E6: =SUM(E7:E9) -> 1093156 | F6: =SUM(F7:F9) -> 1029775 | G6: =SUM(G7:G9) -> 1623858
B7: 1 | C7: Të ardh._S.R. | D7: ='Te Ardhurat '!M5 -> 818245 | E7: ='Te Ardhurat '!N5 -> 815652 | F7: ='Te Ardhurat '!O5+'Te Ardhurat '!O6 -> 841418 | G7: ='Te Ardhurat '!P6 -> 905278
B8: 2 | C8: Të ardh._B.S.R. | D8: ='Te Ardhurat '!M20 -> 327550 | E8: ='Te Ardhurat '!N20 -> 277504 | F8: ='Te Ardhurat '!O22+'Te Ardhurat '!O24 -> 188357 | G8: ='Te Ardhurat '!P22+'Te Ardhurat '!P24 -> 318580
B9: 4 | C9: Shitja_"M.Benz"_ më 09.09.2008 | D9: 0 | E9: 0 | F9: 0 | G9: 400000
B11: II | C11: SHPENZIME | D11: =SUM(D12:D14) -> 438228 | E11: =SUM(E12:E14) -> 438228 | F11: =SUM(F12:F14) -> 547212 | G11: =SUM(G12:G16) -> 767489.44
B12: 1 | C12: Shpenz.jetike | D12: =KK!O14 -> 438228 | E12: =KK!P14 -> 438228 | F12: =KK!Q14 -> 546480 | G12: =KK!R14 -> 546480
B13: 2 | C13: Shpenz.udhët. | D13: 0 | E13: 0 | F13: 0 | G13: =TIMS!C6 -> 3695.475
B14: 3 | C14: Taksat vend._tokës bujq. | D14: 0 | E14: 0 | F14: =2196/3 -> 732 | G14: =F14 -> 732 | I14: 2196
B15: 4 | C15: Paguar int.kredie_NBG Albania ShA | D15: 0 | E15: 0 | F15: 0 | G15: =1726.53*KK!R4 -> 212678.28
B16: 5 | C16: Komisione për transferimin e vlerës | D16: 0 | E16: 0 | F16: 0 | G16: =32*121.99 -> 3903.68
B18: III | C18: PASURI | D18: =SUM(D19:D21) -> 604815.44 | E18: =SUM(E19:E21) -> 863578.06 | F18: =SUM(F19:F21) -> 339106.54 | G18: =SUM(G19:G21) -> 12641685
B19: 1 | C19: Ap.banimi_128.1 m2_23.06.2008 | D19: 0 | E19: 0 | F19: 0 | G19: =94830*121.99 -> 11568312 | J19: 121.99 | K19: 23.06.2008
B20: 2 | C20: Autom."Daimler Chrysler"_14.11.2008 | D20: 0 | E20: 0 | F20: 0 | G20: =5500*123.25 -> 677875 | I20: euro | J20: 123.25 | K20: 14.11.2008
B21: 3 | C21: Ndrysh.gjendje lik. | D21: =' Likujditete'!Q63 -> 604815.44 | E21: =' Likujditete'!R63 -> 863578.06 | F21: =' Likujditete'!S63 -> 339106.54 | G21: =' Likujditete'!T63 -> 395498.02
B23: IV | C23: DETYRIME | D23: =SUM(D24:D25) -> 0 | E23: =SUM(E24:E25) -> 0 | F23: =SUM(F24:F25) -> 0 | G23: =SUM(G24:G26) -> 11479548
B24: 1 | C24: Det.mbetur ndaj shoq,"KDK" ShPk | D24: 0 | E24: 0 | F24: 0 | G24: =48830*121.99 -> 5956771.7
B25: 2 | C25: Kredi bankare_NBG ShA | D25: 0 | E25: 0 | F25: 0 | G25: =46000*121.67 -> 5596820 | J25: 121.67 | K25: 01.08.2008 | M25: 48830
B26: 3 | C26: Shlyer princ.kredie në NBG Albania | D26: 0 | E26: 0 | F26: 0 | G26: =-601.09*KK!R4 -> -74043.769
M27: 46000
B28: V | C28: PASURI NETO: V = III-IV | D28: =D18-(D23) -> 604815.44 | E28: =E18-(E23) -> 863578.06 | F28: =F18-(F23) -> 339106.54 | G28: =G18-(G23) -> 1162136.8 | M28: =SUM(M25:M27) -> 94830
M29: =M28-M27 -> 48830
B30: VI | C30: REZULTATI FIN. VI = I-II-V | D30: =D6-D11-D28 -> 102751.56 | E30: =E6-E11-E28 -> -208650.06 | F30: =F6-F11-F28 -> 143456.46 | G30: =G6-G11-G28 -> -305768.23
H32: =E30+G30 -> -514418.29

Sheet Anal.fin.shly.pjes.
D2: =KK!T14 -> 546480 | E2: =KK!U14 -> 546480 | G2: =KK!V14 -> 558192 | H2: =KK!X14 -> 879992
D4: =D5/30 -> 1518 | E4: =E5/30 -> 1518 | H4: =H5/30 -> 2444.4222
D5: =D2/12 -> 45540 | E5: =E2/12 -> 45540 | G5: =G2/12*7.5 -> 348870 | H5: =H2/12 -> 73332.667
C7: 31.12.2009 | D7: 25.11.2010 | E7: 01.08.2011 | F7: 30.12.2011 | G7: 13.08.2012 | H7: 07.11.2014
A8: A.Sharra | B8: RZB | D8: =1079.55 -> 1079.55 | E8: 35819.65 | F8: =[2]sp_NRP_Balance!$L$533 -> 308.06 | G8: =[2]sp_NRP_Balance!$L$561 -> 225.03 | H8: 60641.78
A9: F.Sharra | B9: TB | D9: 12067 | E9: 47671 | F9: 61919 | G9: =[3]Sheet1!$W$112 -> 242026.88 | H9: 342797
C10: =' Likujditete'!U53 -> 9095.6 | D10: =SUM(D8:D9) -> 13146.55 | E10: =SUM(E8:E9) -> 83490.65 | F10: =SUM(F8:F9) -> 62227.06 | G10: =SUM(G8:G9) -> 242251.91 | H10: =SUM(H8:H9) -> 403438.78 | I10: =' Likujditete'!Y53 -> 3017.83 | J10: =H10-I10 -> 400420.95
D11: =D10-C10 -> 4050.95
D13: 3405 | E13: 3290 | F13: 2060 | G13: 3090 | H13: 15550
B14: Nr. | C14: PERIUDHA | D14: 01.01.– 25.11.2010 | E14: 01.01.- 01.08.2011 | F14: 02.08.-30.12.2011 | G14: 01.01.-13.08.2012 | H14: 01.01.-07.11.2014
D15: I | E15: II | F15: III | G15: IV | H15: V
B16: I | C16: TË ARDHURA | D16: =SUM(D17:D18) -> 1207450 | E16: =SUM(E17:E18) -> 843899 | F16: =SUM(F17:F18) -> 663371 | G16: =SUM(G17:G18) -> 1024913 | H16: =SUM(H17:H19) -> 1664298
B17: 1 | C17: Paga_S.R. | D17: =737467 -> 737467 | E17: =517465 -> 517465 | F17: 411026 | G17: =693828 -> 693828 | H17: 1058086
B18: 2 | C18: Paga_B.S.R. | D18: 469983 | E18: =[4]Sheet1!$AG$19 -> 326434 | F18: =252345 -> 252345 | G18: 331085 | H18: =53229*3+55728*3+45000+55728*2+60228+62657 -> 606212
B19: 3 | C19: Paradh.shitja e ban.K.K. | D19: 0 | E19: 0 | F19: 0 | G19: 0 | H19: 0 | J19: 01.10.2014 | K19: 139.87
B21: II | C21: SHPENZIME | D21: =SUM(D22:D25) -> 717617.76 | E21: =SUM(E22:E25) -> 802927.85 | F21: =SUM(F22:F25) -> 315888.91 | G21: =SUM(G22:G25) -> 454917.48 | H21: =SUM(H22:H25) -> 882827.56 | N21: 45968
B22: 1 | C22: Shenz.jetike | D22: =45540*10+25*1518 -> 493350 | E22: =E5*7+E4 -> 320298 | F22: =E2-E22 -> 226182 | G22: =G2/12*7.5 -> 348870 | H22: =H5*10+7*H4 -> 750437.62 | N22: 5000
B23: 2 | C23: Shpenz.udh. | D23: 0 | E23: =TIMS!F6 -> 338835 | F23: 0 | G23: 0 | H23: 0 | N23: 285 | P23: 31.5.2013
B24: 3 | C24: Int.kredie | D24: ='Kredi ne NBG '!H50*KK!T4 -> 222917.76 | E24: ='Kredi ne NBG '!J58*KK!U4 -> 142444.85 | F24: ='Kredi ne NBG '!J59*KK!U4 -> 89706.912 | G24: ='Kredi ne NBG '!L58*KK!V4 -> 106047.48 | H24: ='Kredi ne NBG '!P53*KK!X4 -> 132389.94 | N24: 24400
B25: 4 | C25: Taksa toke+ndërt. | D25: =2700/2 -> 1350 | E25: =D25 -> 1350 | F25: 0 | G25: 0 | H25: 0 | N25: 5000 | P25: 140.45
N26: 230
B27: III | C27: PASURI | D27: =SUM(D28:D28) -> 4050.95 | E27: =SUM(E28:E29) -> 34820.61 | F27: =SUM(F28:F29) -> 27406.45 | G27: =SUM(G28:G29) -> 180024.85 | H27: =SUM(H28:H29) -> 400420.95 | N27: =SUM(N21:N26) -> 80883 | P27: 40000
B28: 1 | C28: Ndrysh.gjend.lik.bankë | D28: =D10-C10 -> 4050.95 | E28: =E10-' Likujditete'!V53 -> 34820.61 | F28: =F10-E28 -> 27406.45 | G28: =G10-' Likujditete'!W53 -> 180024.85 | H28: =J10 -> 400420.95 | N28: =80883 -> 80883 | P28: =P27/P25 -> 284.79886
B29: 2 | C29: Kursime dekl. | D29: 0 | E29: 0 | F29: 0 | G29: 0 | N29: =N27-N28 -> 0
B31: IV | C31: DETYRIME | D31: =D32 -> -96792.213 | E31: =E32 -> -62696.922 | F31: =F32 -> -752925.95 | G31: =G32 -> -54676.628 | H31: =H32 -> -76707.423
B32: 1 | C32: Princ.kredie NBG | D32: =-'Kredi ne NBG '!G50*KK!T4 -> -96792.213 | E32: =-'Kredi ne NBG '!I58*KK!U4 -> -62696.922 | F32: =-'Kredi ne NBG '!I59*KK!U4 -> -752925.95 | G32: =-'Kredi ne NBG '!K58*KK!V4 -> -54676.628 | H32: =-'Kredi ne NBG '!O53*KK!X4 -> -76707.423
B34: V | C34: PASURI NETO | D34: =D27-(D31) -> 100843.16 | E34: =E27-(E31) -> 97517.532 | F34: =F27-(F31) -> 780332.4 | G34: =G27-(G31) -> 234701.48 | H34: =H27-(H31) -> 477128.37
B36: VI | C36: REZ.FIN: VI=I-II-V | D36: =D16-D21-D34 -> 388989.08 | E36: =E16-E21-E34 -> -56546.383 | F36: =F16-F21-F34 -> -432850.31 | G36: =G16-G21-G34 -> 335294.04 | H36: =H16-H21-H34 -> 304342.07
C37: REZ: (në euro) | D37: =D36/KK!T4 -> 2802.3131 | E37: =E36/KK!U4 -> -408.86756 | F37: =F36/KK!U4 -> -3129.7925 | G37: =G36/KK!V4 -> 2399.757 | H37: =H36/KK!X4 -> 2172.1652
C38: Pagesat e pjes. | D38: =D13 -> 3405 | E38: =E13 -> 3290 | F38: =F13 -> 2060 | G38: =G13 -> 3090 | H38: =H13 -> 15550
D39: =D37-D38 -> -602.6869 | G39: =G37-G38 -> -690.24304 | H39: =H37-H38 -> -13377.835
C41: pa konsideruar paradhënien 20.000 euro, nga shitja e banesës në Kodër Kamëz | H41: 20000
C42: pa konsid të ardhura nga shitja e produkteve bujqësore, me arsyetimin në vijim të relacionit | H42: ok justifikon
C43: pa konsideruar pjesën e kursimeve cash deklaruar në deklaratat periodike të viteve përkatëse e cila mund të
C44: përllogaritej proporcionalisht deri në fund të periudhës së analizuar.
D46: 138.61 | E46: 139.5 | F46: =KK!U4 -> 138.3 | G46: 136.8 | H46: 139.16
D47: =D36/D46 -> 2806.3566 | E47: =E36/E46 -> -405.35042 | F47: =F36/F46 -> -3129.7925 | G47: =G36/G46 -> 2450.9798 | H47: =H36/H46 -> 2186.9939
D49: =D47-D38 -> -598.64345 | E49: =E47-E38 -> -3695.3504 | F49: =F47-F38 -> -5189.7925 | G49: =G47-G38 -> -639.02016 | H49: =H47-H38 -> -13363.006
D50: =D49*D46 -> -82977.968 | E50: =E49*E46 -> -515501.38 | F50: =F49*F46 -> -717748.31 | G50: =G49*G46 -> -87417.958 | H50: =H49*H46 -> -1859595.9
H51: 20000
H52: =H49+H51 -> 6636.9939

Sheet Te Ardhurat 
B3: Subjekti deklaron ne DV | C3: Dokumentuar ILDKPI | D3: 1996 | E3: 1997 | F3: 1998 | G3: 1999 | H3: 2000 | I3: 2001 | J3: 2002 | K3: 2003 | L3: 2004 | M3: 2005 | N3: 2006 | O3: 2007 | P3: 2008 | Q3: 2009 | R3: 2010 | S3: 2011 | T3: 2012 | U3: 2013 | V3: 2014 | W3: 2015 | X3: 2016 | Y3: Total | Z3: DV 2017 | AA3: 2017 | AB3: 2018 | AC3: 2019
B4: Page OPGJ Gjykata e shkalles se pare Elbasan 01.10.1996-15.07.2004 3,064,193 leke | C4: Vertetim Nr 734 Prot 25.01.2017 nga Gjykata e shkalles se pare ELBASAN | D4: 60154 | E4: 231024 | F4: 360525 | G4: 390615 | H4: 442564 | I4: 446705 | J4: 414633 | K4: 473716 | L4: 244530 | Y4: =SUM(D4:X4) -> 3064466
B5: Page Prokuror ne Gjykaten e shkalles se pare Tirane 16.07.2004-30.04.2007 2,284,783 leke | C5: Vertetim dt 17.10.2016 ngaProkuroria ne Gjykaten e shkalles se pare Tirane | L5: 361664 | M5: 818245 | N5: 815652 | O5: 289222 | Y5: =SUM(D5:X5) -> 2284783
B6: Page Prokuror ne Gjykaten e shkalles se pare Diber 01.05.2007-07.10.2010 2,924,660 leke | C6: Vertetim nga Prokuroria ne Gjykaten e shkalles se pare Diber | O6: 552196 | P6: 905278 | Q6: 851469 | R6: 615717 | Y6: =SUM(D6:X6) -> 2924660
B7: Page Prokuror ne Gjykaten e shkalles se pare Durres Tetor 2010- 31.12.2016 6,428,353 leke | C7: Vertetim nga Prokuroria ne Gjykaten e shkalles se pare Durres dt 11.01.2017 | R7: 198569 | S7: 942368 | T7: 983776 | U7: 917794 | V7: 1091512 | W7: 1123493 | X7: 1170841 | Y7: =SUM(D7:X7) -> 6428353
B8: Page Prokuror ne Gjykaten e shkalles se pare Durres te ardhurat vjetore per 2017 shuma 1,264,368 leke per 2018 shuma 1,227,031 leke per 2019 shuma 2,481,785 leke | C8: Vertetim nga Prokuroria ne Gjykaten e shkalles se pare Durres dt 09.03.2018 | Z8: =+' Likujditete'!AD11 -> 99845 | AA8: 1264368 | AB8: 1227031 | AC8: 2481785
B9: Total | D9: =SUM(D4:D7) -> 60154 | E9: =SUM(E4:E7) -> 231024 | F9: =SUM(F4:F7) -> 360525 | G9: =SUM(G4:G7) -> 390615 | H9: =SUM(H4:H7) -> 442564 | I9: =SUM(I4:I7) -> 446705 | J9: =SUM(J4:J7) -> 414633 | K9: =SUM(K4:K7) -> 473716 | ... U9: =SUM(U4:U7) -> 917794 | V9: =SUM(V4:V8) -> 1091512 | W9: =SUM(W4:W8) -> 1123493 | X9: =SUM(X4:X8) -> 1170841 | Y9: =SUM(Y4:Y8) -> 14702262 | Z9: =SUM(Z4:Z8) -> 99845 | AA9: =SUM(AA4:AA8) -> 1264368 | AB9: =SUM(AB4:AB8) -> 1227031 | AC9: =SUM(AC4:AC8) -> 2481785
B11: Paga te kaluara ne Banke | M11: =+' Likujditete'!Q11 -> 648255 | N11: =+' Likujditete'!R11 -> 835937 | O11: =+' Likujditete'!S11 -> 912971 | P11: =+' Likujditete'!T11 -> 888580 | Q11: =+' Likujditete'!U11 -> 808684 | R11: =+' Likujditete'!V11 -> 829725 | S11: =+' Likujditete'!W11 -> 928491 | T11: =+' Likujditete'!X11 -> 994162 | ... X11: =+' Likujditete'!AB11 -> 1164829 | Z11: =+' Likujditete'!AD11 -> 99845 | AA11: =+' Likujditete'!#REF! -> #REF! | AB11: =+' Likujditete'!#REF! -> #REF! | AC11: =+' Likujditete'!#REF! -> #REF!
B18: Te ardhurat e b/shortes se subjektit | C18: Dokumentuar ILDKPI | D18: 1996 | E18: 1997 | F18: 1998 | G18: 1999 | H18: 2000 | I18: 2001 | J18: 2002 | K18: 2003 | L18: 2004 | M18: 2005 | N18: 2006 | O18: 2007 | P18: 2008 | Q18: 2009 | R18: 2010 | S18: 2011 | T18: 2012 | U18: 2013 | V18: 2014 | W18: 2015 | X18: 2016 | Y18: Total | Z18: DV 2017 | AA18: 2017 | AB18: 2018 | AC18: 2019
B19: Barre lindje per djalin 01.07.1997-12.06.1998 e padokumentuar per shkak te mos gjetjes se dokumentacionit ne DRSSHT | E19: xxx | F19: xxx | Y19: =SUM(D19:X19) -> 0
B20: Page juriste Ndermarrja e trajtimit te studenteve nr ! Tirane Maj 1999-Shtator 2006 1,765,318 Leke | C20: Vertetim nga ISSH mbi bazen e vleresueshme dhe pagen neto mesatare si juriste ne shoqerine Rezidenca Studentore Universitare nr 1 sha Tirane | G20: 70634 | H20: 160873 | I20: 177089 | J20: 132813 | K20: 291424 | L20: 327431 | M20: 327550 | N20: 277504 | Y20: =SUM(D20:X20) -> 1765318
B21: Barre lindje per vajzen 17.12.2001- 31.05.2002 73,689 leke | C21: Vertetim nga Bashkia Tirane nr. 47 prot., dt. 25.01.2017 | I21: =73689/6 -> 12281.5 | J21: =73689/6*5 -> 61407.5 | Y21: =SUM(D21:X21) -> 73689
C22: Vertetim nga ISSH nr EXTRA prot dt 26.01.2017 Te ardhura nga Fondi I vecante 78,360 leke | O22: =78360/10 -> 7836 | P22: =78360/10 -> 7836 | Q22: =78360/10 -> 7836 | R22: =78360/10 -> 7836 | S22: =78360/10 -> 7836 | T22: =78360/10 -> 7836 | U22: =78360/10 -> 7836 | V22: =78360/10 -> 7836 | ... X22: =78360/10 -> 7836 | Y22: =SUM(D22:X22) -> 78360
B23: Kete e konsiderojme ne analize sepse perputhet me pagat ne banke | C23: Vertetim nga ISSH nr 20 prot dt 29.01.2020 | O23: 180450 | P23: 310742 | Q23: 490430 | R23: 567353 | S23: 569779 | T23: 577125 | U23: 588942 | V23: 741896 | W23: 808778 | X23: 896583 | Y23: =SUM(D23:X23) -> 5732078 | Z23: 75828 | AA23: 944538 | AB23: 957324 | AC23: 959965
B24: Page Juriste ISSH 01.05.2007-31.12.2016 5,833,290 Leke | C24: Vertetim nga ISSH nr EXTRA prot dt 26.01.2017 Te ardhura nga paga 5,754,930 leke | O24: =18268+18267+22434+21569+21569+26138+26138+26138 -> 180521 | P24: =5*26138+23649+2*23405+22160+31893+2*27771 -> 310744 | Q24: =27771+33226+45566*9+53756 -> 524847 | R24: =46591*9+50710+49750+47620 -> 567399 | S24: =47620*3+49785+47620+38549+47620*5+52865 -> 569779 | T24: =48574*3+50807+48574*2+37408+49133+49733+49058*3 -> 577125 | U24: =49058*2+37781+49058+50750+50773*3+51790+51281*2+46566 -> 588942 | V24: =53229*3+55728*5+60228*3+62657 -> 681668 | W24: =3*60228+61170+55718+77060*6+70457 -> 830389 | X24: =75548+73390+77060+77311+77312*7+78016 -> 922509 | Y24: =SUM(D24:X24) -> 5753923 | AA24: konfirmo me banke
B25: Total | D25: =SUM(D19:D23) -> 0 | E25: =SUM(E19:E23) -> 0 | F25: =SUM(F19:F23) -> 0 | G25: =SUM(G19:G23) -> 70634 | H25: =SUM(H19:H23) -> 160873 | I25: =SUM(I19:I23) -> 189370.5 | J25: =SUM(J19:J23) -> 194220.5 | K25: =SUM(K19:K23) -> 291424 | ... AC25: =SUM(AC19:AC23) -> 959965
B27: Paga te kaluara ne Banke | Q27: =+' Likujditete'!U22 -> 506084 | R27: =+' Likujditete'!V22 -> 567353 | S27: =+' Likujditete'!W22 -> 578779 | T27: =+' Likujditete'!X22 -> 586125 | U27: =+' Likujditete'!Y22 -> 593312 | V27: =+' Likujditete'!Z25 -> 681668 | W27: =+' Likujditete'!AA25 -> 824438 | X27: =+' Likujditete'!AB25 -> 896583 | Y27: =SUM(Q27:X27) -> 5234342
B31: Te ardhura te tjera | D31: 1996 | E31: 1997 | F31: 1998 | G31: 1999 | H31: 2000 | I31: 2001 | J31: 2002 | K31: 2003 | L31: 2004 | M31: 2005 | N31: 2006 | O31: 2007 | P31: 2008 | Q31: 2009 | R31: 2010 | S31: 2011 | T31: 2012 | U31: 2013 | V31: 2014 | W31: 2015 | X31: 2016 | Y31: Total | Z31: DV 2017 | AA31: 2017
B32: Te ardhura nga shfrytezimi nder vite I tokes prane baneses ne K Kamez dhe tokes bujqesore ne emer te babait te saj ne Shengjin te Nj adm Shengjergj 4,220,000 leke
B33: Te ardhura nga shitja e automjetit Mercedes Benz dt 09.09.2008 shuma 400,000 leke | C33: Kontrate shitblerje nr 4814 nr 1468/3 dt 09.09.2008 cmimi I shitjes marre nga shitesi eshte 400,000 lekw | P33: 400000
B34: Te ardhura nga shitja e automjetit Mercedes Benz dt 15.03.2016 shuma 3,800 Euro | C34: KOntrate shitblerje nr 2980 nr 1948 dt 15.03.2016 cmimi I shitjes marre nga shitesi eshte 3,800 Euro | X34: =3800*KK!Z4 -> 514026
B36: Total | D36: =SUM(D32:D35) -> 0 | E36: =SUM(E32:E35) -> 0 | F36: =SUM(F32:F35) -> 0 | G36: =SUM(G32:G35) -> 0 | H36: =SUM(H32:H35) -> 0 | I36: =SUM(I32:I35) -> 0 | J36: =SUM(J32:J35) -> 0 | K36: =SUM(K32:K35) -> 0 | ... AA36: =SUM(AA32:AA35) -> 0
B38: PERIUDHA | D38: 1996 | E38: 1997 | F38: 1998 | G38: 1999 | H38: 2000 | I38: 2001 | J38: 2002 | K38: 2003 | L38: 2004 | M38: 2005 | N38: 2006 | O38: 2007 | P38: 2008 | Q38: 2009 | R38: 2010 | S38: 2011 | T38: 2012 | U38: 2013 | V38: 2014 | W38: 2015 | X38: 2016 | Y38: Total | Z38: DV 2017 | AA38: 2017
B39: Te ardhurat Totale | E39: =+E9+E25+E36 -> 231024 | F39: =+F9+F25+F36 -> 360525 | G39: =+G9+G25+G36 -> 461249 | H39: =+H9+H25+H36 -> 603437 | I39: =+I9+I25+I36 -> 636075.5 | J39: =+J9+J25+J36 -> 608853.5 | K39: =+K9+K25+K36 -> 765140 | L39: =+L9+L25+L36 -> 933625 | ... AA39: =+AA9+AA25+AA36 -> 2208906
S42: =S27+S11 -> 1507270

Sheet Të ardh_.S.Sharra
B2: 13.04.2013
B3: Kur e ka marre huane
B4: analiza e babait per 4000 eruo
D5: =2427296 -> 2427296 | E5: =E13/5516 -> 4.000422
B6: TE ARDHURAT
B7: Hamide Besim Sharra | C7: Te ardhurat periudha | D7: Pension pleqerie | E7: 1989 | F7: 1990 | G7: 1991 | H7: 1992 | I7: 1993 | J7: 1994 | K7: 1995 | L7: 1996 | M7: 1997 | N7: 1998 | O7: 1999 | P7: 2000 | Q7: 2001 | R7: 2002 | S7: 2003 | T7: 2004 | U7: 2005 | V7: 2006 | W7: 2007 | X7: 2008 | Y7: 2009 | Z7: 2010 | AA7: 2011 | AB7: 2012 | AC7: mars 2013
B8: vertetim nr 442 prot date 19.10.2021 | C8: pensioni Hamide sipas ISSH shuma totale 03.07.1994-31.10.2021 eshte 2,014,575 leke | J8: 5587.2857 | K8: 9845 | L8: 6827.6818 | M8: 10970.727 | N8: 14047 | O8: 14461.412 | P8: 11602.588 | Q8: 16276.5 | R8: 20250 | S8: 22614 | T8: 32474.743 | U8: 16747.4 | V8: 55307.34 | W8: 62764 | X8: 69336.5 | Y8: 82679.143 | Z8: 98981.357 | AA8: 112457 | AB8: 115862.12 | AC8: 29354.308
B9: Vertetim leshuar ne 15.06.1994 | C9: 1janar -31 dhjetor 1993 ka paguar kontribut te sigurimeve shoqerore si Bujk privat shumen 1620 leke MA 409617/315393 dt.21.07.1993 dhe per periudhen 01.01.1994-01.06.1994 shumen 823 leke | I9: =+(1620*100)/9.4 -> 17234.043 | J9: =+(823*100)/9.4 -> 8755.3191
D10: TOTALI | E10: =+E8+E9 -> 0 | F10: =+F8+F9 -> 0 | G10: =+G8+G9 -> 0 | H10: =+H8+H9 -> 0 | I10: =+I8+I9 -> 17234.043 | J10: =+J8+J9 -> 14342.605 | K10: =+K8+K9 -> 9845 | L10: =+L8+L9 -> 6827.6818 | ... AC10: =+AC8+AC9 -> 29354.308
E11: 07.09.1989-31.12.1989
B12: Sinan Hamit Sharra | C12: Te ardhurat periudha | D12: Pension pleqerie | E12: 1989 | F12: 1990 | G12: 1991 | H12: 1992 | I12: 1993 | J12: 1994 | K12: 1995 | L12: 1996 | M12: 1997 | N12: 1998 | O12: 1999 | P12: 2000 | Q12: 2001 | R12: 2002 | S12: 2003 | T12: 2004 | U12: 2005 | V12: 2006 | W12: 2007 | X12: 2008 | Y12: 2009 | Z12: 2010 | AA12: 2011 | AB12: 2012 | AC12: 2013
C13: nga Shtator 1989 deri ne nentor 2016 Shuma totale 2,427,296 vlera 36 vjet e 8 muaj vlera e pensionit 5516 leke ne muaj | E13: 22066.328 | F13: 66198.984 | G13: 66198.984 | H13: 66198.984 | I13: 66198.984 | J13: 66198.984 | K13: 66198.984 | L13: 66198.984 | M13: 66198.984 | N13: 66198.984 | O13: 66198.984 | P13: 66198.984 | Q13: 66198.984 | R13: 66198.984 | S13: 66198.984 | T13: 66198.984 | U13: 66198.984 | V13: 66198.984 | W13: 66198.984 | X13: 66198.984 | Y13: 66198.984 | Z13: 66198.984 | AA13: 66198.984 | AB13: 66198.984 | AC13: 16549.746
B14: 5516 | C14: Ndihme ekonomike paaftesi (Nga llogaria bankare ne intesa san paolo) | AB14: =+X21 -> 221200 | AC14: =+Y21/12*3 -> 57150
D15: TOTALI | E15: =+E14+E13 -> 22066.328 | F15: =+F14+F13 -> 66198.984 | G15: =+G14+G13 -> 66198.984 | H15: =+H14+H13 -> 66198.984 | I15: =+I14+I13 -> 66198.984 | J15: =+J14+J13 -> 66198.984 | K15: =+K14+K13 -> 66198.984 | L15: =+L14+L13 -> 66198.984 | ... AC15: =+AC14+AC13 -> 73699.746
B16: 36.8
B17: =B16*5516 -> 202988.8
B18: LIKUJDITETE
B19: Prinderit Hamide dhe Sinan Sharra | C19: BANKA | D19: Nr Llogarise | E19: monedha | F19: 1994 | G19: 1995 | H19: 1996 | I19: 1997 | J19: 1998 | K19: 1999 | L19: 2000 | M19: 2001 | N19: 2002 | O19: 2003 | P19: 2004 | Q19: 2005 | R19: 2006 | S19: 2007 | T19: 2008 | U19: 2009 | V19: 2010 | W19: 2011 | X19: 2012 | Y19: 2013 | Z19: 2014 | AA19: 2015 | AB19: 2016 | AC19: TOTAL | AD19: DVETTING | AE19: 2017 | AF19: 2018 | AG19: 2019
B20: Hamide Sharra 31.12…… | C20: Intesa san paolo | D20: 847639 | E20: lek | X20: 13525 | Y20: 22222.54 | Z20: 112722.54 | AA20: 442.54
B21: kjo llogari eshte perdorur per kalimin e ndihmes ekonomike paaftesi Sinan Sharra | X21: 221200 | Y21: 228600 | Z21: 296400 | AA21: 273120
B22: Sinan Hamit Sharra pension verberie | C22: Shkresa nr 684/2 dt 22.02.2022 nga Bashkia Tirane | X22: =10600*10+11200+43200 -> 160400 | Y22: =10800*8+11100 -> 97500 | Z22: =11100*11+13500 -> 135600 | AA22: =11259*9+11530+11390*2 -> 135641 | AB22: =11390*9+11630 -> 114140
B23: Hamide Sharra Pagese kUjdestarie per bshortin | C23: Shkresa nr 684/2 dt 22.02.2022 nga Bashkia Tirane | X23: =10600*10+11200+10800 -> 128000 | Y23: =10800*8+11100 -> 97500 | Z23: =11100*11+13500 -> 135600 | AA23: =11259*9+11530+11390*2 -> 135641 | AB23: =11390*9+11630 -> 114140
B24: Hamide Sharra 31.12…… | C24: RZB | D24: 185095 | E24: Euro | AE24: =+(75000-50000)*[5]KK!AA4 -> 3323750
B27: Sinan Sharra 31.12…… | C27: RZB | D27: 185095 | E27: USD | S27: =100000*[5]KK!Q5 -> 8303000 | T27: =5523.55*[5]KK!Q5 -> 458620.36 | U27: =5042*[5]KK!R5 -> 458620.32 | V27: 0
B28: Depozite krijuar ne 22.08.2007 ne 100,000 USD | C28: Interesi perfituar nga depozita | S28: 372265.01
B31: TOTALI | F31: =+F27+F24+F20 -> 0 | G31: =+G27+G24+G20 -> 0 | H31: =+H27+H24+H20 -> 0 | I31: =+I27+I24+I20 -> 0 | J31: =+J27+J24+J20 -> 0 | K31: =+K27+K24+K20 -> 0 | L31: =+L27+L24+L20 -> 0 | M31: =+M27+M24+M20 -> 0 | ... AH31: =+AH27+AH24+AH20 -> 0
B32: Ndryshim likujditeti | F32: =+F31 -> 0 | G32: =+G31-F31 -> 0 | H32: =+H31-G31 -> 0 | I32: =+I31-H31 -> 0 | J32: =+J31-I31 -> 0 | K32: =+K31-J31 -> 0 | L32: =+L31-K31 -> 0 | M32: =+M31-L31 -> 0 | N32: =+N31-M31 -> 0 | ... AF32: =+AF31-AE31 -> -3323750
B35: ANALIZA
C36: 1989 | D36: 1990 | E36: 1991 | F36: 1992 | G36: 1993 | H36: 1994 | I36: 1995 | J36: 1996 | K36: 1997 | L36: 1998 | M36: 1999 | N36: 2000 | O36: 2001 | P36: 2002 | Q36: 2003 | R36: 2004 | S36: 2005 | T36: 2006 | U36: 2007 | V36: 2008 | W36: 2009 | X36: 2010 | Y36: 2011 | Z36: 2012 | AA36: Mars 2013
B37: Pasurite | C37: =+C39 -> 0 | D37: =+D39 -> 0 | E37: =+E39 -> 0 | F37: =+F39 -> 0 | G37: =+G39 -> 0 | H37: =+H39 -> 0 | I37: =+I39 -> 0 | J37: =+J39 -> 0 | ... T37: =+T39 -> 0 | U37: =SUM(U38:U39) -> 15557600 | V37: =+V39 -> -7844379.6 | W37: =+W39 -> -0.0365 | X37: =+X39 -> -458620.32 | Y37: =+Y39 -> 0 | Z37: =+Z39 -> 13525 | AA37: =+AA39 -> 8697.54
B38: 0 | U38: 7254600
B39: Ndryshim likujditeti | C39: 0 | D39: 0 | E39: 0 | F39: 0 | G39: 0 | H39: 0 | I39: 0 | J39: 0 | K39: 0 | L39: 0 | M39: 0 | N39: 0 | O39: 0 | P39: 0 | Q39: 0 | R39: 0 | S39: 0 | T39: 0 | U39: =+S32 -> 8303000 | V39: =+T32 -> -7844379.6 | W39: =+U32 -> -0.0365 | X39: =+V32 -> -458620.32 | Y39: =+W32 -> 0 | Z39: =+X32 -> 13525 | AA39: =+Y32 -> 8697.54
B40: Te ardhura | C40: =+C41+C42+C43 -> 22066.328 | D40: =+D41+D42+D43 -> 66198.984 | E40: =+E41+E42+E43 -> 66198.984 | F40: =+F41+F42+F43 -> 66198.984 | G40: =+G41+G42+G43 -> 83433.027 | H40: =+H41+H42+H43 -> 80541.589 | I40: =+I41+I42+I43 -> 76043.984 | J40: =+J41+J42+J43 -> 73026.666 | ... AA40: =+AA41+AA42+AA43 -> 103054.05
B41: pagat e Hamide Sharra | C41: =+E10 -> 0 | D41: =+F10 -> 0 | E41: =+G10 -> 0 | F41: =+H10 -> 0 | G41: =+I10 -> 17234.043 | H41: =+J10 -> 14342.605 | I41: =+K10 -> 9845 | J41: =+L10 -> 6827.6818 | ... AA41: =+AC10 -> 29354.308
B42: pagat e Sinan Sharra | C42: =+E15 -> 22066.328 | D42: =+F15 -> 66198.984 | E42: =+G15 -> 66198.984 | F42: =+H15 -> 66198.984 | G42: =+I15 -> 66198.984 | H42: =+J15 -> 66198.984 | I42: =+K15 -> 66198.984 | J42: =+L15 -> 66198.984 | ... AA42: =+AC15 -> 73699.746
B43: Te ardhura nga interesi I depozitave | U43: 372265.01
B44: Shpenzime jetike | C44: =+C40*0.66 -> 14563.776 | D44: =+D40*0.66 -> 43691.329 | E44: =+E40*0.66 -> 43691.329 | F44: =+F40*0.66 -> 43691.329 | G44: =+G40*0.66 -> 55065.798 | H44: =+H40*0.66 -> 53157.449 | I44: =+I40*0.66 -> 50189.029 | J44: =+J40*0.66 -> 48197.599 | ... M44: =+M40*0.66 -> 53235.861 | N44: 216000 | O44: 216000 | P44: 187788 | Q44: 187928 | R44: 187928 | S44: 219114 | T44: 219114 | U44: 273240 | V44: 273240 | W44: 273240 | X44: 273240 | Y44: 273240 | Z44: 279096 | AA44: =279096/12*3 -> 69774
B45: Mundesi kursimi | C45: =+C40-C37-C44 -> 7502.5515 | D45: =+D40-D37-D44 -> 22507.655 | E45: =+E40-E37-E44 -> 22507.655 | F45: =+F40-F37-F44 -> 22507.655 | G45: =+G40-G37-G44 -> 28367.229 | H45: =+H40-H37-H44 -> 27384.14 | I45: =+I40-I37-I44 -> 25854.955 | J45: =+J40-J37-J44 -> 24829.066 | ... AA45: =+AA40-AA37-AA44 -> 24582.514
C49: 2427296
C51: 4 | D51: 1989 | E51: 26 | F51: 5516 | H51: =C51*F51 -> 22064
C52: 11 | D52: 2016 | H52: =C52*F51 -> 60676
H54: =C49-H51-H52 -> 2344556
D55: =C42/F51 -> 4.000422
H56: =H54/E51 -> 90175.231

Sheet Të ardh.prind.
C4: PLEQËRI SHTET | X4: PLEQËRI SHTET
C5: PERIUDHA | E5: MASA | F5: MUAJT | G5: KOMP. | H5: e*f | X5: PERIUDHA | Z5: MASA | AA5: MUAJT | AB5: KOMP. | AC5: e*f | AR5: Nr. | AS5: PËRSHKRIMI
L6: =H7/J10 -> 358 | Q6: 1989 | R6: =K7 -> 1432 | AG6: =AC7/AA7 -> 522 | AL6: 1566
A7: 1 | B7: 1.5 | C7: 07.09.1989 | D7: 30.08.1991 | E7: 357 | F7: 24 | H7: 8592 | J7: =1+1+1+1 -> 4 | K7: =L6*J7 -> 1432 | Q7: 1990 | R7: =K8 -> 4296 | V7: 1 | W7: 1.5 | X7: 03.07.1994 | Y7: 30.09.1994 | Z7: 528 | AA7: 3 | AC7: 1566 | AE7: 3 | AF7: =AG6*AE7 -> 1566 | AL7: 9383
C8: 1990 | J8: 12 | K8: =L6*J8 -> 4296 | Q8: 1991 | R8: =K9+K13 -> 4309.1429 | X8: 1994 | AL8: 5760
C9: 1991 | J9: 8 | K9: =L6*J9 -> 2864 | Q9: 1992 | R9: =K14+K17 -> 5332.8571 | AL9: 8170
J10: =SUM(J7:J9) -> 24 | K10: =SUM(K7:K9) -> 8592 | Q10: 1993 | R10: =K18+K21+K24 -> 13500 | V10: 2 | X10: 01.10.1994 | Y10: 30.04.1995 | Z10: 700 | AA10: 7 | AB10: 4460 | AC10: 9383 | AG10: =(AC10-AB10)/AA10 -> 703.28571 | AI10: =AB10/AA10 -> 637.14286 | AL10: 20113
Q11: 1994 | R11: =K27+K30 -> 28267.429 | S11: =AF7+AF11 -> 5587.2857 | X11: 1994 | AE11: 3 | AF11: =AE11*AG10+AI11 -> 4021.2857 | AI11: =AE11*AI10 -> 1911.4286 | AL11: 14047
A12: 2 | C12: 01.09.1991 | D12: 30.10.1992 | E12: 357 | F12: 14 | H12: 5058 | L12: =H12/F12 -> 361.28571 | Q12: 1995 | R12: =K31+K34+K38 -> 33732.571 | S12: =AF12+AF15+AF18 -> 15206.714 | X12: 1995 | AE12: 4 | AF12: =AE12*AG10+AI12 -> 5361.7143 | AI12: =AE12*AI10 -> 2548.5714 | AL12: 20487
C13: 1991 | J13: 4 | K13: =J13*L12 -> 1445.1429 | Q13: 1996 | R13: =K39+K42 -> 43441.227 | S13: =AF19+AF22 -> 12313.045 | AL13: 5577
C14: 1992 | J14: 10 | K14: =H12-K13 -> 3612.8571 | Q14: 1997 | R14: =K43 -> 45613.636 | S14: =AF23 -> 10970.727 | V14: 3 | W14: 1.1 | X14: 01.05.1995 | Y14: 30.09.1995 | Z14: 700 | AA14: 5 | AB14: 2213 | AC14: 5760 | AG14: =(AC14-AB14)/AA14 -> 709.4 | AI14: =AB14/AA14 -> 442.6 | AL14: 15027
Q15: 1998 | R15: =K44+K47 -> 53601.136 | S15: =AF24+AF27 -> 14961.227 | X15: 1995 | AE15: 5 | AF15: =AE15*AG14+AI15 -> 5760 | AI15: =AI14*AE15 -> 2213 | AL15: 17526
A16: 3 | B16: 1.3 | C16: 01.11.1992 | D16: 30.01.1993 | E16: 860 | F16: 3 | H16: 2580 | L16: =H16/F16 -> 860 | Q16: 1999 | R16: =K51 -> 59453.333 | S16: =AF30 -> 16389.6 | AL16: 22974
C17: 1992 | J17: 2 | K17: =J17*L16 -> 1720 | Q17: 2000 | R17: =K52+K55 -> 63991.167 | S17: =AF31+AF34+AF37 -> 17187.9 | V17: 4 | W17: 1.12 | X17: 01.10.1995 | Y17: 30.03.1996 | Z17: 784 | AA17: 6 | AB17: 3440 | AC17: 8170 | AG17: =(AC17-AB17)/AA17 -> 788.33333 | AI17: =AB17/AA17 -> 573.33333 | AL17: 11127
C18: 1993 | J18: 1 | K18: =H16-K17 -> 860 | Q18: 2001 | R18: =K56+K59 -> 71028.5 | S18: =AF38+AF41 -> 16276.5 | X18: 1995 | AE18: 3 | AF18: =AE18*AG17+AI18 -> 4085 | AI18: =AE18*AI17 -> 1720 | AL18: 17877
Q19: 2002 | R19: =K60+K63 -> 76901 | S19: =AF42+AF45 -> 20250 | X19: 1996 | AE19: 3 | AF19: =AE19*AG17+AI19 -> 4085 | AI19: =AE19*AI17 -> 1720 | AL19: 28586
A20: 4 | B20: 1.25 | C20: 01.02.1993 | D20: 30.07.1993 | E20: 1075 | F20: 6 | H20: 6414 | L20: =H20/F20 -> 1069 | Q20: 2003 | R20: =K64+K67 -> 84107.5 | S20: =AF46+AF49+AF52 -> 25167.857 | AL20: 5313
C21: 1993 | J21: 6 | K21: =H20 -> 6414 | Q21: 2004 | R21: =K68+K71 -> 90990.318 | S21: =AF53+AF56 -> 32474.743 | V21: 5 | W21: 1.25 | X21: 01.04.1996 | Y21: 30.01.1998 | Z21: 875 | AA21: 22 | AB21: 600 | AC21: 20113 | AG21: =(AC21-AB21)/AA21 -> 886.95455 | AI21: =AB21/AA21 -> 27.272727 | AL21: 56145
Q22: 2005 | R22: =K72+K75 -> 98218.49 | S22: =AF57+AF60+AF63 -> 46979.323 | X22: 1996 | AE22: 9 | AF22: =AE22*AG21+AI22 -> 8228.0455 | AI22: =AE22*AI21 -> 245.45455 | AL22: 60181
A23: 5 | B23: 1.15 | C23: 01.08.1993 | D23: 30.12.1993 | E23: 1237 | F23: 5 | H23: 6226 | L23: =H23/F23 -> 1245.2 | Q23: 2006 | R23: =K76+K79 -> 106651.69 | S23: =AF64+AF67 -> 56003.577 | X23: 1997 | AE23: 12 | AF23: =AE23*AG21+AI23 -> 10970.727 | AI23: =AE23*AI21 -> 327.27273 | AL23: 65347
C24: 1993 | J24: 5 | K24: =L23*J24 -> 6226 | Q24: 2007 | R24: =K80+K83 -> 119383.5 | S24: =AF68+AF71 -> 62764 | X24: 1998 | AE24: 1 | AF24: =AE24*AG21+AI24 -> 914.22727 | AI24: =AE24*AI21 -> 27.272727 | AL24: 61105
Q25: 2008 | R25: =K84+K87 -> 131666.3 | S25: =AF72+AF75 -> 69336.5 | AL25: 101915
A26: 6 | B26: 1.15 | C26: 01.01.1994 | D26: 30.09.1994 | E26: 1920 | F26: 9 | G26: 3173 | H26: 20581 | L26: =(H26-G26)/F26 -> 1934.2222 | Q26: 2009 | R26: =K88+K91 -> 144538.06 | S26: =AF76+AF79 -> 82679.143 | V26: 6 | W26: 1.23 | X26: 01.02.1998 | Y26: 30.12.1998 | Z26: 1050 | AA26: 11 | AB26: 2427 | AC26: 14047 | AG26: =(AC26-AB26)/AA26 -> 1056.3636 | AI26: =AB26/AA26 -> 220.63636 | AL26: 110607
C27: 1994 | J27: 9 | K27: =L26*J27+G26 -> 20581 | Q27: 2010 | R27: =K92+K95 -> 152123.64 | S27: =AF80+AF83 -> 98981.357 | AE27: 11 | AF27: =AE27*AG26+AI27 -> 14047 | AI27: =AE27*AI26 -> 2427 | AL27: 114307
Q28: 2011 | R28: =K96+K99 -> 160717 | S28: =AF84+AF87 -> 112457 | AL28: 127202
A29: 7 | C29: 01.10.1994 | D29: 30.04.1995 | E29: 2200 | F29: 7 | G29: 2462 | H29: 17935 | L29: =(H29-G29)/F29 -> 2210.4286 | Q29: 2012 | R29: =K100+K103 -> 172017.73 | S29: =AF88+AF91 -> 115862.12 | V29: 7 | W29: 1.1. | X29: 01.01.1999 | Y29: 31.03.2000 | Z29: 1050 | AA29: 15 | AB29: 2427 | AC29: 20487 | AG29: =(AC29-AB29)/AA29 -> 1204 | AI29: =AB29/AA29 -> 161.8 | AL29: 125489
C30: 1994 | J30: 3 | K30: =L29*J30+M30 -> 7686.4286 | M30: =O30*J30 -> 1055.1429 | O30: =G29/F29 -> 351.71429 | Q30: 2013 | R30: =K104+K107 -> 180564.27 | S30: =AF92+AF95 -> 120780.47 | X30: 1999 | AE30: 12 | AF30: =AE30*AG29+AI30 -> 16389.6 | AI30: =AE30*AI29 -> 1941.6 | AL30: 127481
C31: 1995 | J31: 4 | K31: =L29*J31+M31 -> 10248.571 | M31: =O30*J31 -> 1406.8571 | Q31: 2014 | R31: =K108+K111 -> 184842.08 | S31: =AF96+AF99 -> 126319 | X31: 2000 | AE31: 3 | AF31: =AE31*AG29+AI31 -> 4097.4 | AI31: =AE31*AI29 -> 485.4 | AL31: 129259
Q32: 2015 | R32: =K112+K115 -> 190897.33 | S32: =AF100+AF103 -> 128221.83 | AL32: 75886
A33: 8 | B33: 1.1 | C33: 01.05.1995 | D33: 30.09.1995 | E33: 2463 | F33: 5 | G33: 1773 | H33: 14253 | L33: =(H33-G33)/F33 -> 2496 | Q33: 2016 | R33: =K116+K119 -> 181204.08 | S33: =AF104+AF107 -> 129605.37 | V33: 8 | X33: 01.04.2000 | Y33: 30.06.2000 | Z33: 1050 | AA33: 3 | AB33: 2427 | AC33: 5577 | AG33: =(AC33-AB33)/AA33 -> 1050 | AI33: =AB33/AA33 -> 809 | AL33: 178994
C34: 1995 | J34: 5 | K34: =L33*J34+G33 -> 14253 | R34: =SUM(R6:R33) -> 2502822 | S34: =SUM(S11:S33) -> 1336775.3 | X34: 2000 | AE34: 3 | AF34: =AE34*AG33+AI34 -> 5577 | AI34: =AE34*AI33 -> 2427 | AL34: 102817
AL35: 140586
V36: 9 | W36: 1.17 | X36: 01.07.2000 | Y36: 30.06.2001 | Z36: 1155 | AA36: 12 | AB36: 1013 | AC36: 15027 | AG36: =(AC36-AB36)/AA36 -> 1167.8333 | AI36: =AB36/AA36 -> 84.416667 | AL36: 142829
A37: 9 | B37: 1.12 | C37: 01.10.1995 | D37: 30.03.1996 | E37: 2710 | F37: 6 | G37: 2112 | H37: 18462 | L37: =(H37-G37)/F37 -> 2725 | N37: =G37/F37 -> 352 | X37: 2000 | AE37: 6 | AF37: =AE37*AG36+AI37 -> 7513.5 | AI37: =AE37*AI36 -> 506.5 | AL37: 85425
C38: 1995 | J38: 3 | K38: =L37*J38+N38 -> 9231 | N38: =N37*3 -> 1056 | X38: 2001 | AE38: 6 | AF38: =AE38*AG36+AI38 -> 7513.5 | AI38: =AE38*AI36 -> 506.5 | AL38: =SUM(AL5:AL37) -> 2009108 | AM38: 2014575
C39: 1996 | J39: 3 | K39: =L37*J39+N39 -> 9231 | N39: =N37*3 -> 1056 | AM39: =AM38-AL38 -> 5467
V40: 10 | W40: 1.08 | X40: 01.07.2001 | Y40: 30.06.2002 | Z40: 1328 | AA40: 12 | AB40: 1413 | AC40: 17526 | AG40: =(AC40-AB40)/AA40 -> 1342.75 | AI40: =AB40/AA40 -> 117.75
A41: 10 | B41: 1.25 | C41: 01.04.1996 | D41: 30.01.1998 | E41: 3250 | F41: 22 | G41: 11150 | H41: 83625 | L41: =(H41-G41)/F41 -> 3294.3182 | N41: =G41/F41 -> 506.81818 | X41: 2001 | AE41: 6 | AF41: =AE41*AG40+AI41 -> 8763 | AI41: =AE41*AI40 -> 706.5
C42: 1996 | J42: 9 | K42: =L41*J42+N42 -> 34210.227 | N42: =N41*J42 -> 4561.3636 | X42: 2002 | AE42: 6 | AF42: =AE42*AG40+AI42 -> 8763 | AI42: =AE42*AI40 -> 706.5
C43: 1997 | J43: 12 | K43: =J43*L41+N43 -> 45613.636 | N43: =N41*J43 -> 6081.8182
C44: 1998 | J44: 1 | K44: =L41*J44+N44 -> 3801.1364 | N44: =N41*J44 -> 506.81818 | V44: 11 | W44: 1.1 | X44: 01.07.2002 | Y44: 30.06.2003 | Z44: 1727 | AA44: 12 | AB44: 2020 | AC44: 22974 | AG44: =(AC44-AB44)/AA44 -> 1746.1667 | AI44: =AB44/AA44 -> 168.33333
X45: 2002 | AE45: 6 | AF45: =AE45*AG44+AI45 -> 11487 | AI45: =AE45*AI44 -> 1010
A46: 11 | B46: 1.23 | C46: 01.02.1998 | D46: 30.12.1998 | E46: 4000 | F46: 11 | G46: 5533 | H46: 49800 | L46: =(H46-G46)/F46 -> 4024.2727 | N46: =G46/F46 -> 503 | X46: 2003 | AE46: 6 | AF46: =AE46*AG44+AI46 -> 11487 | AI46: =AE46*AI44 -> 1010
C47: 1998 | J47: 11 | K47: =L46*J47+N47 -> 49800 | N47: =N46*J47 -> 5533
V48: 12 | W48: 1.1 | X48: 01.07.2003 | Y48: 30.11.2003 | Z48: 2158 | AA48: 5 | AB48: 193 | AC48: 11127 | AG48: =(AC48-AB48)/AA48 -> 2186.8 | AI48: =AB48/AA48 -> 38.6
X49: 2003 | AE49: 5 | AF49: =AE49*AG48+AI49 -> 11127 | AI49: =AE49*AI48 -> 193
A50: 12 | B50: 1.1 | C50: 01.01.1999 | D50: 30.06.2000 | E50: 4400 | F50: 18 | G50: 9100 | H50: 89180 | L50: =(H50-G50)/F50 -> 4448.8889 | N50: =G50/F50 -> 505.55556
C51: 1999 | J51: 12 | K51: =J51*L50+N51 -> 59453.333 | N51: =N50*J51 -> 6066.6667 | V51: 13 | X51: 01.12.2003 | Y51: 30.06.2004 | Z51: 2158 | AA51: 7 | AB51: 2627 | AC51: 17877 | AG51: =(AC51-AB51)/AA51 -> 2178.5714 | AI51: =AB51/AA51 -> 375.28571
C52: 2000 | J52: 6 | K52: =L50*J52+N52 -> 29726.667 | N52: =N50*J52 -> 3033.3333 | X52: 2003 | AE52: 1 | AF52: =AE52*AG51+AI52 -> 2553.8571 | AI52: =AE52*AI51 -> 375.28571
X53: 2004 | AE53: 6 | AF53: =AE53*AG51+AI53 -> 15323.143 | AI53: =AE53*AI51 -> 2251.7143
A54: 13 | B54: 1.17 | C54: 01.07.2000 | D54: 30.06.2001 | E54: 5148 | F54: 12 | G54: 6067 | H54: 68529 | L54: =(H54-G54)/F54 -> 5205.1667 | N54: =G54/F54 -> 505.58333
C55: 2000 | J55: 6 | K55: =L54*J55+N55 -> 34264.5 | N55: =N54*J55 -> 3033.5 | V55: 14 | W55: 1.08 | X55: 01.07.2004 | Y55: 30.04.2005 | Z55: 2590 | AA55: 10 | AB55: 2427 | AC55: 28586 | AG55: =(AC55-AB55)/AA55 -> 2615.9 | AI55: =AB55/AA55 -> 242.7
C56: 2001 | J56: 6 | K56: =L54*J56+N56 -> 34264.5 | N56: =N54*J56 -> 3033.5 | X56: 2004 | AE56: 6 | AF56: =AE56*AG55+AI56 -> 17151.6 | AI56: =AE56*AI55 -> 1456.2
X57: 2005 | AE57: 4 | AF57: =AE57*AG55+AI57 -> 11434.4 | AI57: =AE57*AI55 -> 970.8
A58: 14 | B58: 1.08 | C58: 01.07.2001 | D58: 30.06.2002 | E58: 5560 | F58: 12 | G58: 6067 | H58: 73528 | L58: =(H58-G58)/F58 -> 5621.75 | N58: =G58/F58 -> 505.58333
C59: 2001 | J59: 6 | K59: =J59*L58+N59 -> 36764 | N59: =J59*N58 -> 3033.5 | V59: 15 | X59: 1.05.2005 | Y59: 30.05.2005 | Z59: 2979 | AA59: 1 | AB59: 2433 | AC59: 5313 | AG59: =(AC59-AB59)/AA59 -> 2880 | AI59: =AB59/AA59 -> 2433
C60: 2002 | J60: 6 | K60: =J60*L58+N60 -> 36764 | N60: =J60*N58 -> 3033.5 | AE60: 1 | AF60: =AE60*AG59+AI60 -> 5313 | AI60: =AE60*AI59 -> 2433
A62: 15 | B62: 1.1 | C62: 01.07.2002 | D62: 30.06.2003 | E62: 6116 | F62: 12 | G62: 6067 | H62: 80274 | L62: =(H62-G62)/F62 -> 6183.9167 | N62: =G62/F62 -> 505.58333 | V62: 16 | W62: 1.08 | X62: 01.06.2005 | Y62: 30.06.2006 | Z62: 3425 | AA62: 13 | AB62: 11163 | AC62: 56145 | AG62: =(AC62-AB62)/AA62 -> 3460.1538 | AI62: =AB62/AA62 -> 858.69231
C63: 2002 | J63: 6 | K63: =L62*J63+N63 -> 40137 | N63: =N62*J63 -> 3033.5 | X63: 2005 | AE63: 7 | AF63: =AE63*AG62+AI63 -> 30231.923 | AI63: =AE63*AI62 -> 6010.8462
C64: 2003 | J64: 6 | K64: =L62*J64+N64 -> 40137 | N64: =N62*J64 -> 3033.5 | X64: 2006 | AE64: 6 | AF64: =AE64*AG62+AI64 -> 25913.077 | AI64: =AE64*AI62 -> 5152.1538
A66: 16 | B66: 1.1 | C66: 01.07.2003 | D66: 30.06.2004 | E66: 6728 | F66: 12 | G66: 6083 | H66: 87941 | L66: =(H66-G66)/F66 -> 6821.5 | N66: =G66/F66 -> 506.91667 | V66: 17 | W66: 1.05 | X66: 01.07.2006 | Y66: 30.06.2007 | Z66: 4110 | AA66: 12 | AB66: 10313 | AC66: 60181 | AG66: =(AC66-AB66)/AA66 -> 4155.6667 | AI66: =AB66/AA66 -> 859.41667
C67: 2003 | J67: 6 | K67: =J67*L66+N67 -> 43970.5 | N67: =N66*J67 -> 3041.5 | X67: 2006 | AE67: 6 | AF67: =AE67*AG66+AI67 -> 30090.5 | AI67: =AE67*AI66 -> 5156.5
C68: 2004 | J68: 6 | K68: =J68*L66+N68 -> 43970.5 | N68: =N66*J68 -> 3041.5 | X68: 2007 | AE68: 6 | AF68: =AE68*AG66+AI68 -> 30090.5 | AI68: =AE68*AI66 -> 5156.5
A70: 17 | B70: 1.08 | C70: 01.07.2004 | D70: 30.05.2005 | E70: 7266 | F70: 11 | G70: 5550 | H70: 86203 | L70: =(H70-G70)/F70 -> 7332.0909 | N70: =G70/F70 -> 504.54545 | V70: 18 | W70: 1.05 | X70: 01.07.2007 | Y70: 30.06.2008 | Z70: 4521 | AA70: 12 | AB70: 10342 | AC70: 65347 | AG70: =(AC70-AB70)/AA70 -> 4583.75 | AI70: =AB70/AA70 -> 861.83333
C71: 2004 | J71: 6 | K71: =J71*L70+N71 -> 47019.818 | N71: =J71*N70 -> 3027.2727 | X71: 2007 | AE71: 6 | AF71: =AE71*AG70+AI71 -> 32673.5 | AI71: =AE71*AI70 -> 5171
C72: 2005 | J72: 5 | K72: =J72*L70+N72 -> 39183.182 | N72: =J72*N70 -> 2522.7273 | X72: 2008 | AE72: 6 | AF72: =AE72*AG70+AI72 -> 32673.5 | AI72: =AE72*AI70 -> 5171
A74: 18 | B74: 1.08 | C74: 01.06.2005 | D74: 30.06.2006 | E74: 7848 | F74: 13 | G74: 6567 | H74: 109637 | L74: =(H74-G74)/F74 -> 7928.4615 | N74: =G74/F74 -> 505.15385 | V74: 19 | W74: 1.1 | X74: 01.07.2008 | Y74: 30.04.2009 | Z74: 5200 | AA74: 10 | AB74: 8585 | AC74: 61105 | AG74: =(AC74-AB74)/AA74 -> 5252 | AI74: =AB74/AA74 -> 858.5
C75: 2005 | J75: 7 | K75: =J75*L74+N75 -> 59035.308 | N75: =N74*J75 -> 3536.0769 | X75: 2008 | AE75: 6 | AF75: =AE75*AG74+AI75 -> 36663 | AI75: =AE75*AI74 -> 5151
C76: 2006 | J76: 6 | K76: =J76*L74+N76 -> 50601.692 | N76: =N74*J76 -> 3030.9231 | X76: 2009 | AE76: 4 | AF76: =AE76*AG74+AI76 -> 24442 | AI76: =AE76*AI74 -> 3434
A78: 19 | B78: 1.05 | C78: 01.07.2006 | D78: 30.06.2007 | E78: 8239 | F78: 12 | G78: 12133 | H78: 112100 | L78: =(H78-G78)/F78 -> 8330.5833 | N78: =G78/F78 -> 1011.0833 | V78: 20 | W78: 1.08 | X78: 01.05.2009 | Y78: 30.06.2010 | Z78: 6344 | AA78: 14 | AB78: 12042 | AC78: 101915 | AG78: =(AC78-AB78)/AA78 -> 6419.5 | AI78: =AB78/AA78 -> 860.14286
C79: 2006 | J79: 6 | K79: =J79*L78+N79 -> 56050 | N79: =J79*N78 -> 6066.5 | X79: 2009 | AE79: 8 | AF79: =AE79*AG78+AI79 -> 58237.143 | AI79: =AE79*AI78 -> 6881.1429
C80: 2007 | J80: 6 | K80: =J80*L78+N80 -> 56050 | N80: =J80*N78 -> 6066.5 | X80: 2010 | AE80: 6 | AF80: =AE80*AG78+AI80 -> 43677.857 | AI80: =AE80*AI78 -> 5160.8571
A82: 20 | B82: 1.05 | C82: 01.07.2007 | D82: 30.06.2008 | E82: 8651 | F82: 12 | G82: 21413 | H82: 126667 | L82: =(H82-G82)/F82 -> 8771.1667 | N82: =G82/F82 -> 1784.4167 | V82: 21 | W82: 1.04 | X82: 01.07.2010 | Y82: 30.06.2011 | Z82: 6978 | AA82: 12 | AB82: 25941 | AC82: 110607 | AG82: =(AC82-AB82)/AA82 -> 7055.5 | AI82: =AB82/AA82 -> 2161.75
C83: 2007 | J83: 6 | K83: =J83*L82+N83 -> 63333.5 | N83: =J83*N82 -> 10706.5 | X83: 2010 | AE83: 6 | AF83: =AE83*AG82+AI83 -> 55303.5 | AI83: =AE83*AI82 -> 12970.5
C84: 2008 | J84: 6 | K84: =J84*L82+N84 -> 63333.5 | N84: =J84*N82 -> 10706.5 | X84: 2011 | AE84: 6 | AF84: =AE84*AG82+AI84 -> 55303.5 | AI84: =AE84*AI82 -> 12970.5
A86: 21 | B86: 1.1 | C86: 01.07.2008 | D86: 30.04.2009 | E86: 9516 | F86: 10 | G86: 17776 | H86: 113888 | L86: =(H86-G86)/F86 -> 9611.2 | N86: =G86/F86 -> 1777.6 | V86: 22 | W86: 1.04 | X86: 01.07.2011 | Y86: 30.06.2012 | Z86: 7257 | AA86: 12 | AB86: 26012 | AC86: 114307 | AG86: =(AC86-AB86)/AA86 -> 7357.9167 | AI86: =AB86/AA86 -> 2167.6667
C87: 2008 | J87: 6 | K87: =J87*L86+N87 -> 68332.8 | N87: =N86*J87 -> 10665.6 | X87: 2011 | AE87: 6 | AF87: =AE87*AG86+AI87 -> 57153.5 | AI87: =AE87*AI86 -> 13006
C88: 2009 | J88: 4 | K88: =J88*L86+N88 -> 45555.2 | N88: =N86*J88 -> 7110.4 | X88: 2012 | AE88: 6 | AF88: =AE88*AG86+AI88 -> 57153.5 | AI88: =AE88*AI86 -> 13006
A90: 22 | B90: 1.08 | C90: 01.05.2009 | D90: 30.06.2010 | E90: 10277 | F90: 14 | G90: 27625 | H90: 173220 | L90: =(H90-G90)/F90 -> 10399.643 | N90: =G90/F90 -> 1973.2143 | V90: 23 | W90: 1.04 | X90: 01.07.2012 | Y90: 30.07.2013 | Z90: 7547 | AA90: 13 | AB90: 28079 | AC90: 127202 | AG90: =(AC90-AB90)/AA90 -> 7624.8462 | AI90: =AB90/AA90 -> 2159.9231
C91: 2009 | J91: 8 | K91: =L90*J91+N91 -> 98982.857 | N91: =J91*N90 -> 15785.714 | X91: 2012 | AE91: 6 | AF91: =AE91*AG90+AI91 -> 58708.615 | AI91: =AE91*AI90 -> 12959.538
C92: 2010 | J92: 6 | K92: =L90*J92+N92 -> 74237.143 | N92: =J92*N90 -> 11839.286 | X92: 2013 | AE92: 7 | AF92: =AE92*AG90+AI92 -> 68493.385 | AI92: =AE92*AI90 -> 15119.462
A94: 23 | B94: 1.04 | C94: 01.07.2010 | D94: 30.06.2011 | E94: 10688 | F94: 12 | G94: 26087 | H94: 155773 | L94: =(H94-G94)/F94 -> 10807.167 | N94: =G94/F94 -> 2173.9167 | V94: 24 | W94: 1.04 | X94: 01.08.2013 | Y94: 30.07.2014 | Z94: 8233 | AA94: 12 | AB94: 25870 | AC94: 125489 | AG94: =(AC94-AB94)/AA94 -> 8301.5833 | AI94: =AB94/AA94 -> 2155.8333
C95: 2010 | J95: 6 | K95: =J95*L94+N95 -> 77886.5 | N95: =N94*J95 -> 13043.5 | X95: 2013 | AE95: 5 | AF95: =AE95*AG94+AI95 -> 52287.083 | AI95: =AE95*AI94 -> 10779.167
C96: 2011 | J96: 6 | K96: =J96*L94+N96 -> 77886.5 | N96: =N94*J96 -> 13043.5 | X96: 2014 | AE96: 7 | AF96: =AE96*AG94+AI96 -> 73201.917 | AI96: =AE96*AI94 -> 15090.833
A98: 24 | B98: 1.04 | C98: 01.07.2011 | D98: 30.06.2012 | E98: 11116 | F98: 12 | G98: 30417 | H98: 165661 | L98: =(H98-G98)/F98 -> 11270.333 | N98: =G98/F98 -> 2534.75 | V98: 25 | W98: 1.02 | X98: 01.08.2014 | Y98: 30.07.2015 | Z98: 8398 | AA98: 12 | AB98: 25870 | AC98: 127481 | AG98: =(AC98-AB98)/AA98 -> 8467.5833 | AI98: =AB98/AA98 -> 2155.8333
C99: 2011 | J99: 6 | K99: =J99*L98+N99 -> 82830.5 | N99: =J99*N98 -> 15208.5 | X99: 2014 | AE99: 5 | AF99: =AE99*AG98+AI99 -> 53117.083 | AI99: =AE99*AI98 -> 10779.167
C100: 2012 | J100: 6 | K100: =J100*L98+N100 -> 82830.5 | N100: =J100*N98 -> 15208.5 | X100: 2015 | AE100: 7 | AF100: =AE100*AG98+AI100 -> 74363.917 | AI100: =AE100*AI98 -> 15090.833
A102: 25 | B102: 1.04 | C102: 01.07.2012 | D102: 30.07.2013 | E102: 11561 | F102: 13 | G102: 41409 | H102: 193239 | L102: =(H102-G102)/F102 -> 11679.231 | N102: =G102/F102 -> 3185.3077 | V102: 26 | W102: 1.014 | X102: 01.08.2015 | Y102: 30.07.2016 | Z102: 8515 | AA102: 12 | AB102: 25941 | AC102: 129259 | AG102: =(AC102-AB102)/AA102 -> 8609.8333 | AI102: =AB102/AA102 -> 2161.75
C103: 2012 | J103: 6 | K103: =J103*L102+N103 -> 89187.231 | N103: =N102*J103 -> 19111.846 | X103: 2015 | AE103: 5 | AF103: =AE103*AG102+AI103 -> 53857.917 | AI103: =AE103*AI102 -> 10808.75
C104: 2013 | J104: 7 | K104: =J104*L102+N104 -> 104051.77 | N104: =N102*J104 -> 22297.154 | X104: 2016 | AE104: 7 | AF104: =AE104*AG102+AI104 -> 75401.083 | AI104: =AE104*AI102 -> 15132.25
A106: 26 | B106: 1.04 | C106: 01.08.2013 | D106: 30.07.2014 | E106: 12023 | F106: 12 | G106: 38151 | H106: 183630 | L106: =(H106-G106)/F106 -> 12123.25 | N106: =G106/F106 -> 3179.25 | V106: 27 | W106: 1.016 | X106: 01.08.2016 | Y106: 28.02.2017 | Z106: 8651 | AA106: 7 | AB106: 15037 | AC106: 75886 | AG106: =(AC106-AB106)/AA106 -> 8692.7143 | AI106: =AB106/AA106 -> 2148.1429
C107: 2013 | J107: 5 | K107: =J107*L106+N107 -> 76512.5 | N107: =J107*N106 -> 15896.25 | X107: 2016 | AE107: 5 | AF107: =AE107*AG106+AI107 -> 54204.286 | AI107: =AE107*AI106 -> 10740.714
C108: 2014 | J108: 7 | K108: =J108*L106+N108 -> 107117.5 | N108: =J108*N106 -> 22254.75 | X108: 2017 | AE108: 2 | AF108: =AE108*AG106+AI108 -> 21681.714 | AI108: =AE108*AI106 -> 4296.2857
A110: 27 | B110: 1.02 | C110: 01.08.2014 | D110: 30.07.2015 | E110: 12263 | F110: 12 | G110: 38151 | H110: 186539 | L110: =(H110-G110)/F110 -> 12365.667 | N110: =G110/F110 -> 3179.25
C111: 2014 | J111: 5 | K111: =J111*L110+N111 -> 77724.583 | N111: =J111*N110 -> 15896.25
C112: 2015 | J112: 7 | K112: =J112*L110+N112 -> 108814.42 | N112: =J112*N110 -> 22254.75
A114: 28 | B114: 1.014 | C114: 01.08.2015 | D114: 30.07.2016 | E114: 12435 | F114: 12 | G114: 46119 | H114: 196999 | L114: =(H114-G114)/F114 -> 12573.333 | N114: =G114/F114 -> 3843.25
C115: 2015 | J115: 5 | K115: =J115*L114+N115 -> 82082.917 | N115: =J115*N114 -> 19216.25
C116: 2016 | J116: 7 | K116: =J116*L114+N116 -> 114916.08 | N116: =J116*N114 -> 26902.75
A118: 29 | B118: 1.016 | C118: 01.08.2016 | D118: 30.11.2016 | E118: 12634 | F118: 4 | G118: 15331 | H118: 66288 | L118: =(H118-G118)/F118 -> 12739.25 | N118: =G118/F118 -> 3832.75
...

Sheet Kredi ne NBG 
B2: Pagesat e kesteve te kredise sipas statement bankar nga subjekti Arben Sharra | C2: Monedha | D2: 2008 | E2: 2009 | F2: 2010 | G2: 2011 | H2: 2012 | I2: 2013 | J2: 2014
B3: Llogari kredie | D3: =0.41*KK!R26 -> 0 | E3: =0.62*KK!S26 -> 0 | F3: =4.65*KK!T26 -> 0 | G3: =0.37*KK!U26 -> 0 | H3: 0 | I3: =2.82*KK!W26 -> 0 | J3: =24.85*KK!X26 -> 0
B4: kestet e paguara | C4: Euro | D4: =346+345+345+346+345+345 -> 2072 | E4: =345+346+345.24+345+345.24+15000+230.24+356.24+231+230+230+231+230 -> 18464.96 | F4: =230*7+231+230.24+231+126+231+3405+100 -> 6164.24 | G4: =201+204+205+205+205+205+205+3290+180.86+180.86+180.86+180.75+2060 -> 7503.33 | H4: =165+165+165+165+162+165+165+3090+198+180+150+130 -> 4900 | I4: =140+138+138+140+140+140+137+140+138+140+100+150+130+140 -> 1911 | J4: =140*8+100+135+135+15550 -> 17040
C5: Kursi I Kembimit | D5: =+KK!R4 -> 123.1825 | E5: =+KK!S4 -> 137.17 | F5: =+KK!T4 -> 138.81 | G5: =+KK!U4 -> 138.3 | H5: =+KK!V4 -> 139.72 | I5: =+KK!W4 -> 140.21 | J5: =+KK!X4 -> 140.11
B6: Totali | C6: Lek | D6: =+D4*D5 -> 255234.14 | E6: =+E4*E5 -> 2532838.6 | F6: =+F4*F5 -> 855658.15 | G6: =+G4*G5 -> 1037710.5 | H6: =+H4*H5 -> 684628 | I6: =+I4*I5 -> 267941.31 | J6: =+J4*J5 -> 2387474.4
D8: 2008 | F8: 2009 | H8: 2010 | J8: 2011 | L8: 2012 | N8: 2013 | P8: 2014
C9: Princcipal | D9: Interesa | E9: Princcipal | F9: Interesa | G9: Princcipal | H9: Interesa | I9: Princcipal | J9: Interesa | K9: Princcipal | L9: Interesa | M9: Princcipal | N9: Interesa | O9: Princcipal | P9: Interesa
C10: =129.3 -> 129.3
D11: 215.94 | F11: 0.35 | G11: 64.81 | I11: 61.83 | K11: 51.4
D12: 0.76 | F12: 0.03 | H12: 165.43 | J12: 142.92 | L12: 112.92 | N12: 0.15 | O12: 51.71
D13: 0.03 | E13: 90.58 | G13: 65.18 | I13: 62.17 | K13: 53.5 | N13: 0.32 | P13: 87.37
C14: 88.49 | E14: 254.31 | H14: 165.06 | J14: 142.58 | L14: 110.82 | M14: 50.91 | O14: 52
D15: 255.99 | F15: 0.06 | G15: 81.48 | I15: 76.28 | L15: 1.73 | N15: 86.05 | P15: 87.08
D16: 0.06 | F16: 0.02 | H16: 148.76 | J16: 128.47 | L16: 0.03 | M16: 48.25 | O16: 60.69
D17: 0.43 | F17: 0.03 | G17: 66 | J17: 0.4 | L17: 0.06 | N17: 90.83 | P17: 78.39
D18: 0.06 | E18: 91.09 | H18: 164.24 | J18: 0.02 | K18: 60.93 | M18: 48.52 | P18: 5.58
C19: 97.25 | F19: 254.13 | G19: 71.65 | J19: 0.04 | L19: 101.66 | N19: 90.56 | P19: 0.11
D20: 247.56 | F20: 0.06 | H20: 158.59 | I20: 52.95 | K20: 54.14 | M20: 57.53 | P20: 0.24
D21: 0.12 | F21: 0.69 | H21: 0.42 | J21: 141.4 | L21: 110.18 | N21: 81.55 | O21: 52.63
D22: 0.01 | F22: 0.14 | H22: 0.06 | I22: 67.86 | K22: 57.99 | N22: 1.33 | P22: 80.87
D23: 0.03 | E23: 116.14 | G23: 66.77 | J23: 135.89 | L23: 106.33 | N23: 0.01 | O23: 55.71
C24: 89.53 | F24: 228.41 | H24: 163.05 | I24: 63.68 | K24: 54.77 | N24: 0.02 | P24: 83.37
D25: 255.7 | F25: 0.31 | H25: 0.12 | J25: 141.07 | L25: 109.55 | M25: 49.12 | O25: 53.24
D26: 0.06 | E26: 92.25 | G26: 72.4 | I26: 68.57 | K26: 58.6 | N26: 88.53 | P26: 85.84
D27: 0.68 | F27: 252.99 | H27: 157.84 | J27: 136.18 | L27: 105.72 | N27: 2.22 | O27: 56.3
D28: 0.03 | E28: 100.91 | H28: 105 | J28: 22 | L28: 90 | N28: 0.02 | P28: 82.78
C29: 98.26 | F29: 244.33 | H29: 0.16 | J29: 39 | K29: 3000 | N29: 0.05 | P29: 40
D30: 246.3 | E30: 15000 | G30: 67.55 | I30: 92.15 | L30: 60 | M30: 52.29 | P30: 60
D31: 255.7 | E31: 54.16 | H31: 57.69 | I31: 3000 | L31: 0.03 | N31: 84.57 | P31: 43.91
D32: 0.06 | F32: 176.08 | H32: 0.36 | I32: 18.04 | L32: 0.08 | N32: 3.07 | P32: 1
D33: 0.68 | E33: 68 | G33: 67.93 | J33: 127.64 | K33: 36.66 | N33: 0.01 | P33: 0.02
D34: 0.03 | F34: 162.24 | H34: 162.31 | J34: 36 | L34: 102.42 | N34: 0.02 | P34: 41.32
C35: 98.26 | E35: 62.97 | H35: 0.04 | J35: 0.01 | L35: 15 | M35: 49.69 | O35: 53.85
D36: 246.3 | F36: 167.27 | G36: 73.53 | J36: 0.03 | L36: 26 | N36: 86.32 | P36: 4.8
F37: 0.76 | H37: 156.71 | I37: 35.18 | L37: 0.02 | N37: 0.96 | P37: 0.04
C38: =SUM(C10:C37) -> 601.09 | D38: =SUM(D10:D37) -> 1726.53 | F38: 0.06 | H38: 0.08 | J38: 0.78 | L38: 0.05 | N38: 0.01 | P38: 0.1
E39: 63.32 | G39: 68.72 | J39: 0.02 | K39: 47.16 | N39: 0.02 | O39: 54.16
D40: 2327.62 | F40: 166.16 | H40: 161.52 | J40: 0.03 | L40: 91.92 | M40: 52.84 | P40: 80.12
F41: 0.12 | G41: 3200 | I41: 57.22 | L41: 0.7 | N41: 85.28 | P41: 5.58
E42: 69.05 | G42: 54.01 | J42: 122.86 | L42: 0.05 | N42: 1.85 | P42: 0.02
F43: 161.19 | H43: 150.74 | J43: 0.73 | L43: 0.1 | N43: 0.03 | P43: 0.05
E44: 64.07 | J44: 0.03 | K44: 50.38 | N44: 0.07 | O44: 57.19
F45: 166.17 | G45: =SUM(G11:G44) -> 4020.03 | H45: =SUM(H11:H44) -> 1918.18 | J45: 0.07 | L45: 88 | M45: 50.26 | P45: 76.31
E46: 69.77 | I46: 61.52 | L46: 11.47 | N46: 86.97 | O46: 451.84
F47: 160.47 | H47: =G45+H45 -> 5938.21 | J47: 118.61 | L47: 0.08 | N47: 41 | P47: 35.35
I48: 57.88 | L48: 0.19 | N48: 60 | O48: 15061.29
E49: =SUM(E11:E48) -> 16196.62 | F49: =SUM(F11:F48) -> 2142.07 | J49: 122.98 | K49: 47.7 | N49: 39.67 | P49: 21.9
G50: =SUM(G11:G38) -> 697.3 | H50: =SUM(H11:H38) -> 1605.92 | J50: 0.63 | L50: 79.91 | N50: 0.1 | P50: 41
F51: =E49+F49 -> 18338.69 | J51: 0.05 | L51: 2.12 | N51: 0.22
J52: 0.1 | N52: 48.87
H53: 6164 | I53: 62.16 | M53: 50.54 | O53: =SUM(O12:O45) -> 547.48 | P53: =SUM(P12:P45) -> 944.9
C54: =C38+E49+G45+I61+K61+M69+O56 -> 46919.97 | J54: 118.07 | N54: 0.27 | O54: =SUM(O46:O50) -> 15513.13 | P54: =SUM(P46:P50) -> 98.25
I55: 2000 | N55: 0.03
I56: 60 | N56: 0.08 | O56: =SUM(O11:O51) -> 16060.61 | P56: =SUM(P11:P51) -> 1043.15
M57: 53.67
I58: =SUM(I11:I29) -> 453.34 | J58: =SUM(J11:J29) -> 1029.97 | K58: =SUM(K11:K27) -> 391.33 | L58: =SUM(L11:L27) -> 759 | N58: 85.14
I59: =SUM(I30:I56) -> 5444.15 | J59: =SUM(J30:J56) -> 648.64 | K59: =SUM(K28:K51) -> 3181.9 | L59: =SUM(L28:L51) -> 568.14 | N59: 11.08
N60: 0.02
I61: =SUM(I11:I56) -> 5897.49 | J61: =SUM(J11:J56) -> 1678.61 | K61: =SUM(K11:K39) -> 3475.15 | L61: =SUM(L11:L40) -> 1144.52 | N61: 0.05
M62: 51.12 | N62: 76.88
N63: 1.93
N64: 0.01
N65: 0.02
M66: 54.24
N67: 82.91
M69: =SUM(M11:M67) -> 668.98 | N69: =SUM(N11:N67) -> 1239.1

Sheet KPA_apart 05 10 2007
C3: Shtëpi 3 (tre)kate,Kodër Kamëz Tiranë/viti 1996 | G3: 0.66
B5: Nr. | C5: PËRSHKRIMI/PERIUDHA | D5: 9.1989 | E5: 1990 | F5: 1991 | G5: 1992 | H5: 1993 | I5: 1994 | J5: 1995 | K5: 1996 | L5: KUMUL. | M5: 1997 | N5: 1998 | O5: 1999 | P5: KUMUL. | Q5: TOTAL | S5: 1996 | T5: 1997 | U5: 1998 | V5: 1999 | X5: 2000 | Y5: 2001 | Z5: 2002 | AA5: 2003 | AB5: 2004 | AC5: 2005 | AD5: 2006 | AE5: 2007 | AF5: 2008 | AG5: 2009 | AH5: 2010 | AI5: 2011 | AJ5: 2012 | AK5: 3.2013
B7: I | C7: TARDHURA | D7: =SUM(D8:D9) -> 1432 | E7: =SUM(E8:E9) -> 4296 | F7: =SUM(F8:F9) -> 4309.1429 | G7: =SUM(G8:G9) -> 5332.8571 | H7: =SUM(H8:H9) -> 13500 | I7: =SUM(I8:I9) -> 33854.714 | J7: =SUM(J8:J9) -> 48939.286 | K7: =SUM(K8:K9) -> 55754.273 | L7: =SUM(D7:K7) -> 167418.27 | M7: =SUM(M8:M9) -> 56584.364 | N7: =SUM(N8:N9) -> 68562.364 | O7: =SUM(O8:O9) -> 75842.933 | P7: =SUM(P8:P9) -> 200989.66 | Q7: =SUM(Q8:Q9) -> 368407.93 | S7: 12883 | T7: 12883 | U7: 20033 | V7: 20033 | X7: =SUM(X8:X9) -> 81179.067 | Y7: =SUM(Y8:Y9) -> 87305 | Z7: =SUM(Z8:Z9) -> 97151 | AA7: =SUM(AA8:AA9) -> 109275.36 | AB7: =SUM(AB8:AB9) -> 123465.06 | AC7: =SUM(AC8:AC9) -> 145197.81 | AD7: =SUM(AD8:AD9) -> 162655.27 | AE7: =SUM(AE8:AE9) -> 182147.5 | ... AK7: =SUM(AK8:AK9) -> 75336.184
B8: 1 | C8: Të ardh.babai S.R._S. Sharra | D8: ='[6]Të ardhurat e prindërve_KPA'!R6 -> 1432 | E8: ='[6]Të ardhurat e prindërve_KPA'!R7 -> 4296 | F8: ='[6]Të ardhurat e prindërve_KPA'!R8 -> 4309.1429 | G8: ='[6]Të ardhurat e prindërve_KPA'!R9 -> 5332.8571 | H8: ='[6]Të ardhurat e prindërve_KPA'!R10 -> 13500 | I8: ='[6]Të ardhurat e prindërve_KPA'!R11 -> 28267.429 | J8: ='[6]Të ardhurat e prindërve_KPA'!R12 -> 33732.571 | K8: ='[6]Të ardhurat e prindërve_KPA'!R13 -> 43441.227 | L8: =SUM(D8:K8) -> 134311.23 | M8: ='[6]Të ardhurat e prindërve_KPA'!R14 -> 45613.636 | N8: ='[6]Të ardhurat e prindërve_KPA'!R15 -> 53601.136 | O8: ='[6]Të ardhurat e prindërve_KPA'!R16 -> 59453.333 | P8: =SUM(M8:O8) -> 158668.11 | Q8: =L8+P8 -> 292979.33 | X8: ='[6]Të ardhurat e prindërve_KPA'!R17 -> 63991.167 | Y8: ='[6]Të ardhurat e prindërve_KPA'!R18 -> 71028.5 | Z8: ='[6]Të ardhurat e prindërve_KPA'!R19 -> 76901 | AA8: ='[6]Të ardhurat e prindërve_KPA'!R20 -> 84107.5 | AB8: ='[6]Të ardhurat e prindërve_KPA'!R21 -> 90990.318 | AC8: ='[6]Të ardhurat e prindërve_KPA'!R22 -> 98218.49 | AD8: ='[6]Të ardhurat e prindërve_KPA'!R23 -> 106651.69 | AE8: ='[6]Të ardhurat e prindërve_KPA'!R24 -> 119383.5 | AF8: ='[6]Të ardhurat e prindërve_KPA'!R25 -> 131666.3 | AG8: ='[6]Të ardhurat e prindërve_KPA'!R26 -> 144538.06 | AH8: ='[6]Të ardhurat e prindërve_KPA'!R27 -> 152123.64 | AI8: ='[6]Të ardhurat e prindërve_KPA'!R28 -> 160717 | AJ8: ='[6]Të ardhurat e prindërve_KPA'!R29 -> 172017.73 | AK8: ='[6]Të ardhurat e prindërve_KPA'!R30/12*3 -> 45141.067
B9: 2 | C9: Të ardh.nëna S.R._H. Sharra | D9: 0 | E9: 0 | F9: 0 | G9: 0 | H9: 0 | I9: ='[6]Të ardhurat e prindërve_KPA'!S11 -> 5587.2857 | J9: ='[6]Të ardhurat e prindërve_KPA'!S12 -> 15206.714 | K9: ='[6]Të ardhurat e prindërve_KPA'!S13 -> 12313.045 | L9: =SUM(D9:K9) -> 33107.045 | M9: ='[6]Të ardhurat e prindërve_KPA'!S14 -> 10970.727 | N9: ='[6]Të ardhurat e prindërve_KPA'!S15 -> 14961.227 | O9: ='[6]Të ardhurat e prindërve_KPA'!S16 -> 16389.6 | P9: =SUM(M9:O9) -> 42321.555 | Q9: =L9+P9 -> 75428.6 | X9: ='[6]Të ardhurat e prindërve_KPA'!S17 -> 17187.9 | Y9: ='[6]Të ardhurat e prindërve_KPA'!S18 -> 16276.5 | Z9: ='[6]Të ardhurat e prindërve_KPA'!S19 -> 20250 | AA9: ='[6]Të ardhurat e prindërve_KPA'!S20 -> 25167.857 | AB9: ='[6]Të ardhurat e prindërve_KPA'!S21 -> 32474.743 | AC9: ='[6]Të ardhurat e prindërve_KPA'!S22 -> 46979.323 | AD9: ='[6]Të ardhurat e prindërve_KPA'!S23 -> 56003.577 | AE9: ='[6]Të ardhurat e prindërve_KPA'!S24 -> 62764 | AF9: ='[6]Të ardhurat e prindërve_KPA'!S25 -> 69336.5 | AG9: ='[6]Të ardhurat e prindërve_KPA'!S26 -> 82679.143 | AH9: ='[6]Të ardhurat e prindërve_KPA'!S27 -> 98981.357 | AI9: ='[6]Të ardhurat e prindërve_KPA'!S28 -> 112457 | AJ9: ='[6]Të ardhurat e prindërve_KPA'!S29 -> 115862.12 | AK9: =('[6]Të ardhurat e prindërve_KPA'!S30/12)*3 -> 30195.117
B11: II | C11: SHPENZIME | D11: =D12 -> 945.12 | E11: =E12 -> 2835.36 | F11: =F12 -> 2844.0343 | G11: =G12 -> 3519.6857 | H11: =H12 -> 8910 | I11: =I12 -> 22344.111 | J11: =J12 -> 32299.929 | K11: =K12 -> 36797.82 | L11: =SUM(D11:K11) -> 110496.06 | M11: =M12 -> 37345.68 | N11: =N12 -> 45251.16 | O11: =O12 -> 50056.336 | P11: =SUM(M11:O11) -> 132653.18 | Q11: =L11+P11 -> 243149.24 | U11: 17649 | X11: =SUM(X12) -> 216000 | Y11: =SUM(Y12) -> 216000 | Z11: =SUM(Z12) -> 187728 | AA11: =SUM(AA12) -> 187728 | AB11: =SUM(AB12) -> 187728 | AC11: =SUM(AC12) -> 219114 | AD11: =SUM(AD12) -> 219114 | AE11: =SUM(AE12) -> 273240 | ... AK11: =SUM(AK12) -> 70512
B12: 1 | C12: Shpenzime jetike | D12: =D7*$G$3 -> 945.12 | E12: =E7*$G$3 -> 2835.36 | F12: =F7*$G$3 -> 2844.0343 | G12: =G7*$G$3 -> 3519.6857 | H12: =H7*$G$3 -> 8910 | I12: =I7*$G$3 -> 22344.111 | J12: =J7*$G$3 -> 32299.929 | K12: =K7*$G$3 -> 36797.82 | L12: =SUM(D12:K12) -> 110496.06 | M12: =M7*$G$3 -> 37345.68 | N12: =N7*$G$3 -> 45251.16 | O12: =O7*$G$3 -> 50056.336 | P12: =SUM(M12:O12) -> 132653.18 | Q12: =L12+P12 -> 243149.24 | U12: =U11-U11*25% -> 13236.75 | X12: =9000*2*12 -> 216000 | Y12: =9000*2*12 -> 216000 | Z12: =7822*2*12 -> 187728 | AA12: =7822*2*12 -> 187728 | AB12: =7822*2*12 -> 187728 | AC12: 219114 | AD12: 219114 | AE12: 273240 | AF12: 273240 | AG12: 273240 | AH12: 273240 | AI12: 273240 | AJ12: 282048 | AK12: =282048/12*3 -> 70512
B14: III | C14: PASURI | D14: =SUM(D15:D16) -> 0 | E14: =SUM(E15:E16) -> 0 | F14: =SUM(F15:F16) -> 0 | G14: =SUM(G15:G16) -> 0 | H14: =SUM(H15:H16) -> 0 | I14: =SUM(I15:I16) -> 0 | J14: =SUM(J15:J16) -> 0 | K14: =SUM(K15:K16) -> 1336956.9 | L14: =SUM(D14:K14) -> 1336956.9 | M14: =SUM(M15:M16) -> 0 | N14: =SUM(N15:N16) -> 0 | O14: =SUM(O15:O16) -> 3852345.9 | P14: =SUM(M14:O14) -> 3852345.9 | Q14: =L14+P14 -> 5189302.8
B15: 1 | C15: Shtëpi një katëshe [107.6 m2] | D15: 0 | E15: 0 | F15: 0 | G15: 0 | H15: 0 | I15: 0 | J15: 0 | K15: =(107.6*16567)-(107.6*16567)*25% -> 1336956.9 | L15: =SUM(D15:K15) -> 1336956.9 | M15: 0 | N15: 0 | O15: 0 | P15: =SUM(M15:O15) -> 0 | Q15: =L15+P15 -> 1336956.9 | X15: =0 -> 0 | Y15: =0 -> 0 | Z15: =0 -> 0 | AA15: =0 -> 0 | AB15: =0 -> 0 | AC15: =0 -> 0 | AD15: =0 -> 0 | AE15: =0 -> 0 | ... AI15: =0 -> 0 | AJ15: =AJ7-AJ11 -> 5831.8462 | AK15: =AK7-AK11 -> 4824.1843 | AL15: =SUM(AJ15:AK15) -> 10656.03
B16: 2 | C16: Kati I-rë + papaf. (256.4 m2) | D16: 0 | E16: 0 | F16: 0 | G16: 0 | H16: 0 | I16: 0 | J16: 0 | K16: 0 | M16: 0 | N16: 0 | O16: =(256.4*20033)-(256.4*20033)*25% -> 3852345.9 | P16: =SUM(M16:O16) -> 3852345.9 | Q16: =L16+P16 -> 3852345.9
B18: IV | C18: DETYRIME | D18: 0 | E18: 0 | F18: 0 | G18: 0 | H18: 0 | I18: 0 | J18: 0 | K18: 0 | L18: 0 | M18: 0 | N18: 0 | O18: 0 | Q18: 0
B20: V | C20: PASURI NETO: V = III - IV | D20: =D14-D18 -> 0 | E20: =E14-E18 -> 0 | F20: =F14-F18 -> 0 | G20: =G14-G18 -> 0 | H20: =H14-H18 -> 0 | I20: =I14-I18 -> 0 | J20: =J14-J18 -> 0 | K20: =K14-K18 -> 1336956.9 | ... O20: =O14-O18 -> 3852345.9 | P20: =SUM(M20:O20) -> 3852345.9 | Q20: =Q14-Q18 -> 5189302.8
B22: VI | C22: REZULTATI FIN. VI = I-II-V | D22: =D7-D11-D20 -> 486.88 | E22: =E7-E11-E20 -> 1460.64 | F22: =F7-F11-F20 -> 1465.1086 | G22: =G7-G11-G20 -> 1813.1714 | H22: =H7-H11-H20 -> 4590 | I22: =I7-I11-I20 -> 11510.603 | J22: =J7-J11-J20 -> 16639.357 | K22: =K7-K11-K20 -> -1318000.4 | L22: =SUM(D22:K22) -> -1280034.7 | M22: =M7-M11-M20 -> 19238.684 | N22: =N7-N11-N20 -> 23311.204 | O22: =O7-O11-O20 -> -3826559.3 | P22: =P7-P11-P20 -> -3784009.4 | Q22: =SUM(D22:K22)+SUM(M22:O22) -> -5064044.1 | R22: =Q7-Q11-Q20 -> -5064044.1
L24: =L7-L11-L20 -> -1280034.7 | Q24: =L22+P22 -> -5064044.1
Q26: =L22+P22 -> -5064044.1
Q28: =Q26+5064044 -> -0.10266667

Sheet KPA_ndërt.2 kate+ papaf. (2)
C3: Shtëpi 3 (tre)kate,Kodër Kamëz Tiranë/viti 1996 | G3: 0.66
B5: Nr. | C5: PËRSHKRIMI/PERIUDHA | D5: 9.1989 | E5: 1990 | F5: 1991 | G5: 1992 | H5: 1993 | I5: 1994 | J5: 1995 | K5: 1996 | L5: KUMUL. | M5: 1997 | N5: 1998 | O5: 1999 | P5: KUMUL. | Q5: TOTAL | S5: 1996 | T5: 1997 | U5: 1998 | V5: 1999 | X5: 2000 | Y5: 2001 | Z5: 2002 | AA5: 2003 | AB5: 2004 | AC5: 2005 | AD5: 2006 | AE5: 2007 | AF5: 2008 | AG5: 2009 | AH5: 2010 | AI5: 2011 | AJ5: 2012 | AK5: 3.2013
B7: I | C7: TARDHURA | D7: =SUM(D8:D9) -> 1432 | E7: =SUM(E8:E9) -> 4296 | F7: =SUM(F8:F9) -> 4309.1429 | G7: =SUM(G8:G9) -> 5332.8571 | H7: =SUM(H8:H9) -> 13500 | I7: =SUM(I8:I9) -> 33854.714 | J7: =SUM(J8:J9) -> 48939.286 | K7: =SUM(K8:K9) -> 55754.273 | L7: =SUM(D7:K7) -> 167418.27 | M7: =SUM(M8:M9) -> 56584.364 | N7: =SUM(N8:N9) -> 68562.364 | O7: =SUM(O8:O9) -> 75842.933 | P7: =SUM(P8:P9) -> 200989.66 | Q7: =SUM(Q8:Q9) -> 368407.93 | S7: 12883 | T7: 12883 | U7: 20033 | V7: 20033 | X7: =SUM(X8:X9) -> 81179.067 | Y7: =SUM(Y8:Y9) -> 87305 | Z7: =SUM(Z8:Z9) -> 97151 | AA7: =SUM(AA8:AA9) -> 109275.36 | AB7: =SUM(AB8:AB9) -> 123465.06 | AC7: =SUM(AC8:AC9) -> 145197.81 | AD7: =SUM(AD8:AD9) -> 162655.27 | AE7: =SUM(AE8:AE9) -> 182147.5 | ... AK7: =SUM(AK8:AK9) -> 75336.184
B8: 1 | C8: Të ardh.babai S.R._S. Sharra | D8: ='[6]Të ardhurat e prindërve_KPA'!R6 -> 1432 | E8: ='[6]Të ardhurat e prindërve_KPA'!R7 -> 4296 | F8: ='[6]Të ardhurat e prindërve_KPA'!R8 -> 4309.1429 | G8: ='[6]Të ardhurat e prindërve_KPA'!R9 -> 5332.8571 | H8: ='[6]Të ardhurat e prindërve_KPA'!R10 -> 13500 | I8: ='[6]Të ardhurat e prindërve_KPA'!R11 -> 28267.429 | J8: ='[6]Të ardhurat e prindërve_KPA'!R12 -> 33732.571 | K8: ='[6]Të ardhurat e prindërve_KPA'!R13 -> 43441.227 | L8: =SUM(D8:K8) -> 134311.23 | M8: ='[6]Të ardhurat e prindërve_KPA'!R14 -> 45613.636 | N8: ='[6]Të ardhurat e prindërve_KPA'!R15 -> 53601.136 | O8: ='[6]Të ardhurat e prindërve_KPA'!R16 -> 59453.333 | P8: =SUM(M8:O8) -> 158668.11 | Q8: =L8+P8 -> 292979.33 | X8: ='[6]Të ardhurat e prindërve_KPA'!R17 -> 63991.167 | Y8: ='[6]Të ardhurat e prindërve_KPA'!R18 -> 71028.5 | Z8: ='[6]Të ardhurat e prindërve_KPA'!R19 -> 76901 | AA8: ='[6]Të ardhurat e prindërve_KPA'!R20 -> 84107.5 | AB8: ='[6]Të ardhurat e prindërve_KPA'!R21 -> 90990.318 | AC8: ='[6]Të ardhurat e prindërve_KPA'!R22 -> 98218.49 | AD8: ='[6]Të ardhurat e prindërve_KPA'!R23 -> 106651.69 | AE8: ='[6]Të ardhurat e prindërve_KPA'!R24 -> 119383.5 | AF8: ='[6]Të ardhurat e prindërve_KPA'!R25 -> 131666.3 | AG8: ='[6]Të ardhurat e prindërve_KPA'!R26 -> 144538.06 | AH8: ='[6]Të ardhurat e prindërve_KPA'!R27 -> 152123.64 | AI8: ='[6]Të ardhurat e prindërve_KPA'!R28 -> 160717 | AJ8: ='[6]Të ardhurat e prindërve_KPA'!R29 -> 172017.73 | AK8: ='[6]Të ardhurat e prindërve_KPA'!R30/12*3 -> 45141.067
B9: 2 | C9: Të ardh.nëna S.R._H. Sharra | D9: 0 | E9: 0 | F9: 0 | G9: 0 | H9: 0 | I9: ='[6]Të ardhurat e prindërve_KPA'!S11 -> 5587.2857 | J9: ='[6]Të ardhurat e prindërve_KPA'!S12 -> 15206.714 | K9: ='[6]Të ardhurat e prindërve_KPA'!S13 -> 12313.045 | L9: =SUM(D9:K9) -> 33107.045 | M9: ='[6]Të ardhurat e prindërve_KPA'!S14 -> 10970.727 | N9: ='[6]Të ardhurat e prindërve_KPA'!S15 -> 14961.227 | O9: ='[6]Të ardhurat e prindërve_KPA'!S16 -> 16389.6 | P9: =SUM(M9:O9) -> 42321.555 | Q9: =L9+P9 -> 75428.6 | X9: ='[6]Të ardhurat e prindërve_KPA'!S17 -> 17187.9 | Y9: ='[6]Të ardhurat e prindërve_KPA'!S18 -> 16276.5 | Z9: ='[6]Të ardhurat e prindërve_KPA'!S19 -> 20250 | AA9: ='[6]Të ardhurat e prindërve_KPA'!S20 -> 25167.857 | AB9: ='[6]Të ardhurat e prindërve_KPA'!S21 -> 32474.743 | AC9: ='[6]Të ardhurat e prindërve_KPA'!S22 -> 46979.323 | AD9: ='[6]Të ardhurat e prindërve_KPA'!S23 -> 56003.577 | AE9: ='[6]Të ardhurat e prindërve_KPA'!S24 -> 62764 | AF9: ='[6]Të ardhurat e prindërve_KPA'!S25 -> 69336.5 | AG9: ='[6]Të ardhurat e prindërve_KPA'!S26 -> 82679.143 | AH9: ='[6]Të ardhurat e prindërve_KPA'!S27 -> 98981.357 | AI9: ='[6]Të ardhurat e prindërve_KPA'!S28 -> 112457 | AJ9: ='[6]Të ardhurat e prindërve_KPA'!S29 -> 115862.12 | AK9: =('[6]Të ardhurat e prindërve_KPA'!S30/12)*3 -> 30195.117
B11: II | C11: SHPENZIME | D11: =D12 -> 945.12 | E11: =E12 -> 2835.36 | F11: =F12 -> 2844.0343 | G11: =G12 -> 3519.6857 | H11: =H12 -> 8910 | I11: =I12 -> 22344.111 | J11: =J12 -> 32299.929 | K11: =K12 -> 36797.82 | L11: =SUM(D11:K11) -> 110496.06 | M11: =M12 -> 37345.68 | N11: =N12 -> 45251.16 | O11: =O12 -> 50056.336 | P11: =SUM(M11:O11) -> 132653.18 | Q11: =L11+P11 -> 243149.24 | U11: 17649 | X11: =SUM(X12) -> 216000 | Y11: =SUM(Y12) -> 216000 | Z11: =SUM(Z12) -> 187728 | AA11: =SUM(AA12) -> 187728 | AB11: =SUM(AB12) -> 187728 | AC11: =SUM(AC12) -> 219114 | AD11: =SUM(AD12) -> 219114 | AE11: =SUM(AE12) -> 273240 | ... AK11: =SUM(AK12) -> 70512
B12: 1 | C12: Shpenzime jetike | D12: =D7*$G$3 -> 945.12 | E12: =E7*$G$3 -> 2835.36 | F12: =F7*$G$3 -> 2844.0343 | G12: =G7*$G$3 -> 3519.6857 | H12: =H7*$G$3 -> 8910 | I12: =I7*$G$3 -> 22344.111 | J12: =J7*$G$3 -> 32299.929 | K12: =K7*$G$3 -> 36797.82 | L12: =SUM(D12:K12) -> 110496.06 | M12: =M7*$G$3 -> 37345.68 | N12: =N7*$G$3 -> 45251.16 | O12: =O7*$G$3 -> 50056.336 | P12: =SUM(M12:O12) -> 132653.18 | Q12: =L12+P12 -> 243149.24 | U12: =U11-U11*25% -> 13236.75 | X12: =9000*2*12 -> 216000 | Y12: =9000*2*12 -> 216000 | Z12: =7822*2*12 -> 187728 | AA12: =7822*2*12 -> 187728 | AB12: =7822*2*12 -> 187728 | AC12: 219114 | AD12: 219114 | AE12: 273240 | AF12: 273240 | AG12: 273240 | AH12: 273240 | AI12: 273240 | AJ12: 282048 | AK12: =282048/12*3 -> 70512
B14: III | C14: PASURI | D14: =SUM(D15:D16) -> 0 | E14: =SUM(E15:E16) -> 0 | F14: =SUM(F15:F16) -> 0 | G14: =SUM(G15:G16) -> 0 | H14: =SUM(H15:H16) -> 0 | I14: =SUM(I15:I16) -> 0 | J14: =SUM(J15:J16) -> 0 | K14: =SUM(K15:K16) -> 1782609.2 | L14: =SUM(D14:K14) -> 1782609.2 | M14: =SUM(M15:M16) -> 0 | N14: =SUM(N15:N16) -> 0 | O14: =SUM(O15:O16) -> 4509812.9 | P14: =SUM(M14:O14) -> 4509812.9 | Q14: =L14+P14 -> 6292422.1
B15: 1 | C15: Shtëpi një katëshe [107.6 m2] | D15: 0 | E15: 0 | F15: 0 | G15: 0 | H15: 0 | I15: 0 | J15: 0 | K15: =(107.6*16567) -> 1782609.2 | L15: =SUM(D15:K15) -> 1782609.2 | M15: 0 | N15: 0 | O15: 0 | P15: =SUM(M15:O15) -> 0 | Q15: =L15+P15 -> 1782609.2 | X15: =0 -> 0 | Y15: =0 -> 0 | Z15: =0 -> 0 | AA15: =0 -> 0 | AB15: =0 -> 0 | AC15: =0 -> 0 | AD15: =0 -> 0 | AE15: =0 -> 0 | ... AI15: =0 -> 0 | AJ15: =AJ7-AJ11 -> 5831.8462 | AK15: =AK7-AK11 -> 4824.1843 | AL15: =SUM(AJ15:AK15) -> 10656.03
B16: 2 | C16: Kati I-rë + papaf. (256.4 m2) | D16: 0 | E16: 0 | F16: 0 | G16: 0 | H16: 0 | I16: 0 | J16: 0 | K16: 0 | M16: 0 | N16: 0 | O16: =(256.4*20033)-(256.4*20033)*12.2% -> 4509812.9 | P16: =SUM(M16:O16) -> 4509812.9 | Q16: =L16+P16 -> 4509812.9
B18: IV | C18: DETYRIME | D18: 0 | E18: 0 | F18: 0 | G18: 0 | H18: 0 | I18: 0 | J18: 0 | K18: 0 | L18: 0 | M18: 0 | N18: 0 | O18: 0 | Q18: 0
B20: V | C20: PASURI NETO: V = III - IV | D20: =D14-D18 -> 0 | E20: =E14-E18 -> 0 | F20: =F14-F18 -> 0 | G20: =G14-G18 -> 0 | H20: =H14-H18 -> 0 | I20: =I14-I18 -> 0 | J20: =J14-J18 -> 0 | K20: =K14-K18 -> 1782609.2 | ... O20: =O14-O18 -> 4509812.9 | P20: =SUM(M20:O20) -> 4509812.9 | Q20: =Q14-Q18 -> 6292422.1
B22: VI | C22: REZULTATI FIN. VI = I-II-V | D22: =D7-D11-D20 -> 486.88 | E22: =E7-E11-E20 -> 1460.64 | F22: =F7-F11-F20 -> 1465.1086 | G22: =G7-G11-G20 -> 1813.1714 | H22: =H7-H11-H20 -> 4590 | I22: =I7-I11-I20 -> 11510.603 | J22: =J7-J11-J20 -> 16639.357 | K22: =K7-K11-K20 -> -1763652.7 | L22: =SUM(D22:K22) -> -1725687 | M22: =M7-M11-M20 -> 19238.684 | N22: =N7-N11-N20 -> 23311.204 | O22: =O7-O11-O20 -> -4484026.3 | P22: =P7-P11-P20 -> -4441476.4 | Q22: =SUM(D22:K22)+SUM(M22:O22) -> -6167163.4 | R22: =Q7-Q11-Q20 -> -6167163.4
L24: =L7-L11-L20 -> -1725687 | Q24: =L22+P22 -> -6167163.4
Q26: =L22+P22 -> -6167163.4
Q28: =Q26+5064044 -> -1103119.4

Sheet ndertesa 2 kate+papafingo
B2: Godine 2 kate 1999 | C2: 01.01.1997- 08.01.1999
B3: Pasuri | C3: =+C4+C5 -> 3448180.1
B4: Godine 2 Kt sip ndertimi 229.5 m2 | C4: 3448180.1
B5: Ndryshim likujditeti | C5: 0
B6: Detyrime | C6: =+C7 -> 0
B7: Detyrime | C7: 0
B8: Pasuri neto | C8: =+C3-C6 -> 3448180.1
B9: Te ardhura | C9: 164137.39
B10: Te ardhurat e Hamide Sharra | C10: 26222.84
B11: Te ardhurat e Sinan Sharra | C11: 137914.55
B12: Te ardhurat e subjektit
B13: Te ardhurat e b/shortes se subjektit
B14: Shpenzime | C14: =+C15+C16 -> 108330.68
B15: Shpenzime jetike | C15: 108330.68
B16: Shpenzime jetike | C16: 0
B17: Mundesi kursimi | C17: =+C9-C8-C14 -> -3392373.4
B20: Godine kati perdhes 1996 | C20: kumulative 1989- 1996
B21: Pasuri | C21: =+C22+C23 -> 1336956.9
B22: Godine 2 Kt sip ndertimi 107.6 m2 | C22: 1336956.9
B23: Ndryshim likujditeti | C23: 0
B24: Detyrime | C24: =+C25 -> 0
B25: Detyrime | C25: 0
B26: Pasuri neto | C26: =+C21-C24 -> 1336956.9
B27: Te ardhura | C27: =+C28+C29+C30+C31 -> 533708.55
B28: Te ardhurat e Hamide Sharra | C28: 48249.33
B29: Te ardhurat e Sinan Sharra | C29: 485459.22
B30: Te ardhurat e subjektit | C30: 0
B31: Te ardhurat e b/shortes se subjektit | C31: 0
B32: Shpenzime | C32: =+C33+C34 -> 352247.64
B33: Shpenzime jetike | C33: 352247.64
B34: Shpenzime mobilimi | C34: 0
B35: Mundesi kursimi | C35: =+C27-C26-C32 -> -1155496

Sheet KPA_ndërt.2 kate+ papaf.
C3: Shtëpi 3 (tre)kate,Kodër Kamëz Tiranë/viti 1996
B5: Nr. | C5: PËRSHKRIMI/PERIUDHA | D5: 9.1989 | E5: 1990 | F5: 1991 | G5: 1992 | H5: 1993 | I5: 1994 | J5: 1995 | K5: 1996 | L5: KUMUL. | M5: 1997 | N5: 1998 | O5: 1999 | P5: KUMUL. | Q5: TOTAL | S5: 1996 | T5: 1997 | U5: 1998 | V5: 1999 | X5: 2000 | Y5: 2001 | Z5: 2002 | AA5: 2003 | AB5: 2004 | AC5: 2005 | AD5: 2006 | AE5: 2007 | AF5: 2008 | AG5: 2009 | AH5: 2010 | AI5: 2011 | AJ5: 2012 | AK5: 3.2013
B7: I | C7: TARDHURA | D7: =SUM(D8:D9) -> 1432 | E7: =SUM(E8:E9) -> 4296 | F7: =SUM(F8:F9) -> 4309.1429 | G7: =SUM(G8:G9) -> 5332.8571 | H7: =SUM(H8:H9) -> 13500 | I7: =SUM(I8:I9) -> 33854.714 | J7: =SUM(J8:J9) -> 48939.286 | K7: =SUM(K8:K9) -> 55754.273 | L7: =SUM(D7:K7) -> 167418.27 | M7: =SUM(M8:M9) -> 56584.364 | N7: =SUM(N8:N9) -> 68562.364 | O7: =SUM(O8:O9) -> 75842.933 | P7: =SUM(P8:P9) -> 200989.66 | Q7: =SUM(Q8:Q9) -> 368407.93 | S7: 12883 | T7: 12883 | U7: 20033 | V7: 20033 | X7: =SUM(X8:X9) -> 81179.067 | Y7: =SUM(Y8:Y9) -> 87305 | Z7: =SUM(Z8:Z9) -> 97151 | AA7: =SUM(AA8:AA9) -> 109275.36 | AB7: =SUM(AB8:AB9) -> 123465.06 | AC7: =SUM(AC8:AC9) -> 145197.81 | AD7: =SUM(AD8:AD9) -> 162655.27 | AE7: =SUM(AE8:AE9) -> 182147.5 | ... AK7: =SUM(AK8:AK9) -> 75336.184
B8: 1 | C8: Të ardh.babai S.R._S. Sharra | D8: ='[5]Të ardhurat e prindërve_KPA'!R6 -> 1432 | E8: ='[5]Të ardhurat e prindërve_KPA'!R7 -> 4296 | F8: ='[5]Të ardhurat e prindërve_KPA'!R8 -> 4309.1429 | G8: ='[5]Të ardhurat e prindërve_KPA'!R9 -> 5332.8571 | H8: ='[5]Të ardhurat e prindërve_KPA'!R10 -> 13500 | I8: ='[5]Të ardhurat e prindërve_KPA'!R11 -> 28267.429 | J8: ='[5]Të ardhurat e prindërve_KPA'!R12 -> 33732.571 | K8: ='[5]Të ardhurat e prindërve_KPA'!R13 -> 43441.227 | L8: =SUM(D8:K8) -> 134311.23 | M8: ='[5]Të ardhurat e prindërve_KPA'!R14 -> 45613.636 | N8: ='[5]Të ardhurat e prindërve_KPA'!R15 -> 53601.136 | O8: ='[5]Të ardhurat e prindërve_KPA'!R16 -> 59453.333 | P8: =SUM(M8:O8) -> 158668.11 | Q8: =L8+P8 -> 292979.33 | X8: ='[5]Të ardhurat e prindërve_KPA'!R17 -> 63991.167 | Y8: ='[5]Të ardhurat e prindërve_KPA'!R18 -> 71028.5 | Z8: ='[5]Të ardhurat e prindërve_KPA'!R19 -> 76901 | AA8: ='[5]Të ardhurat e prindërve_KPA'!R20 -> 84107.5 | AB8: ='[5]Të ardhurat e prindërve_KPA'!R21 -> 90990.318 | AC8: ='[5]Të ardhurat e prindërve_KPA'!R22 -> 98218.49 | AD8: ='[5]Të ardhurat e prindërve_KPA'!R23 -> 106651.69 | AE8: ='[5]Të ardhurat e prindërve_KPA'!R24 -> 119383.5 | AF8: ='[5]Të ardhurat e prindërve_KPA'!R25 -> 131666.3 | AG8: ='[5]Të ardhurat e prindërve_KPA'!R26 -> 144538.06 | AH8: ='[5]Të ardhurat e prindërve_KPA'!R27 -> 152123.64 | AI8: ='[5]Të ardhurat e prindërve_KPA'!R28 -> 160717 | AJ8: ='[5]Të ardhurat e prindërve_KPA'!R29 -> 172017.73 | AK8: ='[5]Të ardhurat e prindërve_KPA'!R30/12*3 -> 45141.067
B9: 2 | C9: Të ardh.nëna S.R._H. Sharra | D9: 0 | E9: 0 | F9: 0 | G9: 0 | H9: 0 | I9: ='[5]Të ardhurat e prindërve_KPA'!S11 -> 5587.2857 | J9: ='[5]Të ardhurat e prindërve_KPA'!S12 -> 15206.714 | K9: ='[5]Të ardhurat e prindërve_KPA'!S13 -> 12313.045 | L9: =SUM(D9:K9) -> 33107.045 | M9: ='[5]Të ardhurat e prindërve_KPA'!S14 -> 10970.727 | N9: ='[5]Të ardhurat e prindërve_KPA'!S15 -> 14961.227 | O9: ='[5]Të ardhurat e prindërve_KPA'!S16 -> 16389.6 | P9: =SUM(M9:O9) -> 42321.555 | Q9: =L9+P9 -> 75428.6 | X9: ='[5]Të ardhurat e prindërve_KPA'!S17 -> 17187.9 | Y9: ='[5]Të ardhurat e prindërve_KPA'!S18 -> 16276.5 | Z9: ='[5]Të ardhurat e prindërve_KPA'!S19 -> 20250 | AA9: ='[5]Të ardhurat e prindërve_KPA'!S20 -> 25167.857 | AB9: ='[5]Të ardhurat e prindërve_KPA'!S21 -> 32474.743 | AC9: ='[5]Të ardhurat e prindërve_KPA'!S22 -> 46979.323 | AD9: ='[5]Të ardhurat e prindërve_KPA'!S23 -> 56003.577 | AE9: ='[5]Të ardhurat e prindërve_KPA'!S24 -> 62764 | AF9: ='[5]Të ardhurat e prindërve_KPA'!S25 -> 69336.5 | AG9: ='[5]Të ardhurat e prindërve_KPA'!S26 -> 82679.143 | AH9: ='[5]Të ardhurat e prindërve_KPA'!S27 -> 98981.357 | AI9: ='[5]Të ardhurat e prindërve_KPA'!S28 -> 112457 | AJ9: ='[5]Të ardhurat e prindërve_KPA'!S29 -> 115862.12 | AK9: =('[5]Të ardhurat e prindërve_KPA'!S30/12)*3 -> 30195.117
B11: II | C11: SHPENZIME | D11: =D12 -> 716 | E11: =E12 -> 2148 | F11: =F12 -> 2154.5714 | G11: =G12 -> 2666.4286 | H11: =H12 -> 6750 | I11: =I12 -> 16927.357 | J11: =J12 -> 24469.643 | K11: =K12 -> 27877.136 | L11: =SUM(D11:K11) -> 83709.136 | M11: =M12 -> 28292.182 | N11: =N12 -> 34281.182 | O11: =O12 -> 37921.467 | P11: =SUM(M11:O11) -> 100494.83 | Q11: =L11+P11 -> 184203.97 | U11: 17649 | X11: =SUM(X12) -> 216000 | Y11: =SUM(Y12) -> 216000 | Z11: =SUM(Z12) -> 187728 | AA11: =SUM(AA12) -> 187728 | AB11: =SUM(AB12) -> 187728 | AC11: =SUM(AC12) -> 219114 | AD11: =SUM(AD12) -> 219114 | AE11: =SUM(AE12) -> 273240 | ... AK11: =SUM(AK12) -> 70512
B12: 1 | C12: Shpenzime jetike | D12: =D7*50% -> 716 | E12: =E7*50% -> 2148 | F12: =F7*50% -> 2154.5714 | G12: =G7*50% -> 2666.4286 | H12: =H7*50% -> 6750 | I12: =I7*50% -> 16927.357 | J12: =J7*50% -> 24469.643 | K12: =K7*50% -> 27877.136 | L12: =SUM(D12:K12) -> 83709.136 | M12: =M7*50% -> 28292.182 | N12: =N7*50% -> 34281.182 | O12: =O7*50% -> 37921.467 | P12: =SUM(M12:O12) -> 100494.83 | Q12: =L12+P12 -> 184203.97 | U12: =U11-U11*25% -> 13236.75 | X12: =9000*2*12 -> 216000 | Y12: =9000*2*12 -> 216000 | Z12: =7822*2*12 -> 187728 | AA12: =7822*2*12 -> 187728 | AB12: =7822*2*12 -> 187728 | AC12: 219114 | AD12: 219114 | AE12: 273240 | AF12: 273240 | AG12: 273240 | AH12: 273240 | AI12: 273240 | AJ12: 282048 | AK12: =282048/12*3 -> 70512
B14: III | C14: PASURI | D14: =SUM(D15:D16) -> 0 | E14: =SUM(E15:E16) -> 0 | F14: =SUM(F15:F16) -> 0 | G14: =SUM(G15:G16) -> 0 | H14: =SUM(H15:H16) -> 0 | I14: =SUM(I15:I16) -> 0 | J14: =SUM(J15:J16) -> 0 | K14: =SUM(K15:K16) -> 1336956.9 | L14: =SUM(D14:K14) -> 1336956.9 | M14: =SUM(M15:M16) -> 0 | N14: =SUM(N15:N16) -> 0 | O14: =SUM(O15:O16) -> 3852345.9 | P14: =SUM(M14:O14) -> 3852345.9 | Q14: =L14+P14 -> 5189302.8
B15: 1 | C15: Shtëpi një katëshe [107.6 m2] | D15: 0 | E15: 0 | F15: 0 | G15: 0 | H15: 0 | I15: 0 | J15: 0 | K15: =(107.6*16567)-(107.6*16567)*25% -> 1336956.9 | L15: =SUM(D15:K15) -> 1336956.9 | M15: 0 | N15: 0 | O15: 0 | P15: =SUM(M15:O15) -> 0 | Q15: =L15+P15 -> 1336956.9 | X15: =0 -> 0 | Y15: =0 -> 0 | Z15: =0 -> 0 | AA15: =0 -> 0 | AB15: =0 -> 0 | AC15: =0 -> 0 | AD15: =0 -> 0 | AE15: =0 -> 0 | ... AI15: =0 -> 0 | AJ15: =AJ7-AJ11 -> 5831.8462 | AK15: =AK7-AK11 -> 4824.1843 | AL15: =SUM(AJ15:AK15) -> 10656.03
B16: 2 | C16: Kati I-rë + papaf. (256.4 m2) | D16: 0 | E16: 0 | F16: 0 | G16: 0 | H16: 0 | I16: 0 | J16: 0 | K16: 0 | M16: 0 | N16: 0 | O16: =(256.4*20033)-(256.4*20033)*25% -> 3852345.9 | P16: =SUM(M16:O16) -> 3852345.9 | Q16: =L16+P16 -> 3852345.9
B18: IV | C18: DETYRIME | D18: 0 | E18: 0 | F18: 0 | G18: 0 | H18: 0 | I18: 0 | J18: 0 | K18: 0 | L18: 0 | M18: 0 | N18: 0 | O18: 0 | Q18: 0
B20: V | C20: PASURI NETO: V = III - IV | D20: =D14-D18 -> 0 | E20: =E14-E18 -> 0 | F20: =F14-F18 -> 0 | G20: =G14-G18 -> 0 | H20: =H14-H18 -> 0 | I20: =I14-I18 -> 0 | J20: =J14-J18 -> 0 | K20: =K14-K18 -> 1336956.9 | ... O20: =O14-O18 -> 3852345.9 | P20: =SUM(M20:O20) -> 3852345.9 | Q20: =Q14-Q18 -> 5189302.8
B22: VI | C22: REZULTATI FIN. VI = I-II-V | D22: =D7-D11-D20 -> 716 | E22: =E7-E11-E20 -> 2148 | F22: =F7-F11-F20 -> 2154.5714 | G22: =G7-G11-G20 -> 2666.4286 | H22: =H7-H11-H20 -> 6750 | I22: =I7-I11-I20 -> 16927.357 | J22: =J7-J11-J20 -> 24469.643 | K22: =K7-K11-K20 -> -1309079.8 | L22: =SUM(D22:K22) -> -1253247.8 | M22: =M7-M11-M20 -> 28292.182 | N22: =N7-N11-N20 -> 34281.182 | O22: =O7-O11-O20 -> -3814424.4 | P22: =P7-P11-P20 -> -3751851.1 | Q22: =SUM(D22:K22)+SUM(M22:O22) -> -5005098.8 | R22: =Q7-Q11-Q20 -> -5005098.8
L24: =L7-L11-L20 -> -1253247.8 | Q24: =L22+P22 -> -5005098.8
Q26: =L22+P22 -> -5005098.8 | T26: =L22+Q22 -> -6258346.6
Q28: =Q26+5064044 -> 58945.167
B30: Nr. | C30: PËRSHKRIMI/PERIUDHA | D30: 2000 | E30: 2001 | F30: 2002 | G30: 2003 | H30: 2004 | I30: 2005 | J30: 2006 | K30: 05.10.2007 | L30: TOTAL
K31: 22.08.2007
B32: I | C32: TARDHURA | D32: =SUM(D33:D34) -> 81179.067 | E32: =SUM(E33:E34) -> 87305 | F32: =SUM(F33:F34) -> 97151 | G32: =SUM(G33:G34) -> 109275.36 | H32: =SUM(H33:H34) -> 123465.06 | I32: =SUM(I33:I34) -> 145197.81 | J32: =SUM(J33:J34) -> 162655.27 | K32: =SUM(K33:K34) -> 188328.75 | L32: =SUM(L33:L34) -> 913378.25
B33: 1 | C33: Të ardh.babai S.R._S. Sharra | D33: =X8 -> 63991.167 | E33: ='[5]Të ardhurat e prindërve_KPA'!R18 -> 71028.5 | F33: ='[5]Të ardhurat e prindërve_KPA'!R19 -> 76901 | G33: ='[5]Të ardhurat e prindërve_KPA'!R20 -> 84107.5 | H33: ='[5]Të ardhurat e prindërve_KPA'!R21 -> 90990.318 | I33: ='[5]Të ardhurat e prindërve_KPA'!R22 -> 98218.49 | J33: ='[5]Të ardhurat e prindërve_KPA'!R23 -> 106651.69 | K33: ='[5]Të ardhurat e prindërve_KPA'!R27/12*9 -> 114092.73 | L33: =SUM(E33:K33) -> 641990.23
B34: 2 | C34: Të ardh.nëna S.R._H. Sharra | D34: =X9 -> 17187.9 | E34: ='[5]Të ardhurat e prindërve_KPA'!S18 -> 16276.5 | F34: ='[5]Të ardhurat e prindërve_KPA'!S19 -> 20250 | G34: ='[5]Të ardhurat e prindërve_KPA'!S20 -> 25167.857 | H34: ='[5]Të ardhurat e prindërve_KPA'!S21 -> 32474.743 | I34: ='[5]Të ardhurat e prindërve_KPA'!S22 -> 46979.323 | J34: ='[5]Të ardhurat e prindërve_KPA'!S23 -> 56003.577 | K34: ='[5]Të ardhurat e prindërve_KPA'!S27/12*9 -> 74236.018 | L34: =SUM(E34:K34) -> 271388.02
B36: II | C36: SHPENZIME | D36: =SUM(D37) -> 81179.067 | E36: =SUM(E37) -> 87305 | F36: =SUM(F37) -> 97151 | G36: =SUM(G37) -> 109275.36 | H36: =SUM(H37) -> 123465.06 | I36: =SUM(I37) -> 145197.81 | J36: =SUM(J37) -> 162655.27 | K36: =SUM(K37) -> 188328.75 | L36: =SUM(L37) -> 913378.25
B37: 1 | C37: Shpenzime jetike | D37: =D33+D34 -> 81179.067 | E37: =E33+E34 -> 87305 | F37: =F33+F34 -> 97151 | G37: =G33+G34 -> 109275.36 | H37: =H33+H34 -> 123465.06 | I37: =I33+I34 -> 145197.81 | J37: =J33+J34 -> 162655.27 | K37: =K33+K34 -> 188328.75 | L37: =SUM(E37:K37) -> 913378.25
B39: III | C39: PASURI | D39: =SUM(D40:D43) -> 0 | E39: =SUM(E40:E43) -> 0 | F39: =SUM(F40:F43) -> 0 | G39: =SUM(G40:G43) -> 0 | H39: =SUM(H40:H43) -> 0 | I39: =SUM(I40:I43) -> 0 | J39: =SUM(J40:J43) -> 0 | K39: =SUM(K40:K43) -> 16055200 | L39: =SUM(L40:L43) -> 16055200
B40: 1 | C40: Shtëpi një katëshe [107.6 m2] | D40: 0 | E40: 0 | F40: 0 | G40: 0 | H40: 0 | I40: 0 | J40: 0 | K40: 0 | L40: =SUM(E40:K40) -> 0
B41: 2 | C41: Kati I-rë + papaf. (256.4 m2) | D41: 0 | E41: 0 | F41: 0 | G41: 0 | H41: 0 | I41: 0 | J41: 0 | K41: 0 | L41: =SUM(E41:K41) -> 0 | S41: EUR | T41: 122.72
B42: 3 | C42: Ap.banimi me sip. 56.5 m2 | D42: 0 | E42: 0 | F42: 0 | G42: 0 | H42: 0 | I42: 0 | J42: 0 | K42: =60000*122.72 -> 7363200 | L42: =SUM(E42:K42) -> 7363200 | S42: USD | T42: 86.92
B43: 4 | C43: Ndryshim gjendje lik. | D43: 0 | E43: 0 | F43: 0 | G43: 0 | H43: 0 | I43: 0 | J43: 0 | K43: =100000*86.92 -> 8692000 | L43: =SUM(E43:K43) -> 8692000
B45: IV | C45: DETYRIME | D45: 0 | E45: 0 | F45: 0 | G45: 0 | H45: 0 | I45: 0 | J45: 0 | K45: 0 | L45: =SUM(E45:K45) -> 0
B47: V | C47: PASURI NETO: V = III - IV | D47: =D39-D45 -> 0 | E47: =E39-E45 -> 0 | F47: =F39-F45 -> 0 | G47: =G39-G45 -> 0 | H47: =H39-H45 -> 0 | I47: =I39-I45 -> 0 | J47: =J39-J45 -> 0 | K47: =K39-K45 -> 16055200 | L47: =SUM(E47:K47) -> 16055200
B49: VI | C49: REZULTATI FIN. VI = I-II-V | D49: =D32-D36-D47 -> 0 | E49: =E32-E36-E47 -> 0 | F49: =F32-F36-F47 -> 0 | G49: =G32-G36-G47 -> 0 | H49: =H32-H36-H47 -> 0 | I49: =I32-I36-I47 -> 0 | J49: =J32-J36-J47 -> 0 | K49: =K32-K36-K47 -> -16055200 | L49: =L32-L36-L39 -> -16055200

Sheet lik këst. 5,000 eur-19.10.2012
E2: =KK!V14 -> 558192 | G2: =[7]sp_NRP_Balance!$L$568 -> 143036.03
E3: =E2/12 -> 46516 | G3: 5.88
E4: =E2/365 -> 1529.2932 | G4: =SUM(G2:G3) -> 143041.91
B7: Nr. | C7: PERIUDHA | E7: 01.01.-19.10.2012 | G7: 01.01.-19.10.2012
E8: I
B9: I | C9: TË ARDHURA | E9: =SUM(E10:E11) -> 1266837 | G9: =SUM(G10:G11) -> 1266837
B10: 1 | C10: Paga_S.R. | E10: =836886 -> 836886 | G10: =E10 -> 836886
B11: 2 | C11: Paga_B.S.R. | E11: =[8]Sheet1!$AH$19 -> 429951 | G11: =E11 -> 429951
B12: 3 | C12: Paradh.shitja e ban.K.K. | E12: 0 | G12: =E12 -> 0
B14: II | C14: SHPENZIME | E14: =SUM(E15:E17) -> 607612.9 | G14: =SUM(G15:G17) -> 607612.9
B15: 1 | C15: Shenz.jetike | E15: =E3*9+E4*19 -> 447700.57 | G15: =E15 -> 447700.57
B16: 2 | C16: Shpenz.udh. | E16: 0 | G16: =E16 -> 0
B17: 3 | C17: Int.kredie | E17: ='Kredi ne NBG '!L61*KK!V4 -> 159912.33 | G17: =E17 -> 159912.33
B19: III | C19: PASURI | E19: =SUM(E20) -> 80814.85 | F19: =SUM(F20) -> 0 | G19: =SUM(G20) -> 191648.18
B20: 1 | C20: Ndrysh.gjend.lik.bankë | E20: =E21-D21 -> 80814.85 | G20: =G21-F21 -> 191648.18 | I20: =G17-G26 -> 645460.29
B21: a | C21: Total gjend.lik. | D21: =SUM(D22:D23) -> 62227.06 | E21: =SUM(E22:E23) -> 143041.91 | F21: =SUM(F22:F23) -> 1073923.1 | G21: =SUM(G22:G23) -> 1265571.2
B22: b | C22: Gjendje lik. bankë | D22: =' Likujditete'!W53 -> 62227.06 | E22: =G4 -> 143041.91 | F22: =D22 -> 62227.06 | G22: =G4 -> 143041.91
B23: c | C23: Gjendje lik. cash | F23: =' Likujditete'!W56 -> 1011696 | G23: =F23+H23 -> 1122529.3 | H23: =(140000/12)*9.5 -> 110833.33
B25: IV | C25: DETYRIME | D25: =SUM(D26:D27) -> 0 | E25: =SUM(E26:E27) -> -1184148 | F25: =SUM(F26:F27) -> 0 | G25: =SUM(G26:G27) -> -1184148
B26: 1 | C26: Princ.kredie NBG | E26: =-'Kredi ne NBG '!K61*KK!V4 -> -485547.96 | G26: =E26 -> -485547.96
B27: 2 | C27: Shlyer det."KDK" ShPK | E27: =-5000*139.72 -> -698600 | G27: =E27 -> -698600 | H27: 139.72
B29: V | C29: PASURI NETO | D29: =(D19)-(D25) -> 0 | E29: =(E19)-(E25) -> 1264962.8 | F29: =(F19)-(F25) -> 0 | G29: =(G19)-(G25) -> 1375796.1
B31: VI | C31: REZ.FIN: VI=I-II-V | D31: 0 | E31: =(E9)-(E14)-(E29) -> -605738.71 | F31: =(F9)-(F14)-(F29) -> 0 | G31: =(G9)-(G14)-(G29) -> -716572.05
C32: REZ: (në euro)

Sheet anal.fin.2015
B3: Nr. | C3: PASURIA/PERIUDHA | D3: 2014 | E3: 2015
B5: I | C5: TË ARDHURA | E5: =SUM(E6:E8) -> 6169790
B6: 1 | C6: Të ardh.S.R._pagat | E6: =[7]sp_NRP_Balance!$N$709 -> 1120422
B7: 2 | C7: Të ardh.B.S.R._pagat | E7: =824168 -> 824168
B8: 3 | C8: Paradhënie_I.Lala_shitje banese K-K | E8: =30000*F8 -> 4225200 | F8: 140.84 | G8: 19.06.2015
B10: II | C10: SHPENZIME | E10: =SUM(E11:E17) -> 1796082.3
B11: 1 | C11: Shpenz.jetike | E11: 897104
B12: 2 | C12: Shpenz.shkoll.Enea Sharra | E12: =(40000/10)*4 -> 16000
B13: 3 | C13: Shpenz.shkoll.Ersa Sharra_"F.Konica" | E13: =+(1800/10*4+1800/10*6)*[9]KK!Y4 -> 247770
B14: 4 | C14: Shpenz.udhët._TIMS | E14: 37166
B15: 5 | C15: Shpenz.mobilimi | E15: =4000*[9]KK!X4/3 -> 186813.33
B16: 6 | C16: Shpenz.legal.godinës tre kate K.K. | E16: 410000
B17: 7 | C17: Shpenz,taksa vendore_tokë bujq. | E17: 1229
B19: III | C19: PASURI | E19: =SUM(E20:E21) -> 4219811
B20: 1 | C20: Shlyer detyrim ndaj "KDK" ShPK | E20: =24400*140.84+230*138.33+5000*137.39 -> 4155261.9
B21: 2 | C21: Ndrysh.gjend.lik. | E21: =E22-D22 -> 64549.13
B22: a | C22: Total gjendje lik. | D22: =D23+D24 -> 1352928.7 | E22: =E23+E24 -> 1417477.8
B23: b | C23: Gjendje lik.bankë | D23: ='[9] Likujditete'!Z53 -> 546609.66 | E23: ='[9] Likujditete'!AA53 -> 611158.79
B24: c | C24: Gjendje lik.cash | D24: ='[9] Likujditete'!Z56 -> 806319 | E24: ='[9] Likujditete'!AA56 -> 806319
B26: IV | C26: DETYRIME | D26: =SUM(D27:D29) -> 0 | E26: =SUM(E27:E29) -> 0
B27: 1 | C27: Detyrime ndaj shoq."KDK" ShPK | D27: - | E27: -
B28: 2 | C28: Detyrim ndaj A.Ramadani | D28: - | E28: -
B29: 3 | C29: Detyrim ndaj babait | D29: - | E29: -
B31: V | C31: PASURI NETO: V = III - IV | E31: =E19-E26 -> 4219811
B49: VI | C49: REZULTATI FIN. VI = I - II - V | E49: =E5-E10-E31 -> 153896.64
G54: Nisur nga fakti që këto pagesa janë kryer në datat 19.06.2015 shuma 24,400, më 13.11.2015 shuma 230 euro, dhe më 30.12.2015 shuma 5,000 euro
G56: 140.84/19.06.2015
G57: 138.33/13.11.2015
G58: 137.39/30.12.2015

Sheet Automjeti ne 14.11.2008
C2: 14.11.2008
B3: Pasuria | C3: =SUM(C4:C5) -> 600527.05
B4: =+'Analiza '!B8 -> Automjet Daimler Chrysler | C4: =+'Analiza '!P8 -> 677503.75
B5: Ndryshim likujditeti | C5: -76976.7
B6: Detyrime | C6: =SUM(C7:C8) -> -170238.21
B7: Kredi ne NBG 46,000 Euro
B8: Shlyerje e kredise ne NBG 46,000 Euro | C8: =-(346+345+345+346)*KK!R4 -> -170238.21
B9: Pasuria Neto | C9: =+C3-C6 -> 770765.27
B10: Te ardhura | C10: =SUM(C11:C13) -> 1521868
B11: Te ardhurat e subjektit | C11: =+'Analiza '!P27/12*11 -> 829838.17
B12: Te ardhurat e Bshortes se Subjektit | C12: =+'Analiza '!P28/12*11 -> 292029.83
B13: Te ardhura nga shitja e automjetit Mercedes Benz dt 09.09.2008 | C13: =+'Analiza '!P29 -> 400000
B14: Shpenzime | C14: =SUM(C15:C16) -> 504635.47
B15: Shpenzime Jetike | C15: =+'Analiza '!P34/12*11 -> 500940
B16: TIMS | C16: 3695.475
B17: Mundesia per kursime | C17: =+C10-C9-C14 -> 246467.26

Sheet Apartamenti 
B2: Pagesat e kryera | C2: 01.01.2008-01.08.2008 | F2: 01.01.2012- 19.10.2012 | H2: Pagesat e kryera | I2: 01.01.2013-31.05.2013 | K2: Pagesat e kryera | L2: 19.06.2015 | M2: 19.06.2015-13.11.2015 | N2: 13.11.2015-30.12.2015
C3: 45968 | E3: Pagesat e kryera | F3: 5000 | I3: 285 | L3: 24400 | M3: 230 | N3: 5000
C4: 01.08.2008 | F4: 19.10.2012 | I4: 31.05.2013 | L4: 6 Muaj | M4: 5 Muaj | N4: 1 Muaj
B5: Pasuria | C5: =SUM(C6:C7) -> 12134283 | E5: Pasuria | F5: =SUM(F6:F6) -> -270515.11 | H5: Pasuria | I5: =SUM(I6:I6) -> 51878.07 | L5: data e kryerjes se pageses 19.06.2015 | M5: data e kryerjes se pageses 13.11.2015 | N5: data e kryerjes se pageses 30.12.2015
B6: Apartament banimi me sip 128.1 m2 | C6: 11681396 | E6: Ndryshim likujditeti | F6: -270515.11 | H6: Ndryshim likujditeti | I6: 51878.07 | K6: Pasuria | L6: =SUM(L7) -> -112009.6 | M6: =SUM(M7) -> -638532.69 | N6: =SUM(N7) -> -943326.58
B7: Ndryshim likujditeti | C7: 452886.71 | E7: Detyrime | F7: =SUM(F8:F9) -> -1344106.4 | H7: Detyrime | I7: =SUM(I8:I11) -> -14599.69 | K7: Ndryshim likujditeti | L7: -112009.6 | M7: =562761.91-L23 -> -638532.69 | N7: -943326.58
B8: Detyrime | C8: =SUM(C9:C12) -> 11472479 | E8: Shlyerje e kredise ne NBG 46,000 Euro | F8: =-(165+165+165+165+162+165+165+3090+198+180)*KK!V4 -> -645506.4 | H8: Shlyerje e kredise ne NBG 46,000 Euro | I8: =-(165+165+165+165+162)*KK!V4 -> -114849.84 | K8: Detyrime | L8: =+L9 -> -3358660 | M8: =+M9 -> -31659.5 | N8: =+N9 -> -688250
B9: Kredi ne NBG 46,000 Euro | C9: =+'Analiza '!P15 -> 5666395 | E9: Shlyerje detyrim ndaj KDK | F9: =-5000*KK!V4 -> -698600 | H9: Shlyerje detyrim ndaj KDK | I9: =+'Analiza '!U18 -> -39959.85 | K9: Shlyerje detyrim ndaj KDK | L9: -3358660 | M9: -31659.5 | N9: -688250
B10: Shlyerje e kredise ne NBG 46,000 Euro | C10: -212859.36 | E10: Pasuria Neto | F10: =+F5-F7 -> 1073591.3 | H10: Detyrim per garazhdin | I10: =1000*KK!W4 -> 140210 | K10: Pasuria Neto | L10: =+L6-L8 -> 3246650.4 | M10: =+M6-M8 -> -606873.19 | N10: =+N6-N8 -> -255076.58
B11: Detyrim ndaj KDK | C11: =+'Analiza '!P17 -> 11681396 | E11: Te ardhura | F11: =SUM(F12:F13) -> 1307280.8 | H11: =+'Analiza '!B19 -> Hua nga babai 4000 Euro 2013 | I11: 0 | K11: Te ardhura | L11: =SUM(L12:L14) -> 5099553.5 | M11: =SUM(M12:M14) -> 808377.92 | N11: =SUM(N12:N14) -> 161675.58
B12: Shlyerje detyrim ndaj KDK | C12: =+'Analiza '!P18 -> -5662453.2 | E12: Te ardhurat e subjektit | F12: =983776/12*10 -> 819813.33 | H12: Pasuria Neto | I12: =+I5-I7 -> 66477.76 | K12: Te ardhurat e subjektit | L12: 561746.5 | M12: 468122.08 | N12: 93624.417
B13: Pasuria Neto | C13: =+C5-C8 -> 661804.23 | E13: Te ardhurat e Bshortes se Subjektit | F13: =584961/12*10 -> 487467.5 | H13: Te ardhura | I13: =SUM(I14:I15) -> 631071.67 | K13: Te ardhurat e Bshortes se Subjektit | L13: 408307 | M13: 340255.83 | N13: 68051.167
B14: Te ardhura | C14: =SUM(C15:C16) -> 815904 | E14: Shpenzime | F14: =SUM(F15:F15) -> 465160 | H14: Te ardhurat e subjektit | I14: =917794/12*5 -> 382414.17 | K14: PARADHENIE per shitjen e baneses ne K.Kamez | L14: 4129500 | M14: 0
B15: Te ardhurat e subjektit | C15: =+'Analiza '!P27/12*8 -> 603518.67 | E15: Shpenzime Jetike | F15: =558192/12*10 -> 465160 | H15: Te ardhurat e Bshortes se Subjektit | I15: =596778/12*5 -> 248657.5 | K15: Shpenzime | L15: =SUM(L16:L22) -> 651608.5 | M15: =SUM(M16:M22) -> 858124.33 | N15: =SUM(N16:N22) -> 286349
B16: Te ardhurat e Bshortes se Subjektit | C16: =+'Analiza '!P28/12*8 -> 212385.33 | E16: Mundesia per kursime | F16: =+F11-F10-F14 -> -231470.46 | H16: Shpenzime | I16: =SUM(I17:I19) -> 723531.64 | K16: Shpenzime Jetike | L16: 448552 | M16: 373793.33 | N16: 74758.667
B17: Shpenzime | C17: =SUM(C18:C19) -> 322475.47 | H17: Shpenzime Jetike | I17: =564096/12*5 -> 235040 | K17: TIMS | L17: 37165.5 | M17: 0 | N17: 0
B18: Shpenzime Jetike | C18: =+'Analiza '!P34/12*7 -> 318780 | H18: TIMS | I18: 392588 | K18: Shpenzime per legalizimin e Godine banimi 3 kateshe 01.07.2015 | M18: 410000 | N18: 0
B19: TIMS | C19: 3695.475 | H19: Shpenzime per shkollimin e Ersa Sharra Shkolla Faik Konica | I19: =+'Analiza '!U39 -> 95903.64 | K19: Shpenzime per Taksat vendore te tokes bujqesore | L19: 1229 | M19: 0
B20: Mundesia per kursime | C20: =+C14-C17-C13 -> -168375.71 | H20: Mundesia per kursime | I20: =+I13-I12-I16 -> -158937.73 | K20: Shpenzime per shkollimin e Enea Sharra | L20: 16000
K21: Shpenzime per shkollimin e Ersa Sharra Shkolla Faik Konica | L21: 148662 | M21: 74331 | N21: 24777
K22: Shpenzime Mobilimi | N22: 186813.33
K23: Mundesia per kursime | L23: =+L11-L10-L15 -> 1201294.6 | M23: =+M11-M10-M15 -> 557126.77 | N23: =+N11-N10-N15 -> 130403.16

Sheet Garazhd 
C2: 13.04.2013
B3: =+'Analiza '!B4 -> Pasuria | C3: =SUM(C4:C5) -> 1164373.1
B4: =+'Analiza '!B9 -> Garazhd me sip 45 m2 | C4: =11000*KK!W4 -> 1542310
B5: =+'Analiza '!B11 -> Ndryshim likujditeti | C5: -377936.93
B6: =+'Analiza '!B14 -> Detyrime | C6: =SUM(C7:C11) -> 2623.84
B7: =+'Analiza '!B16 -> Shlyerje e kredise ne NBG 46,000 Euro | C7: =-(140+138+138+140+140)*KK!W4 -> -97586.16
B8: =+'Analiza '!B18 -> Shlyerje detyrim ndaj KDK | C8: -40000
B9: =+'Analiza '!B19 -> Hua nga babai 4000 Euro 2013
B10: =+'Analiza '!B22 -> Detyrim per garazhdin | C10: 1542310
B11: =+'Analiza '!B23 -> Shlyerje detyrim per garazhdin | C11: -1402100
B12: =+'Analiza '!B24 -> Pasuria Neto | C12: =+C3-C6 -> 1161749.2
B13: =+'Analiza '!B26 -> Te ardhura | C13: =SUM(C14:C15) -> 504857.33
B14: =+'Analiza '!B27 -> Te ardhurat e subjektit | C14: =917794/12*4 -> 305931.33
B15: =+'Analiza '!B28 -> Te ardhurat e Bshortes se Subjektit | C15: =596778/12*4 -> 198926
B16: =+'Analiza '!B33 -> Shpenzime | C16: =SUM(C17:C20) -> 261952.14
B17: =+'Analiza '!B34 -> Shpenzime Jetike | C17: =564096/12*3.5 -> 164528
B18: =+'Analiza '!B35 -> TIMS
B19: =+'Analiza '!B37 -> Shpenzime per Taksat vendore te tokes bujqesore | C19: 1520.5
B20: =+'Analiza '!B39 -> Shpenzime per shkollimin e Ersa Sharra Shkolla Faik Konica | C20: =+'Analiza '!U39 -> 95903.64
B21: =+'Analiza '!B42 -> Mundesia per kursime | C21: =+C13-C12-C16 -> -918844.04

Sheet Garazh_KPA
C4: Nr. | D4: PASURIA/PERIUDHA | E4: 31.12.2012 | F4: 13.04.2013 | G4: 13.04.2013 | H4: NDRYSHIMET
F5: KPK | G5: KPA
C6: I | D6: TË ARDHURA (*) | F6: =SUM(F7:F8) -> 504857 | G6: =SUM(G7:G8) -> 438197
C7: 1 | D7: Të ardh.S.R._pagat | E7: - | F7: 305931 | G7: 302300 | H7: ≠
C8: 2 | D8: Të ardh.B.S.R._pagat | E8: - | F8: 198926 | G8: 135897 | H8: ≠
C10: II | D10: SHPENZIME | F10: =SUM(F11:F15) -> 261953 | G10: =SUM(G11:G15) -> 310792
C11: 1 | D11: Shpenz.jetike | E11: - | F11: 164528 | G11: 164528
C12: 2 | D12: Shpenz.inter. kredie_NBG Albania ShA | E12: - | F12: - | G12: 48839 | H12: ≠(**)
C13: 3 | D13: Shpenz.shkoll.E.Sharra_"F.Konica" | E13: - | F13: 95904 | G13: 95904
C14: 4 | D14: Shpenz.udhët._TIMS | E14: - | F14: - | G14: -
C15: 5 | D15: Shpenz,taksa vendore_tokë bujq. | E15: - | F15: 1521 | G15: 1521
C17: III | D17: PASURI | E17: 0 | F17: =SUM(F18:F19) -> 1164373 | G17: =SUM(G18:G19) -> 1525132
C18: 1 | D18: Garazh_45 m2_kont.nr.2008/513,13.04.2013 | E18: - | F18: 1542310 | G18: 1542310
C19: 2 | D19: Ndrysh.gjend.lik. | E19: - | F19: -377937 | G19: -17178 | H19: ≠(***)
C20: a | D20: Total gjendje lik. | E20: 1212850 | F20: - | G20: 1195672
C21: b | D21: Gjendje lik.bankë | E21: 61154 | F21: - | G21: 43976
C22: c | D22: Gjendje lik.cash | E22: 1151696 | F22: - | G22: 1151696
C24: IV | D24: DETYRIME | E24: - | F24: =SUM(F25:F29) -> 2624 | G24: =SUM(G25:G29) -> 168889
C25: 1 | D25: Detyrim ndaj shoq. "KDK" ShPK_garazh | E25: - | F25: 1542310 | G25: 1542310
C26: 2 | D26: Shlyerje detyr._"KDK" ShPK_garazh | E26: - | F26: -1402100 | G26: -1402100
C27: 3 | D27: Shlyer.princ.kredie_NBG Albania ShA | E27: - | F27: -97586 | G27: 28679
C28: 4 | D28: Shlyerje detyr._"KDK" ShPK_apart. | E28: - | F28: -40000 | G28: - | H28: ≠(****)
C29: 5 | D29: Hua nga babai_4,000 euro/2013 | E29: - | F29: - | G29: -
C31: V | D31: PASURI NETO: V = III - IV | E31: - | F31: =F17-F24 -> 1161749 | G31: =G17-G24 -> 1356243
C33: VI | D33: REZULTATI FIN. VI = I - II - V | E33: - | F33: =F6-F10-F31 -> -918845 | G33: =G6-G10-G31 -> -1228838

Sheet Automjeti 2017
D2: 02.03.2017
C3: Pasuria | D3: =SUM(D4:D5) -> 874650
C4: Automjet Mercedes Benz 02.03.2017 | D4: 930650
C5: Ndryshim likujditeti | D5: -56000
C6: Detyrime | D6: =SUM(D7:D9) -> 161135.4
C7: Detyrim ndaj KDK | D7: 0
C8: Shlyerje detyrim ndaj KDK | D8: -104764.6
C9: Hua nga nena 2000 Euro 2017 | D9: 265900
C10: Pasuria Neto | D10: =+D3-D6 -> 713514.6
C11: Te ardhura | D11: =SUM(D12:D13) -> 552226.5
C12: Te ardhurat e subjektit | D12: =1264368/12*3 -> 316092
C13: Te ardhurat e Bshortes se Subjektit | D13: =944538/12*3 -> 236134.5
C14: Shpenzime | D14: =SUM(D15:D17) -> 160224.54
C15: Shpenzime Jetike | D15: =952216.216216216/12*2 -> 158702.7
C16: TIMS
C17: Shpenzime per Taksat vendore te tokes bujqesore | D17: 1521.84
C18: Mundesia per kursime | D18: =+D11-D10-D14 -> -321512.64

Sheet Automjeti 2017 KPA
B2: Nr. | C2: PËRSHKRIMI/PERIUDHA | D2: 01.01.2017 02.03.2017
B4: I | C4: TË ARDHURA | D4: =SUM(D5:D6) -> 351346
B5: 1 | C5: Të ardh. S.R. | D5: =99845+99845 -> 199690
B6: 2 | C6: Të ardh. B.S.R. | D6: =75828*2 -> 151656
B8: II | C8: SHPENZIME | D8: =SUM(D9:D11) -> 161255.58
B9: 1 | C9: Shpenzime jetike | D9: =(940368/365)*(31+29+2) -> 159733.74
B10: 2 | C10: Shpenz._taksat vend. të tokës bujq. | D10: 1521.84
B11: 3 | C11: Shpenz.udhët.TIMS
B13: III | C13: PASURI | D13: =SUM(D14:D15) -> 887840
B14: 1 | C14: Automj.Mercedes Benz_02.03.2017 | D14: =7000*135.12 -> 945840
B15: 2 | C15: Ndrysh.gjendje lik. | D15: -58000
B17: IV | C17: DETYRIME | D17: =SUM(D18:D20) -> 161135.4
B18: 1 | C18: Detyrim ndaj shoq."KDK" ShPK | D18: 0
B19: 2 | C19: Shlyerje det.ndaj "KDK" ShPK | D19: =-788*132.95 -> -104764.6
B20: 3 | C20: Marrë hua nga nëna | D20: =2000*132.95 -> 265900
B22: V | C22: PASURI NETO V = III - IV | D22: =D13-D17 -> 726704.6
B24: VI | C24: REZULTATI Vi= I - II - V | D24: =D4-D8-D22 -> -536614.18

Sheet Sheet1

Sheet Te ardhura S Sharra
B2: 13.04.2013
B3: Kur e ka marre huane
B4: analiza e babait per 4000 eruo
B7: TE ARDHURAT
B8: Hamide Besim Sharra | C8: Te ardhurat periudha | D8: Pension pleqerie | E8: 1989 | F8: 1990 | G8: 1991 | H8: 1992 | I8: 1993 | J8: 1994 | K8: 1995 | L8: 1996 | M8: 1997 | N8: 1998 | O8: 1999 | P8: 2000 | Q8: 2001 | R8: 2002 | S8: 2003 | T8: 2004 | U8: 2005 | V8: 2006 | W8: 2007 | X8: 2008 | Y8: 2009 | Z8: 2010 | AA8: 2011 | AB8: 2012 | AC8: mars 2013
B9: vertetim nr 442 prot date 19.10.2021 | C9: pensioni Hamide sipas ISSH shuma totale 03.07.1994-31.10.2021 eshte 2,014,575 leke | J9: 5587.2857 | K9: 9845 | L9: 6827.6818 | M9: 10970.727 | N9: 14047 | O9: 14461.412 | P9: 11602.588 | Q9: 16276.5 | R9: 20250 | S9: 22614 | T9: 32474.743 | U9: 16747.4 | V9: 55307.34 | W9: 62764 | X9: 69336.5 | Y9: 82679.143 | Z9: 98981.357 | AA9: 112457 | AB9: 115862.12 | AC9: 29354.308
B10: Vertetim leshuar ne 15.06.1994 | C10: 1janar -31 dhjetor 1993 ka paguar kontribut te sigurimeve shoqerore si Bujk privat shumen 1620 leke MA 409617/315393 dt.21.07.1993 dhe per periudhen 01.01.1994-01.06.1994 shumen 823 leke | I10: =+(1620*100)/9.4 -> 17234.043 | J10: =+(823*100)/9.4 -> 8755.3191
D11: TOTALI | E11: =+E9+E10 -> 0 | F11: =+F9+F10 -> 0 | G11: =+G9+G10 -> 0 | H11: =+H9+H10 -> 0 | I11: =+I9+I10 -> 17234.043 | J11: =+J9+J10 -> 14342.605 | K11: =+K9+K10 -> 9845 | L11: =+L9+L10 -> 6827.6818 | ... AC11: =+AC9+AC10 -> 29354.308
B13: Sinan Hamit Sharra | C13: Te ardhurat periudha | D13: Pension pleqerie | E13: 1989 | F13: 1990 | G13: 1991 | H13: 1992 | I13: 1993 | J13: 1994 | K13: 1995 | L13: 1996 | M13: 1997 | N13: 1998 | O13: 1999 | P13: 2000 | Q13: 2001 | R13: 2002 | S13: 2003 | T13: 2004 | U13: 2005 | V13: 2006 | W13: 2007 | X13: 2008 | Y13: 2009 | Z13: 2010 | AA13: 2011 | AB13: 2012 | AC13: 2013
C14: nga Shtator 1989 deri ne nentor 2016 Shuma totale 2,427,296 vlera 36 vjet e 8 muaj vlera e pensionit 5516 leke ne muaj | E14: 22066.328 | F14: 66198.984 | G14: 66198.984 | H14: 66198.984 | I14: 66198.984 | J14: 66198.984 | K14: 66198.984 | L14: 66198.984 | M14: 66198.984 | N14: 66198.984 | O14: 66198.984 | P14: 66198.984 | Q14: 66198.984 | R14: 66198.984 | S14: 66198.984 | T14: 66198.984 | U14: 66198.984 | V14: 66198.984 | W14: 66198.984 | X14: 66198.984 | Y14: 66198.984 | Z14: 66198.984 | AA14: 66198.984 | AB14: 66198.984 | AC14: 16549.746
C15: Ndihme ekonomike paaftesi (Nga llogaria bankare ne intesa san paolo) | AB15: =+X22 -> 221200 | AC15: =+Y22/12*3 -> 57150
D16: TOTALI | E16: =+E15+E14 -> 22066.328 | F16: =+F15+F14 -> 66198.984 | G16: =+G15+G14 -> 66198.984 | H16: =+H15+H14 -> 66198.984 | I16: =+I15+I14 -> 66198.984 | J16: =+J15+J14 -> 66198.984 | K16: =+K15+K14 -> 66198.984 | L16: =+L15+L14 -> 66198.984 | ... AC16: =+AC15+AC14 -> 73699.746
B19: LIKUJDITETE
B20: Prinderit Hamide dhe Sinan Sharra | C20: BANKA | D20: Nr Llogarise | E20: monedha | F20: 1994 | G20: 1995 | H20: 1996 | I20: 1997 | J20: 1998 | K20: 1999 | L20: 2000 | M20: 2001 | N20: 2002 | O20: 2003 | P20: 2004 | Q20: 2005 | R20: 2006 | S20: 2007 | T20: 2008 | U20: 2009 | V20: 2010 | W20: 2011 | X20: 2012 | Y20: 2013 | Z20: 2014 | AA20: 2015 | AB20: 2016 | AC20: TOTAL | AD20: DVETTING | AE20: 2017 | AF20: 2018 | AG20: 2019
B21: Hamide Sharra 31.12…… | C21: Intesa san paolo | D21: 847639 | E21: lek | X21: 13525 | Y21: 22222.54 | Z21: 112722.54 | AA21: 442.54
B22: kjo llogari eshte perdorur per kalimin e ndihmes ekonomike paaftesi Sinan Sharra | X22: 221200 | Y22: 228600 | Z22: 296400 | AA22: 273120
B23: Sinan Hamit Sharra pension verberie | C23: Shkresa nr 684/2 dt 22.02.2022 nga Bashkia Tirane | X23: =10600*10+11200+43200 -> 160400 | Y23: =10800*8+11100 -> 97500 | Z23: =11100*11+13500 -> 135600 | AA23: =11259*9+11530+11390*2 -> 135641 | AB23: =11390*9+11630 -> 114140
B24: Hamide Sharra Pagese kUjdestarie per bshortin | C24: Shkresa nr 684/2 dt 22.02.2022 nga Bashkia Tirane | X24: =10600*10+11200+10800 -> 128000 | Y24: =10800*8+11100 -> 97500 | Z24: =11100*11+13500 -> 135600 | AA24: =11259*9+11530+11390*2 -> 135641 | AB24: =11390*9+11630 -> 114140
B25: Hamide Sharra 31.12…… | C25: RZB | D25: 185095 | E25: Euro | AE25: =+(75000-50000)*KK!AA4 -> 3323750
B28: Sinan Sharra 31.12…… | C28: RZB | D28: 185095 | E28: USD | S28: =100000*KK!Q5 -> 8303000 | T28: =5523.55*KK!Q5 -> 458620.36 | U28: =5042*KK!R5 -> 458620.32 | V28: 0
B29: Depozite krijuar ne 22.08.2007 ne 100,000 USD | C29: Interesi perfituar nga depozita | S29: 372265.01
B32: TOTALI | F32: =+F28+F25+F21 -> 0 | G32: =+G28+G25+G21 -> 0 | H32: =+H28+H25+H21 -> 0 | I32: =+I28+I25+I21 -> 0 | J32: =+J28+J25+J21 -> 0 | K32: =+K28+K25+K21 -> 0 | L32: =+L28+L25+L21 -> 0 | M32: =+M28+M25+M21 -> 0 | ... AH32: =+AH28+AH25+AH21 -> 0
B33: Ndryshim likujditeti | F33: =+F32 -> 0 | G33: =+G32-F32 -> 0 | H33: =+H32-G32 -> 0 | I33: =+I32-H32 -> 0 | J33: =+J32-I32 -> 0 | K33: =+K32-J32 -> 0 | L33: =+L32-K32 -> 0 | M33: =+M32-L32 -> 0 | N33: =+N32-M32 -> 0 | ... AF33: =+AF32-AE32 -> -3323750
B38: ANALIZA
C39: 1989 | D39: 1990 | E39: 1991 | F39: 1992 | G39: 1993 | H39: 1994 | I39: 1995 | J39: 1996 | K39: 1997 | L39: 1998 | M39: 1999 | N39: 2000 | O39: 2001 | P39: 2002 | Q39: 2003 | R39: 2004 | S39: 2005 | T39: 2006 | U39: 2007 | V39: 2008 | W39: 2009 | X39: 2010 | Y39: 2011 | Z39: 2012 | AA39: Mars 2013
B40: Pasurite | C40: =+C42 -> 0 | D40: =+D42 -> 0 | E40: =+E42 -> 0 | F40: =+F42 -> 0 | G40: =+G42 -> 0 | H40: =+H42 -> 0 | I40: =+I42 -> 0 | J40: =+J42 -> 0 | ... T40: =+T42 -> 0 | U40: =SUM(U41:U42) -> 15557600 | V40: =+V42 -> -7844379.6 | W40: =+W42 -> -0.0365 | X40: =+X42 -> -458620.32 | Y40: =+Y42 -> 0 | Z40: =+Z42 -> 13525 | AA40: =+AA42 -> 8697.54
B41: =+#REF! -> #REF! | U41: 7254600
B42: Ndryshim likujditeti | C42: 0 | D42: 0 | E42: 0 | F42: 0 | G42: 0 | H42: 0 | I42: 0 | J42: 0 | K42: 0 | L42: 0 | M42: 0 | N42: 0 | O42: 0 | P42: 0 | Q42: 0 | R42: 0 | S42: 0 | T42: 0 | U42: =+S33 -> 8303000 | V42: =+T33 -> -7844379.6 | W42: =+U33 -> -0.0365 | X42: =+V33 -> -458620.32 | Y42: =+W33 -> 0 | Z42: =+X33 -> 13525 | AA42: =+Y33 -> 8697.54
B43: Te ardhura | C43: =+C44+C45+C46 -> 22066.328 | D43: =+D44+D45+D46 -> 66198.984 | E43: =+E44+E45+E46 -> 66198.984 | F43: =+F44+F45+F46 -> 66198.984 | G43: =+G44+G45+G46 -> 83433.027 | H43: =+H44+H45+H46 -> 80541.589 | I43: =+I44+I45+I46 -> 76043.984 | J43: =+J44+J45+J46 -> 73026.666 | ... AA43: =+AA44+AA45+AA46 -> 103054.05
B44: pagat e Hamide Sharra | C44: =+E11 -> 0 | D44: =+F11 -> 0 | E44: =+G11 -> 0 | F44: =+H11 -> 0 | G44: =+I11 -> 17234.043 | H44: =+J11 -> 14342.605 | I44: =+K11 -> 9845 | J44: =+L11 -> 6827.6818 | ... AA44: =+AC11 -> 29354.308
B45: pagat e Sinan Sharra | C45: =+E16 -> 22066.328 | D45: =+F16 -> 66198.984 | E45: =+G16 -> 66198.984 | F45: =+H16 -> 66198.984 | G45: =+I16 -> 66198.984 | H45: =+J16 -> 66198.984 | I45: =+K16 -> 66198.984 | J45: =+L16 -> 66198.984 | ... AA45: =+AC16 -> 73699.746
B46: Te ardhura nga interesi I depozitave | U46: 372265.01
B47: Shpenzime jetike | C47: =+C43*0.66 -> 14563.776 | D47: =+D43*0.66 -> 43691.329 | E47: =+E43*0.66 -> 43691.329 | F47: =+F43*0.66 -> 43691.329 | G47: =+G43*0.66 -> 55065.798 | H47: =+H43*0.66 -> 53157.449 | I47: =+I43*0.66 -> 50189.029 | J47: =+J43*0.66 -> 48197.599 | ... M47: =+M43*0.66 -> 53235.861 | N47: 216000 | O47: 216000 | P47: 187788 | Q47: 187928 | R47: 187928 | S47: 219114 | T47: 219114 | U47: 273240 | V47: 273240 | W47: 273240 | X47: 273240 | Y47: 273240 | Z47: 279096 | AA47: =279096/12*3 -> 69774
B48: Mundesi kursimi | C48: =+C43-C40-C47 -> 7502.5515 | D48: =+D43-D40-D47 -> 22507.655 | E48: =+E43-E40-E47 -> 22507.655 | F48: =+F43-F40-F47 -> 22507.655 | G48: =+G43-G40-G47 -> 28367.229 | H48: =+H43-H40-H47 -> 27384.14 | I48: =+I43-I40-I47 -> 25854.955 | J48: =+J43-J40-J47 -> 24829.066 | ... AA48: =+AA43-AA40-AA47 -> 24582.514

Sheet TIMS
B2: Vitet | C2: 2008 | D2: 2009 | E2: 2010 | F2: 2011 | G2: 2012 | H2: 2013 | I2: 2014 | J2: 2015 | K2: 2016 | L2: tot | M2: dv | N2: 2017 | O2: 2018 | P2: 2019 | Q2: 2020
B3: Shpenzimet Eur | C3: =+H24 -> 30 | D3: =+H23 -> 0 | E3: 0 | F3: =+H22+H21 -> 2450 | G3: =+H40 -> 0 | H3: =+H20 -> 2800 | I3: =+H19 -> 1000 | J3: =+H37 -> 270 | K3: =+H36 -> 200 | M3: =+H15 -> 60 | N3: =+H15 -> 60 | O3: =+H55+H56+H57+H70 -> 465 | P3: =+H14+H13 -> 580
B4: Kursi | C4: =+KK!R4 -> 123.1825 | D4: =+KK!S4 -> 137.17 | E4: =+KK!T4 -> 138.81 | F4: =+KK!U4 -> 138.3 | G4: =+KK!V4 -> 139.72 | H4: =+KK!W4 -> 140.21 | I4: =+KK!X4 -> 140.11 | J4: =+KK!Y4 -> 137.65 | K4: =+KK!Z4 -> 135.27 | M4: =+KK!AA4 -> 132.95 | N4: =+KK!AA4 -> 132.95 | O4: =+KK!AB4 -> 123.42 | P4: =+KK!AC4 -> 121.77
B5: Lek | K5: 4000
B6: Shpenzimet LEK | C6: =+C3*C4+C5 -> 3695.475 | D6: =+D3*D4+D5 -> 0 | E6: =+E3*E4+E5 -> 0 | F6: =+F3*F4+F5 -> 338835 | G6: =+G3*G4+G5 -> 0 | H6: =+H3*H4+H5 -> 392588 | I6: =+I3*I4+I5 -> 140110 | J6: =+J3*J4+J5 -> 37165.5 | K6: =+K3*K4+K5 -> 31054 | L6: =SUM(C6:K6) -> 943447.97 | M6: =+M3*M4+M5 -> 7977 | N6: =+N3*N4+N5 -> 7977 | O6: =+O3*O4+O5 -> 57390.3 | P6: =+P3*P4+P5 -> 70626.6 | Q6: =+Q3*Q4+Q5 -> 0
B9: Daljet | J9: Hyrjet
B10: Nr. dokumentit | C10: Data e daljes | D10: Linja | E10: Kalimi kufitar | F10: Targa | G10: Dite Qendrimi | H10: Koment | I10: Nr. dokumentit | J10: Data e hyrjes | K10: Linja | L10: Kalimi kufitar | M10: Targa | N10: SR Deklaron | O10: pagesa | Q10: distanca | R10: nafte | S10: karton jeshil | T10: Kosto udhetimi | U10: Nete qendrimi | V10: Kosto qendrimi | W10: TOTAL
A12: Arben | B12: 035883962-AL | C12: 11.09.2020 09:04 | D12: X AUTOVETURE | E12: PIKA KUFITARE MORINA | F12: AA600OE | I12: 035883962-AL | J12: 11.09.2020 15:04 | K12: X AUTOVETURE | L12: PIKA KUFITARE MORINA | M12: AA600OE
A13: Arben | B13: BG0155044-AL | C13: 28.11.2019 09:23 | D13: X AUTOBUS | E13: PIKA KUFITARE KAPSHTICË | G13: 3 | H13: 330 | I13: BG0155044-AL | J13: 30.11.2019 18:08 | K13: X AUTOBUS | L13: PIKA KUFITARE KAKAVIJË | N13: Selanik Greqi kam udhetuar me bashkeshortetn dhe vajzen per nje vizite 3 ditore Me Autobus | O13: shpenzim per 3 persona 330Euor 89 Euro per person | P13: Vertetim Matias Travel and Tours dt 26.12.2019
A14: Arben | B14: BG0155044-AL | C14: 26.01.2019 08:55 | D14: X AUTOVETURE | E14: PIKA KUFITARE HANI I HOTIT | F14: AA600OE | G14: 1 | H14: 250 | I14: BG0155044-AL | J14: 27.01.2019 13:46 | K14: X AUTOVETURE | L14: PIKA KUFITARE HANI I HOTIT | M14: AA011JN | N14: Podgorice Mal I zi kam udhetuar me familjen time per vizite turistike dhe kam qendruar ne podgorice | O14: shpenzime ne total per 4 persona 250 Euro 55 euro per person | P14: Vertetim Global Tours
A15: Arben | B15: BG0155044-AL | C15: 21.01.2017 08:44 | D15: X AUTOVETURE | E15: PIKA KUFITARE MORINA | F15: AA600OE | G15: 1 | H15: 60 | I15: BG0155044-AL | J15: 21.01.2017 16:35 | K15: X AUTOVETURE | L15: PIKA KUFITARE MORINA | M15: AA600OE | N15: Prizren Kosove kam udhetuar me familjen time per vizite turistike nje ditore dhe jam kthyer po ate dite ne tirane | O15: shpenzime total per 4 persona 60 eruo
A16: Arben | B16: BG0155044-AL | C16: 18.08.2016 09:34 | D16: SARANDE-KORFUZ - RENA | E16: PIKA KUFITARE PORTI I SARANDËS | G16: 1 | H16: 160 | I16: BG0155044-AL | J16: 18.08.2016 18:42 | K16: SARANDE-KORFUZ - RENA | L16: PIKA KUFITARE PORTI I SARANDËS | N16: Korfuz Greqi kam udhetuar bashke me familjen per vizite 1 ditore me anije dhe jam kthyer ne Sarande | O16: udhetimi nje ditor me anije per 4 persona 160 euro
A17: Arben | B17: DG0155044-AL | C17: 03.07.2016 08:31 | D17: X AUTOVETURE | E17: PIKA KUFITARE QAFË MORINI | G17: 0 | H17: 0 | I17: BG0155044-AL | J17: 03.07.2016 11:26 | K17: X AUTOVETURE | L17: PIKA KUFITARE MORINA | M17: AA600OE | N17: Tropoje Valbone Shqiperi vizite turistike me familjen | O17: 0
A18: Arben | B18: BG0155044-AL | C18: 02.07.2016 09:50 | D18: X AUTOVETURE | E18: PIKA KUFITARE MORINA | G18: 1 | H18: 4000 | I18: BG0155044-AL | J18: 02.07.2016 11:12 | K18: X AUTOVETURE | L18: PIKA KUFITARE QAFË MORINI | M18: AA600OE | N18: Tropoje Valbone Shqiperi vizite turistike me familjen | O18: fjetja ne bujtinat e zones (1000 Lek+ mengjesi) totali 4,000 leke
A19: Arben | B19: BG0155044-AL | C19: 21.11.2014 03:38 | D19: ALITALIA - Xhenova 512-513 | E19: KOMISARIATI POLICISË RINAS | G19: 3 | H19: 1000 | I19: BG0155044-AL | J19: 23.11.2014 16:19 | K19: ALITALIA - AZ 506/511 MILANO | L19: KOMISARIATI POLICISË RINAS | N19: Genova Milano Itali kam udhetuar me familjen per pushime 3 net | O19: Shpenzime Bileta avioni per 4 persona 626 Euro Qendrimi ne Savona 1 nate 90 Eur/ Wendrimi ne Milano 1 nate 160Euro Shpenzime ne total 1000 Euro | P19: Vertetim Coral Travel and Tours dt 26.12.2019
A20: Arben | B20: BG0155044-AL | C20: 14.07.2013 01:45 | D20: CHARTER | E20: KOMISARIATI POLICISË RINAS | G20: 7 | H20: 2800 | I20: BG0155044-AL | J20: 20.07.2013 23:36 | K20: BELLEAIR - GENOVA LBY 101 | L20: KOMISARIATI POLICISË RINAS | N20: Antalia Turqi kam udhetuar me familjen per pushime verore | O20: Shpenzime ne Hotel 2800 Euro | P20: Vertetim Sava Tours dt 26.12.2019
A21: Arben | B21: BG0155044-AL | C21: 25.06.2011 05:47 | D21: CHARTER | E21: KOMISARIATI POLICISË RINAS | G21: 7 | H21: 2450 | I21: BG0155044-AL | J21: 02.07.2011 12:15 | K21: CHARTER | L21: KOMISARIATI POLICISË RINAS | N21: Antalia Turqi kam udhetuar me familjen per pushime verore | O21: Shpenzime ne Hotel Kamelya Holliday Village 2450 Euro | P21: Cosmos tours dt 26.12.2019
A22: Arben | B22: BG0155044-AL | C22: 23.01.2011 12:01 | D22: ALITALIA - AZ 510/507 ROME | E22: KOMISARIATI POLICISË RINAS | G22: 7 | I22: BG0155044-AL | J22: 29.01.2011 12:05 | K22: ALITALIA - AZ 510/507 ROME | L22: KOMISARIATI POLICISË RINAS | N22: Udhetim ne Rome trajnim nje javor I paguar nga prokuroria e pergjithshsme | P22: Program Vizite leshuar nga Prokuroria e Pergjithshme Dt.07.01.2011 Urdheri nr 09/1 date 18.01.2011
A23: Arben | B23: Z2185856-AL | C23: 17.03.2009 07:21 | D23: X AUTOVETURE | E23: PIKA KUFITARE QAFA E THANËS | F23: TR1551R | G23: 0 | I23: Z2185856-AL | J23: 17.03.2009 08:37 | K23: X AUTOVETURE | L23: PIKA KUFITARE BLLADË | N23: Tranzit per te shkuar drejt dibres ku isha Prokuror
A24: Arben | B24: Z2185856-AL | C24: 27.06.2008 13:14 | D24: X AUTOVETURE | E24: PIKA KUFITARE MURRIQAN | F24: TR1704L | G24: 1 | H24: 30 | I24: Z2185856-AL | J24: 28.06.2008 13:42 | K24: X AUTOVETURE | L24: PIKA KUFITARE MURRIQAN | M24: TR1704L | N24: Budva Mal I Zi kam udhetuar me dy kolege per vizite turistike | O24: 30 Euro akomodimi eshte bere ne nje ap te zones dhe shpenzimet jabe paguar ne 3 pjese te barabarta per te gjithe
B28: 035371685-AL | C28: 11.09.2020 09:04 | D28: X AUTOVETURE | E28: PIKA KUFITARE MORINA | F28: AA600OE | I28: 035371685-AL | J28: 11.09.2020 15:05 | K28: X AUTOVETURE | L28: PIKA KUFITARE MORINA | M28: AA600OE
B29: BG0155073-AL | C29: 28.11.2019 09:23 | D29: X AUTOBUS | E29: PIKA KUFITARE KAPSHTICË | I29: BG0155073-AL | J29: 30.11.2019 18:07 | K29: X AUTOBUS | L29: PIKA KUFITARE KAKAVIJË
B30: BG0155073-AL | C30: 26.01.2019 08:55 | D30: X AUTOVETURE | E30: PIKA KUFITARE HANI I HOTIT | F30: AA600OE | I30: BG0155073-AL | J30: 27.01.2019 13:46 | K30: X AUTOVETURE | L30: PIKA KUFITARE HANI I HOTIT | M30: AA011JN
B31: BG0155073-AL | C31: 21.01.2017 08:44 | D31: X AUTOVETURE | E31: PIKA KUFITARE MORINA | F31: AA600OE | I31: BG0155073-AL | J31: 21.01.2017 16:36 | K31: X AUTOVETURE | L31: PIKA KUFITARE MORINA | M31: AA600OE
B32: BG0155073-AL | C32: 04.11.2016 16:47 | D32: X AUTOVETURE | E32: PIKA KUFITARE QAFË MORINI | F32: AA141MP | I32: BG0155073-AL | J32: 04.11.2016 20:05 | K32: X AUTOVETURE | L32: PIKA KUFITARE MORINA | M32: AA141MP
B33: BG0155073-AL | C33: 18.08.2016 09:35 | D33: SARANDE-KORFUZ - RENA | E33: PIKA KUFITARE PORTI I SARANDËS | I33: 024442986-AL | J33: 03.11.2016 13:14 | K33: X AUTOBUS | L33: PIKA KUFITARE QAFË MORINI | M33: AA118IC
B34: BG0155073-AL | C34: 03.07.2016 08:30 | D34: X AUTOVETURE | E34: PIKA KUFITARE QAFË MORINI | I34: BG0155073-AL | J34: 18.08.2016 18:43 | K34: SARANDE-KORFUZ - RENA | L34: PIKA KUFITARE PORTI I SARANDËS
B35: BG0155073-AL | C35: 02.07.2016 09:50 | D35: X AUTOVETURE | E35: PIKA KUFITARE MORINA | I35: BG0155073-AL | J35: 02.07.2016 11:14 | K35: X AUTOVETURE | L35: PIKA KUFITARE QAFË MORINI | M35: AA600OE
B36: BG0155073-AL | C36: 26.03.2016 09:37 | D36: X AUTOBUS | E36: PIKA KUFITARE KAPSHTICË | F36: AA300MR | G36: 2 | H36: 200 | J36: 28.03.2016 | N36: Selanik Greqi udhetim 3 ditor me auotbus bashke me vajzen per vizite turistike | O36: Shpenzime ne total 200 euro (79 Euro paketa per 1 person all inclusive) | P36: Vertetim Trevis and Tours dt 26.12.2019
B37: BG0155073-AL | C37: 05.06.2015 09:57 | D37: X AUTOBUS | E37: PIKA KUFITARE HANI I HOTIT | F37: AA577KS | G37: 2 | H37: 270 | I37: BG0155073-AL | J37: 07.06.2015 21:54 | K37: X AUTOBUS | L37: PIKA KUFITARE MURRIQAN | M37: AA577KS | N37: Bosnje Hercegovina udheti 3 ditor me vajzen vizite turistike | O37: shpenzime ne total 270Euro (118 Euro paketa per 1 person all inclusive) | P37: Vertetim Trevis and Tours dt 26.12.2020
B38: BG0155073-AL | C38: 21.11.2014 03:37 | D38: ALITALIA - Xhenova 512-513 | E38: KOMISARIATI POLICISË RINAS | I38: BG0155073-AL | J38: 23.11.2014 16:19 | K38: ALITALIA - AZ 506/511 MILANO | L38: KOMISARIATI POLICISË RINAS
B39: BG0155073-AL | C39: 14.07.2013 01:46 | D39: CHARTER | E39: KOMISARIATI POLICISË RINAS | I39: BG0155073-AL | J39: 20.07.2013 23:36 | K39: BELLEAIR - GENOVA LBY 101 | L39: KOMISARIATI POLICISË RINAS
B40: 024442986-AL | C40: 19.04.2012 13:05 | D40: X AUTOVETURE | E40: PIKA KUFITARE MORINA | J40: 19.04.2012 | N40: prizren kosove inspekti ne drejtorine rajonale te ISSH ne KUKES kthimi brenda dites ne tirane
B41: BG0155073-AL | C41: 25.06.2011 05:47 | D41: CHARTER | E41: KOMISARIATI POLICISË RINAS | I41: BG0155073-AL | J41: 02.07.2011 12:15 | K41: CHARTER | L41: KOMISARIATI POLICISË RINAS
B46: 035883910-AL | C46: 15.01.2022 10:41 | D46: X AUTOVETURE | E46: PIKA KUFITARE MORINA | F46: AA319US | I46: BD1686562-AL | J46: 22.08.2021 15:10 | K46: X AUTOVETURE | L46: PIKA KUFITARE KAPSHTICË
B47: BD1686562-AL | C47: 13.08.2021 04:41 | D47: X AUTOVETURE | E47: PIKA KUFITARE KAKAVIJË | F47: AA319US | I47: 035883910-AL | J47: 22.05.2021 17:16 | K47: X AUTOVETURE | L47: PIKA KUFITARE MORINA | M47: AA319US
B48: 035883910-AL | C48: 15.05.2021 17:00 | D48: X AUTOVETURE | E48: PIKA KUFITARE MORINA | F48: TR7953KK | I48: 035883910-AL | J48: 21.03.2021 20:33 | K48: X AUTOVETURE | L48: PIKA KUFITARE MORINA | M48: AA289NH
B49: 035883910-AL | C49: 19.03.2021 22:20 | D49: X AUTOVETURE | E49: PIKA KUFITARE MORINA | F49: TR7953K | I49: 035883910-AL | J49: 06.12.2020 08:56 | K49: X AUTOVETURE | L49: PIKA KUFITARE MORINA | M49: AA289NH
B50: 035883910-AL | C50: 02.12.2020 14:57 | D50: X AUTOVETURE | E50: PIKA KUFITARE MORINA | F50: AA289NH | I50: 035883910-AL | J50: 11.10.2020 18:32 | K50: X AUTOVETURE | L50: PIKA KUFITARE MORINA | M50: TR7953K
B51: 035883910-AL | C51: 12.09.2020 15:17 | D51: X AUTOVETURE | E51: PIKA KUFITARE MORINA | F51: TR7953K | I51: 035883910-AL | J51: 13.09.2020 18:50 | K51: X AUTOVETURE | L51: PIKA KUFITARE MORINA | M51: TR7953K
B52: 035883910-AL | C52: 11.09.2020 09:04 | D52: X AUTOVETURE | E52: PIKA KUFITARE MORINA | F52: AA600OE | I52: 035883910-AL | J52: 11.09.2020 15:05 | K52: X AUTOVETURE | L52: PIKA KUFITARE MORINA | M52: AA600OE
B53: BC0949269-AL | C53: 28.11.2019 09:23 | D53: X AUTOBUS | E53: PIKA KUFITARE KAPSHTICË | I53: BC0949269-AL | J53: 30.11.2019 18:08 | K53: X AUTOBUS | L53: PIKA KUFITARE KAKAVIJË
B54: BC0949269-AL | C54: 26.01.2019 08:55 | D54: X AUTOVETURE | E54: PIKA KUFITARE HANI I HOTIT | F54: AA600OE | I54: BC0949269-AL | J54: 27.01.2019 13:44 | K54: X AUTOVETURE | L54: PIKA KUFITARE HANI I HOTIT | M54: AA600OE
B55: BC0949269-AL | C55: 15.11.2018 14:32 | D55: X FUGON | E55: PIKA KUFITARE MURRIQAN | F55: AA328RP | G55: 2 | H55: 85 | I55: BC0949269-AL | J55: 17.11.2018 13:13 | K55: X AUTOBUS | L55: PIKA KUFITARE MURRIQAN | M55: AA328RP | N55: Ulqin Mal I zi Ersa Sharra udhetim | O55: Shpenzime totale85 euro | P55: Vertetim nga Shkolla Elite nr prot 167 Tirane 17.01.2020
B56: BC0949269-AL | C56: 22.05.2018 13:29 | D56: X AUTOBUS | E56: PIKA KUFITARE MURRIQAN | F56: ULAE795 | G56: 2 | H56: 85 | I56: BC0949269-AL | J56: 24.05.2018 14:40 | K56: X FUGON | L56: PIKA KUFITARE MURRIQAN | M56: ULAE795 | N56: Ulqin Mal I zi Ersa Sharra udhetim | O56: Shpenzime totale85 euro
B57: BC0949269-AL | C57: 21.01.2018 11:34 | D57: X AUTOBUS | E57: PIKA KUFITARE QAFA E THANËS | G57: 3 | H57: 175 | I57: BC0949269-AL | J57: 24.01.2018 14:21 | K57: X AUTOBUS | L57: PIKA KUFITARE QAFA E THANËS | N57: Tetove Maqedoni Ersa Sharra udhetim | O57: Shpenzime totale 175 euro
B58: BC0949269-AL | C58: 18.08.2016 09:36 | D58: SARANDE-KORFUZ - RENA | E58: PIKA KUFITARE PORTI I SARANDËS | I58: BC0949269-AL | J58: 18.08.2016 18:43 | K58: SARANDE-KORFUZ - RENA | L58: PIKA KUFITARE PORTI I SARANDËS
B59: BC0949269-AL | C59: 03.07.2016 08:30 | D59: X AUTOVETURE | E59: PIKA KUFITARE QAFË MORINI | I59: BC0949269-AL | J59: 02.07.2016 11:14 | K59: X AUTOVETURE | L59: PIKA KUFITARE QAFË MORINI | M59: AA600OE
B60: BC0949269-AL | C60: 02.07.2016 09:50 | D60: X AUTOVETURE | E60: PIKA KUFITARE MORINA | I60: BG0155060-AL | J60: 07.06.2015 21:54 | K60: X AUTOBUS | L60: PIKA KUFITARE MURRIQAN | M60: AA577KS
B61: BC0949269-AL | C61: 26.03.2016 09:46 | D61: X AUTOBUS | E61: PIKA KUFITARE KAPSHTICË | F61: AA300MR | I61: BG0155060-AL | J61: 23.11.2014 16:19 | K61: ALITALIA - AZ 506/511 MILANO | L61: KOMISARIATI POLICISË RINAS
B62: BG0155060-AL | C62: 05.06.2015 09:57 | D62: X AUTOBUS | E62: PIKA KUFITARE HANI I HOTIT | F62: AA577KS | I62: BG0155060-AL | J62: 20.07.2013 23:36 | K62: BELLEAIR - GENOVA LBY 101 | L62: KOMISARIATI POLICISË RINAS
B63: BG0155060-AL | C63: 21.11.2014 03:38 | D63: ALITALIA - Xhenova 512-513 | E63: KOMISARIATI POLICISË RINAS
B64: BG0155060-AL | C64: 14.07.2013 01:46 | D64: CHARTER | E64: KOMISARIATI POLICISË RINAS | I64: BG0155060-AL | J64: 02.07.2011 12:14 | K64: CHARTER | L64: KOMISARIATI POLICISË RINAS
B65: BG0155060-AL | C65: 25.06.2011 05:47 | D65: CHARTER | E65: KOMISARIATI POLICISË RINAS
B69: BA0971222-AL | C69: 26.01.2019 08:54 | D69: X AUTOVETURE | E69: PIKA KUFITARE HANI I HOTIT | F69: AA600OE | I69: BA0971222-AL | J69: 27.01.2019 13:43 | K69: X AUTOVETURE | L69: PIKA KUFITARE HANI I HOTIT | M69: AA600OE
B70: BA0971222-AL | C70: 05.01.2018 10:46 | D70: X AUTOBUS | E70: PIKA KUFITARE HANI I HOTIT | F70: AA982OS | G70: 2 | H70: 120 | I70: BA0971222-AL | J70: 07.01.2018 16:48 | K70: X AUTOBUS | L70: PIKA KUFITARE MURRIQAN | M70: AA982OC | N70: Podgorice Mak I Zi Ene Sharra udhetim turistik | O70: Shpenzime total 120 Euro (99 Euro oakete turistike ) | P70: Vertetim nga Matias Travel & Tours dt 26.12.2019
B71: BA0971222-AL | C71: 21.01.2017 08:44 | D71: X AUTOVETURE | E71: PIKA KUFITARE MORINA | F71: AA600OE | I71: BA0971222-AL | J71: 21.01.2017 16:37 | K71: X AUTOVETURE | L71: PIKA KUFITARE MORINA | M71: AA600OE
B72: BA0971222-AL | C72: 18.08.2016 09:35 | D72: SARANDE-KORFUZ - RENA | E72: PIKA KUFITARE PORTI I SARANDËS | I72: BA0971222-AL | J72: 18.08.2016 18:42 | K72: SARANDE-KORFUZ - RENA | L72: PIKA KUFITARE PORTI I SARANDËS
B73: BA0971222-AL | C73: 03.07.2016 08:29 | D73: X AUTOVETURE | E73: PIKA KUFITARE QAFË MORINI | I73: BA0971222-AL | J73: 03.07.2016 11:26 | K73: X AUTOVETURE | L73: PIKA KUFITARE MORINA | M73: AA600OE
B74: BA0971222-AL | C74: 02.07.2016 09:50 | D74: X AUTOVETURE | E74: PIKA KUFITARE MORINA | I74: BG0155057-AL | J74: 23.11.2014 16:18 | K74: ALITALIA - AZ 506/511 MILANO | L74: KOMISARIATI POLICISË RINAS
B75: BG0155057-AL | C75: 21.11.2014 03:37 | D75: ALITALIA - Xhenova 512-513 | E75: KOMISARIATI POLICISË RINAS | I75: BG0155057-AL | J75: 20.07.2013 23:35 | K75: BELLEAIR - GENOVA LBY 101 | L75: KOMISARIATI POLICISË RINAS
B76: BG0155057-AL | C76: 14.07.2013 01:45 | D76: CHARTER | E76: KOMISARIATI POLICISË RINAS | I76: BG0155057-AL | J76: 02.07.2011 12:14 | K76: CHARTER | L76: KOMISARIATI POLICISË RINAS
B77: BG0155057-AL | C77: 25.06.2011 05:48 | D77: CHARTER | E77: KOMISARIATI POLICISË RINAS

Sheet E.Islamaj
B2: Shenime referuese TIMS sipas vendimit KPA date 22.05.2019 subjekti Edmond Islamaj
B4: Shpenzime transporti AJROR | C4: Vlera në Euro/Dollarë | E4: Shpenzime transporti DETAR | F4: Vlera në Euro
B5: Udhëtime BRENDA kontinentit europian | E5: Bilete trageti vetem nje drejtim (te rritur dhe femije) | F5: 50
B6: Bileta vajtje/ardhje per linja Direkte - te rritur +12 vjeç | C6: 180 | E6: Bilete trageti vetem nje drejtim (automjeti) | F6: 60
B7: Bileta vajtje/ardhje per linja Direkte - femije 2 - 12 vjeç | C7: 135
B8: Bileta vajtje/ardhje per linja Direkte - foshnja 0 - 2 vjeç | C8: 18 | E8: Çmimi mesatar mujor i naftës për litër (në euro)
E9: MUAJI/VITI | F9: 2005 | G9: 2006 | H9: 2007 | I9: 2008 | J9: 2009 | K9: 2010 | L9: 2011 | M9: 2012 | N9: 2013 | O9: 2014 | P9: 2015 | Q9: 2016
B10: Bileta vajtje/ardhje per linja Tranzit - te rritur +12 vjeç | C10: 250 | E10: 1. Janar | F10: 0.932 | G10: 1.074 | H10: 1.032 | I10: 1.201 | J10: 0.973 | K10: 1.09 | L10: 1.302 | M10: 1.472 | N10: 1.47 | O10: 1.423 | P10: 1.193 | Q10: 1.065
B11: Bileta vajtje/ardhje per linja Tranzit - femije 2 - 12 vjeç | C11: 187.5 | E11: 2. Shkurt | F11: 0.94 | G11: 1.076 | H11: 1.035 | I11: 1.208 | J11: 0.972 | K11: 1.086 | L11: 1.338 | M11: 1.49 | N11: 1.483 | O11: 1.422 | P11: 1.228 | Q11: 1.039
B12: Bileta vajtje/ardhje per linja Tranzit - foshnja 0 - 2 vjeç | C12: 25 | E12: 3. Mars | F12: 0.98 | G12: 1.085 | H12: 1.053 | I12: 1.257 | J12: 0.944 | K12: 1.131 | L12: 1.384 | M12: 1.519 | N12: 1.47 | O12: 1.408 | P12: 1.281 | Q12: 1.076
E13: 4. Prill | F13: 1.014 | G13: 1.108 | H13: 1.081 | I13: 1.285 | J13: 0.973 | K13: 1.182 | L13: 1.398 | M13: 1.515 | N13: 1.437 | O13: 1.412 | P13: 1.29 | Q13: 1.086
B14: Udhëtime JASHTë kontinentit europian | E14: 5. Maj | F14: 0.999 | G14: 1.127 | H14: 1.088 | I14: 1.375 | J14: 0.982 | K14: 1.191 | L14: 1.372 | M14: 1.485 | N14: 1.419 | O14: 1.414 | P14: 1.312 | Q14: 1.133
B15: Bileta vajtje/ardhje te rritur +12 vjeç | C15: 600 | E15: 6. Qershor | F15: 1.034 | G15: 1.117 | H15: 1.101 | I15: 1.435 | J15: 1.024 | K15: 1.197 | L15: 1.36 | M15: 1.437 | N15: 1.42 | O15: 1.421 | P15: 1.303 | Q15: 1.163
B16: Bileta vajtje/ardhje per linja Direkte - femije 2 - 12 vjeç | C16: 450 | E16: 7. Korrik | F16: 1.063 | G16: 1.131 | H16: 1.112 | I16: 1.443 | J16: 1.017 | K16: 1.178 | L16: 1.364 | M16: 1.459 | N16: 1.437 | O16: 1.419 | P16: 1.277 | Q16: 1.143
B17: Bileta vajtje/ardhje per linja Direkte - foshnja 0 - 2 vjeç | C17: 60 | E17: 8. Gusht | F17: 1.075 | G17: 1.137 | H17: 1.109 | I17: 1.362 | J17: 1.049 | K17: 1.178 | L17: 1.364 | M17: 1.526 | N17: 1.446 | O17: 1.41 | P17: 1.212 | Q17: 1.122
E18: 9. Shtator | F18: 1.114 | G18: 1.097 | H18: 1.124 | I18: 1.316 | J18: 1.027 | K18: 1.179 | L18: 1.371 | M18: 1.532 | N18: 1.465 | O18: 1.407 | P18: 1.187 | Q18: 1.137
B19: Paketa turistike - udhëtime jashtë vendit me "Charter" | E19: 10. Tetor | F19: 1.122 | G19: 1.059 | H19: 1.146 | I19: 1.234 | J19: 1.03 | K19: 1.186 | L19: 1.387 | M19: 1.518 | N19: 1.436 | O19: 1.374 | P19: 1.177 | Q19: 1.162
B20: Bileta vajtje/ardhje te rritur +12 vjeç | C20: 100 | E20: 11. Nëntor | F20: 1.07 | G20: 1.049 | H20: 1.215 | I20: 1.134 | J20: 1.055 | K20: 1.209 | L20: 1.414 | M20: 1.493 | N20: 1.421 | O20: 1.347 | P20: 1.18 | Q20: 1.164
B21: Bileta vajtje/ardhje per linja Direkte - femije 0 - 12 vjeç | C21: 0 | E21: 12. Dhjetor | F21: 1.051 | G21: 1.054 | H21: 1.223 | I21: 1.038 | J21: 1.047 | K21: 1.252 | L21: 1.422 | M21: 1.472 | N21: 1.434 | O21: 1.209 | P21: 1.145 | Q21: 1.201
E22: TOTAL | F22: 1.032 | G22: 1.094 | H22: 1.108 | I22: 1.283 | J22: 1.008 | K22: 1.17 | L22: 1.37 | M22: 1.494 | N22: 1.445 | O22: 1.399 | P22: 1.236 | Q22: 1.123
B23: Shpenzime qendrimi te rritur +12 vjeç | C23: 50 | E23: Burimi: https://ec.europa.eu/energy/en/data-analysis/weekly-oil-bulletin
B24: Shpenzime qendrimi femije 0 - 12 vjeç | C24: 0
B28: Shpenzime transporti TOKESOR | E28: Shpenzime QENDRIMI | F28: Vlera në Euro/Dollare
B29: Shp udhetimi = distanca ne km * konsum karburanti* çmim mesatar /liter + karton jeshil | E29: Shpenzime te rritur +18 vjeç | F29: 50
E30: Shpenzime femije 5 - 18 vjeç | F30: 25
B31: Konsum karburanti = 7 litra/100 km | E31: Shpenzime femije 0 - 5 vjeç | F31: 15
B33: Cmimi mesatar/liter sipas tabeles
B35: Karton jeshil
B36: Destinacioni Kosovë = 0 euro
B37: Destinacioni Mal i Zi = 15 euro
B38: Destinacioni vende të tjera = 40 euro
B41: Pika doganore | C41: Destinacioni më i afërt
B42: Qafë Thanë | C42: Strugë, Maqedoni
B43: Tushemisht | C43: Ohër, Maqedoni
B44: Kakavijë | C44: Janinë, Greqi
B45: Kapshticë | C45: Kostur, Greqi
B46: Qafë Botë | C46: Igumenicë, Greqi
B47: Morinë, Qafë Morinë | C47: Prizren, Kosove
B48: Murriqan | C48: Ulqin, Mal i Zi
B49: Hani i Hotit | C49: Podgoricë, Mal i Zi

Sheet Sheet2
